Workbook
Name CF_AdminMode: '(Options)'!$B$11
Name CF_AllocateFirstRoleEffortsToOtherRoles: '(Options)'!$B$7
Name CF_Currency: '(Options)'!$B$3
Name CF_FTEdays: '(Options)'!$B$8
Name CF_IncludeInflation: '(Options)'!$B$5
Name CF_LinkManual: '(Options)'!$B$13
Name CF_LinkManualGerman: '(Options)'!$B$14
Name CF_LinkTeams: '(Options)'!$B$16
Name CF_ManualTableOfContents: '(Options)'!$B$15
Name CF_NoPriorSortedTasksGANTT: '(Options)'!$B$6
Name CF_TimePeriodType: '(Options)'!$B$4
Name CO_FirstRow: 'Other costs'!$A$5
Name CO_HeaderAssumptions: 'Other costs'!$C$4
Name CO_HeaderCosts: 'Other costs'!$D$4
Name CO_HeaderDescr: 'Other costs'!$B$4
Name CO_HeaderHandlingFee: 'Other costs'!#REF!
Name CO_HeaderID: 'Other costs'!$A$4
Name CO_HeaderPrice: 'Other costs'!$E$4
Name CO_LastRow: 'Other costs'!$A$36
Name FT_ChangedFeatureTasks: Features!$E$2
Name FT_EstimationMethod: Features!$G$3
Name FT_FirstRow: Features!$A$10
Name FT_HeaderAssumptions: Features!$H$8
Name FT_HeaderDescription: Features!$G$8
Name FT_HeaderEffort: Features!$Q$8
Name FT_HeaderFeature: Features!$E$8
Name FT_HeaderGroup: Features!$C$8
Name FT_HeaderPos: Features!$A$8
Name FT_HeaderRangeQuery: Features!$B$8
Name FT_HeaderRefID: Features!$J$8
Name FT_HeaderRisks: Features!$I$8
Name FT_HeaderStoryPoints: Features!$M$8
Name FT_HeaderSubFeature: Features!$F$8
Name FT_HeaderSubGroup: Features!$D$8
Name FT_HeaderThreeEfforts: Features!$N$8:$P$8
Name FT_HeaderTShirtSizes: Features!$L$8
Name FT_IndividualAveragePercentage: Features!$R$3:$AA$3
Name FT_InputAssistanceMethod: Features!$G$4
Name FT_KeyTaskFlags: Features!$R$5:$AA$5
Name FT_LastRow: Features!$A$56
Name FT_MethodCols: Features!$L$7:$P$7
Name FT_Tasks: Features!$R$8:$AA$8
Name FT_TotalEffort: Features!$Q$9
Name GC_HeaderDependency: 'Chart | GANTT'!$G$4
Name GC_HeaderDuration: 'Chart | GANTT'!$F$4
Name GC_HeaderFinish: 'Chart | GANTT'!$H$4
Name GC_HeaderFirstPeriod: 'Chart | GANTT'!$I$4
Name GC_HeaderID: 'Chart | GANTT'!$C$4
Name GC_HeaderStart: 'Chart | GANTT'!$E$4
Name GC_HeaderSummaryTask: 'Chart | GANTT'!$B$4
Name GC_HeaderTask: 'Chart | GANTT'!$D$4
Name GC_HeaderTaskGroup: 'Chart | GANTT'!$A$4
Name GT_Efforts: 'Project tasks'!#REF!
Name GT_EffortsRisks: 'Project tasks'!$W$75:$AZ$75
Name GT_EffortsTravelTime: 'Project tasks'!$W$73:$AZ$73
Name GT_EffortsWarranty: 'Project tasks'!$W$74:$AZ$74
Name GT_EffortsWithoutWAAndTTAndRisks: 'Project tasks'!$W$77:$AZ$77
Name GT_EffortWithoutWAAndTTAndRisks: 'Project tasks'!$J$77
Name GT_FinishDateGANTT: 'Project tasks'!$Q$70
Name GT_FirstRow: 'Project tasks'!$A$12

Sheet Start
A1: adesso calculator | B1: Manual: see menu item above "Show manual" or click this hyperlink
A2: =B17 | B2: Excel Macros are deactivated and you can't see the menu group above "adesso calculator"? In this case you have to configure the workbook security settings - please have a look at the manual!
A3: Tool version: | B3: 2.01 / 28.03.2025
A4: Last change in this document: | B4: =MAX(tblHistoryOfChanges[Date of change])
B5: see details in sheet "History of changes"
A6: Basic settings
B7: Advanced settings: see menu item above "Edit options"
A8: Proposal title: | B8: Locarno Film Festival - Drupal CMS 2.0 Relaunch
A9: Contract type: | B9: Work contract (fixed price)
A10: Customer: | B10: Locarno Film Festival
A11: Contractor (offering company): | B11: adesso Schweiz AG
A12: Accounting-related company: | B12: 2025-01
B13: Drupal 11 with Drupal CMS 2.0
A14: Calculation template: | B14: general_dev_de
B15: Please use menu above "Import" -> "Import from internal template" if you want to change the template.
A16: Calculation process: | B16: Calculation with two teams
A17: Current step of process: | B17: Preparation
B18: Not sure which process you should choose? Please have a look at the manual!
A19: adesso calculation team
A21: Please use the tabulator key in the last column of the last row for adding a new row.
A22: Team member | B22: Team member role in proposal process

Sheet Features
Q1: =SUM(R1:AA1)
A2: Features (Requirements/Deliverables) | E2: yes | G2: Use these options for calculating efforts. Please have a look at the manual! | Q2: Discuss the percentages with your team!
A3: =Start!A2 | F3: Estimation method: | G3: No specific method | Q3: Forecasted percentages: | R3: 0.25 | S3: 0.5 | T3: 0.15 | U3: 0.1 | V3: 0 | W3: 0 | X3: 0 | Y3: 0 | Z3: 0 | AA3: 0 | AB3: =SUM(FT_IndividualAveragePercentage)
F4: Input assistance for task values: | G4: No assistance | Q4: Actual percentages: | R4: =IFERROR(R9/$Q$9,0) | S4: =IFERROR(S9/$Q$9,0) | T4: =IFERROR(T9/$Q$9,0) | U4: =IFERROR(U9/$Q$9,0) | V4: =IFERROR(V9/$Q$9,0) | W4: =IFERROR(W9/$Q$9,0) | X4: =IFERROR(X9/$Q$9,0) | Y4: =IFERROR(Y9/$Q$9,0) | ... AA4: =IFERROR(AA9/$Q$9,0) | AB4: =SUM(FT_IndividualAveragePercentage)
Q5: Key task (for assistance): | R5: no | S5: yes | T5: no | U5: no | V5: no | W5: no | X5: no | Y5: no | Z5: no | AA5: no
B6: Use this column for special feature queries | D6: Feature group and sub group columns | I6: Use the menu above | R6: Use menu above "Edit feature task" for adding, renaming or reordering feature tasks.
B7: project task sheet. | D7: are optional! | I7: for adding or deleting risks! | L7: T-shirt sizing | M7: Planning poker | N7: Three-point estimation | O7: Three-point estimation | P7: Three-point estimation | R7: FT#1 | S7: FT#2 | T7: FT#3 | U7: FT#4 | V7: FT#5 | W7: FT#6 | X7: FT#7 | Y7: FT#8 | Z7: FT#9 | AA7: FT#10
A8: F-1 | B8: Homepage | C8: Website entry point with hero, featured content | D8: H | E8: 40 | F8: Sub feature title | G8: (Sub-)Feature description | H8: Assumptions | I8: Risks | J8: Ref. ID | L8: T-shirt size | M8: Story points | N8: Optimistic effort | O8: Realistic effort | P8: Pessimistic effort | Q8: Effort total | R8: Analyse & Software Design | S8: Software-entwicklung | T8: Softwaretest | U8: Fehlerbearb. nach BzA
A9: F-2 | B9: Film Program Page | C9: Dynamic festival program with filters | D9: H | E9: 60 | N9: =SUBTOTAL(9,N10:N10012) | O9: =SUBTOTAL(9,O10:O10012) | P9: =SUBTOTAL(9,P10:P10012) | Q9: =SUBTOTAL(9,Q10:Q10012) | R9: =SUBTOTAL(9,R10:R10012) | S9: =SUBTOTAL(9,S10:S10012) | T9: =SUBTOTAL(9,T10:T10012) | U9: =SUBTOTAL(9,U10:U10012) | ... AA9: =SUBTOTAL(9,AA10:AA10012)
A10: F-3 | B10: Film Archive | C10: Historical film database with search | D10: H | E10: 50
A11: F-4 | B11: Film Detail Page | C11: Individual film presentation | D11: M | E11: 30 | Q11: =SUM(R11:AA11)
A12: F-5 | B12: News & Updates | C12: News listing and detail pages | D12: M | E12: 25 | Q12: =SUM(R12:AA12)
A13: F-6 | B13: Event Landing Page | C13: Festival events and schedule | D13: M | E13: 35 | Q13: =SUM(R13:AA13)
A14: F-7 | B14: Press & Media | C14: Press releases and media kit | D14: L | E14: 20 | Q14: =SUM(R14:AA14)
A15: F-8 | B15: Partner & Sponsor | C15: Partner listings and logos | D15: L | E15: 15 | Q15: =SUM(R15:AA15)
A16: F-9 | B16: About Festival | C16: History, mission, team pages | D16: M | E16: 25 | Q16: =SUM(R16:AA16)
A17: F-10 | B17: Industry Section | C17: Professional accreditation area | D17: H | E17: 45 | Q17: =SUM(R17:AA17)
A18: F-11 | B18: Educational Programs | C18: Workshops and masterclasses | D18: M | E18: 30 | Q18: =SUM(R18:AA18)
A19: F-12 | B19: Venue Information | C19: Theater locations and facilities | D19: L | E19: 18 | Q19: =SUM(R19:AA19)
A20: F-13 | B20: Ticketing Integration | C20: Ticket purchase and booking | D20: H | E20: 55 | Q20: =SUM(R20:AA20)
A21: F-14 | B21: User Profile (Keycloak SSO) | C21: User account and preferences | D21: H | E21: 40 | Q21: =SUM(R21:AA21)
A22: F-15 | B22: VOD Streaming Pages | C22: Sony VOD integration | D22: H | E22: 50 | Q22: =SUM(R22:AA22)
... A55: F-48 | B55: Icon Feature List | C55: Feature highlights | D55: L | E55: 6 | Q55: =SUM(R55:AA55)
A56: F-49 | B56: Before/After Slider | C56: Image comparison | D56: M | E56: 10
A57: F-50 | B57: Custom HTML Block | C57: Flexible HTML content | D57: L | E57: 4
A58: F-51 | B58: Divider/Spacer | C58: Visual separators | D58: L | E58: 2
A59: F-52 | B59: Anchor Links | C59: In-page navigation | D59: L | E59: 4

Sheet Project tasks
J1: 0 | K1: no | N1: {=IFERROR(calcDefaultValueOfProjectTask(M1),"error")} | V1: =IF(J1<>"",IFERROR(J1-SUM(W1:AZ1),0),"")
A2: Project tasks (Work breakdown structure) | L2: Forecasted project length: | M2: 20 | N2: =(GT_FinishDateGANTT-GT_StartDateGANTT)/7 | W2: =IFERROR(W11/(GT_ProjectLength/52*CF_FTEdays),0) | X2: =IFERROR(X11/(GT_ProjectLength/52*CF_FTEdays),0) | Y2: =IFERROR(Y11/(GT_ProjectLength/52*CF_FTEdays),0) | Z2: =IFERROR(Z11/(GT_ProjectLength/52*CF_FTEdays),0) | AA2: =IFERROR(AA11/(GT_ProjectLength/52*CF_FTEdays),0) | AB2: =IFERROR(AB11/(GT_ProjectLength/52*CF_FTEdays),0) | AC2: =IFERROR(AC11/(GT_ProjectLength/52*CF_FTEdays),0) | AD2: =IFERROR(AD11/(GT_ProjectLength/52*CF_FTEdays),0) | ... AZ2: =IFERROR(AZ11/(GT_ProjectLength/52*CF_FTEdays),0) | BA2: =SUM(GT_ProjectRolesFTE)
W3: 1 | X3: 2 | Y3: 3 | Z3: 4 | AA3: 5 | AB3: 6 | AC3: 7 | AD3: 8 | AE3: 9 | AF3: 10 | AG3: 11 | AH3: 12 | AI3: 13 | AJ3: 14 | AK3: 15 | AL3: 16 | AM3: 17 | AN3: 18 | AO3: 19 | AP3: 20 | AQ3: 21 | AR3: 22 | AS3: 23 | AT3: 24 | AU3: 25 | AV3: 26 | AW3: 27 | AX3: 28 | AY3: 29 | AZ3: 30
W4: 1 | X4: 2 | Y4: 3 | Z4: 4 | AA4: 5 | AB4: 6 | AC4: 7 | AD4: 8 | AE4: 9
A5: =Start!A2 | L5: Forecasted team size: | M5: 0 | N5: =BA2 | V5: Use menu item above "Edit project roles" for adding, renaming or rearranging project roles. Red color = error! | W5: Any role | X5: Project manager | Y5: Software architect | Z5: Requirement Engineer | AA5: UI/UX Designer | AB5: Test manager | AC5: Test Engineer | AD5: Developer | AE5: DevOps Engineer
L6: Forecasted num of iterations: | M6: 0 | N6: e.g. sprints or releases
I7: Red color = error! | M7: Please update these values if you use the variables [#projectlength], [#teamsize], [#iterations] or [#sprints] in your formulas.
A8: T-1 | B8: Setup & Kickoff | C8: Project kickoff meeting and planning | D8: PM | E8: 8 | G8: Use menu above für special feature query! | H8: Use menu above for adding or deleting risks! | I8: Feature effort (FT): | J8: =SUMIFS($J:$J,$G:$G,"FT*") | L8: You only need these columns to use formulas. | P8: You only need these columns to create a GANTT chart and for a time period-related cost and capacity calculation. Please have a look at the manual!
A9: T-2 | B9: Setup & Kickoff | C9: DDEV local dev environment setup | D9: Backend | E9: 4
A10: T-3 | B10: Setup & Kickoff | C10: Azure infrastructure provisioning | D10: DevOps | E10: 16 | F10: Assumptions | G10: Special task or feature query | H10: Risks | I10: Ref. ID | J10: Effort | K10: Use formula? | L10: Variable | M10: Formula | N10: Result of formula | P10: Start | Q10: Finish | R10: Duration | S10: Dependency | T10: Show in GANTT? | V10: Not allocated effort
A11: T-4 | B11: Setup & Kickoff | C11: CI/CD pipeline configuration | D11: DevOps | E11: 12 | J11: =SUBTOTAL(9,J12:J69) | P11: =MIN(P12:P69) | Q11: =MAX(Q12:Q69) | R11: =Q11-P11 | V11: =SUBTOTAL(9,V12:V69) | W11: =SUBTOTAL(9,W12:W69) | X11: =SUBTOTAL(9,X12:X69) | Y11: =SUBTOTAL(9,Y12:Y69) | Z11: =SUBTOTAL(9,Z12:Z69) | AA11: =SUBTOTAL(9,AA12:AA69) | AB11: =SUBTOTAL(9,AB12:AB69) | AC11: =SUBTOTAL(9,AC12:AC69) | ... AZ11: =SUBTOTAL(9,AZ12:AZ69)
A12: T-5 | B12: Setup & Kickoff | C12: Git repository and branching strategy | D12: Backend | E12: 4 | J12: Use key "f" for formula | M12: For experts only! See manual!
A13: T-6 | B13: Content Architecture | C13: Content type modeling (17 types) | D13: Backend | E13: 40 | J13: 0 | K13: no | N13: {=IFERROR(calcDefaultValueOfProjectTask(M13),"error")} | T13: no | V13: =IF(J13<>"",IFERROR(J13-SUM(W13:AZ13),0),"") | X13: =100%*$J$13
A14: T-7 | B14: Content Architecture | C14: Paragraph component development (35 types) | D14: Backend | E14: 80 | J14: 0 | K14: no | N14: {=IFERROR(calcDefaultValueOfProjectTask(M14),"error")} | T14: no | V14: =IF(J14<>"",IFERROR(J14-SUM(W14:AZ14),0),"") | X14: =100%*$J$14
A15: T-8 | B15: Content Architecture | C15: Taxonomy vocabularies setup | D15: Backend | E15: 12 | J15: 0 | K15: no | N15: {=IFERROR(calcDefaultValueOfProjectTask(M15),"error")} | T15: no | V15: =IF(J15<>"",IFERROR(J15-SUM(W15:AZ15),0),"") | Y15: =100%*$J$15
A16: T-9 | B16: Content Architecture | C16: Views and listing pages | D16: Backend | E16: 30 | J16: 0 | K16: no | N16: {=IFERROR(calcDefaultValueOfProjectTask(M16),"error")} | T16: no | V16: =IF(J16<>"",IFERROR(J16-SUM(W16:AZ16),0),"") | AB16: =100%*$J$16
A17: T-10 | B17: Content Architecture | C17: Custom fields and field formatters | D17: Backend | E17: 20 | J17: 0 | K17: no | N17: {=IFERROR(calcDefaultValueOfProjectTask(M17),"error")} | T17: no | V17: =IF(J17<>"",IFERROR(J17-SUM(W17:AZ17),0),"")
A18: T-11 | B18: Frontend & Theming | C18: Mercury Theme setup | D18: Frontend | E18: 8 | J18: 0 | K18: no | N18: {=IFERROR(calcDefaultValueOfProjectTask(M18),"error")} | T18: no | V18: =IF(J18<>"",IFERROR(J18-SUM(W18:AZ18),0),"") | AE18: =100%*$J$18
A19: T-12 | B19: Frontend & Theming | C19: Storybook component development | D19: Frontend | E19: 60 | J19: 0 | K19: no | N19: {=IFERROR(calcDefaultValueOfProjectTask(M19),"error")} | T19: no | V19: =IF(J19<>"",IFERROR(J19-SUM(W19:AZ19),0),"")
A20: T-13 | B20: Frontend & Theming | C20: Tailwind CSS configuration | D20: Frontend | E20: 12 | G20: FT#1 | J20: =Features!R9 | L20: [design] | N20: {=IFERROR(calcDefaultValueOfProjectTask(M20),"error")} | T20: no | V20: =IF(J20<>"",IFERROR(J20-SUM(W20:AZ20),0),"") | Y20: =20%*$J$20 | Z20: =80%*$J$20
A21: T-14 | B21: Frontend & Theming | C21: Responsive design implementation | D21: Frontend | E21: 40 | G21: FT#2 | J21: =Features!S9 | L21: [dev] | N21: {=IFERROR(calcDefaultValueOfProjectTask(M21),"error")} | T21: no | V21: =IF(J21<>"",IFERROR(J21-SUM(W21:AZ21),0),"") | AD21: =100%*$J$21
A22: T-15 | B22: Frontend & Theming | C22: Accessibility (WCAG 2.1 AA) | D22: Frontend | E22: 24 | G22: FT#3 | J22: =Features!T9 | L22: [test] | N22: {=IFERROR(calcDefaultValueOfProjectTask(M22),"error")} | T22: no | V22: =IF(J22<>"",IFERROR(J22-SUM(W22:AZ22),0),"") | AC22: =100%*$J$22
A23: T-16 | B23: Integrations | C23: Keycloak oAuth2 SSO integration | D23: Backend | E23: 40 | J23: 0 | K23: no | N23: {=IFERROR(calcDefaultValueOfProjectTask(M23),"error")} | T23: no | V23: =IF(J23<>"",IFERROR(J23-SUM(W23:AZ23),0),"") | AB23: =20%*$J$23 | AC23: =80%*$J$23
A24: T-17 | B24: Integrations | C24: Fiona Festival API integration | D24: Backend | E24: 60 | J24: 0 | K24: no | N24: {=IFERROR(calcDefaultValueOfProjectTask(M24),"error")} | T24: no | V24: =IF(J24<>"",IFERROR(J24-SUM(W24:AZ24),0),"") | Y24: =20%*$J$24 | AE24: =80%*$J$24
A25: T-18 | B25: Integrations | C25: Sony VOD DRM streaming | D25: Backend | E25: 50 | J25: 0 | K25: no | N25: {=IFERROR(calcDefaultValueOfProjectTask(M25),"error")} | T25: no | V25: =IF(J25<>"",IFERROR(J25-SUM(W25:AZ25),0),"") | Y25: =20%*$J$25 | AE25: =80%*$J$25
A26: T-19 | B26: Integrations | C26: Mobile App REST API | D26: Backend | E26: 35 | J26: 0 | K26: no | N26: {=IFERROR(calcDefaultValueOfProjectTask(M26),"error")} | T26: no | V26: =IF(J26<>"",IFERROR(J26-SUM(W26:AZ26),0),"") | Z26: =100%*$J$26
A27: T-20 | B27: Integrations | C27: Solr Enterprise Search setup | D27: Backend | E27: 40 | J27: 0 | K27: no | N27: {=IFERROR(calcDefaultValueOfProjectTask(M27),"error")} | T27: no | V27: =IF(J27<>"",IFERROR(J27-SUM(W27:AZ27),0),"") | Z27: =100%*$J$27
A28: T-21 | B28: Integrations | C28: CloudFront CDN configuration | D28: DevOps | E28: 16 | G28: FT#4 | J28: =Features!U9 | L28: [bugfix] | N28: {=IFERROR(calcDefaultValueOfProjectTask(M28),"error")} | T28: no | V28: =IF(J28<>"",IFERROR(J28-SUM(W28:AZ28),0),"") | AC28: =20%*$J$28 | AD28: =80%*$J$28
A29: T-22 | B29: Migration | C29: Content migration scripts | D29: Backend | E29: 40 | J29: 0 | K29: no | N29: {=IFERROR(calcDefaultValueOfProjectTask(M29),"error")} | T29: no | V29: =IF(J29<>"",IFERROR(J29-SUM(W29:AZ29),0),"") | Z29: =50%*$J$29 | AD29: =50%*$J$29
A30: T-23 | B30: Migration | C30: Asset migration (images/videos) | D30: Backend | E30: 20 | J30: 0 | K30: no | N30: {=IFERROR(calcDefaultValueOfProjectTask(M30),"error")} | T30: no | V30: =IF(J30<>"",IFERROR(J30-SUM(W30:AZ30),0),"") | AE30: =100%*$J$30
A31: T-24 | B31: Migration | C31: User account migration | D31: Backend | E31: 16 | J31: 0 | K31: no | N31: {=IFERROR(calcDefaultValueOfProjectTask(M31),"error")} | T31: no | V31: =IF(J31<>"",IFERROR(J31-SUM(W31:AZ31),0),"")
A32: T-25 | B32: Migration | C32: URL redirects (301) | D32: Backend | E32: 12 | J32: 0 | K32: no | N32: {=IFERROR(calcDefaultValueOfProjectTask(M32),"error")} | T32: no | V32: =IF(J32<>"",IFERROR(J32-SUM(W32:AZ32),0),"")
A33: T-26 | B33: Migration | C33: Data validation and cleanup | D33: Backend | E33: 20 | J33: 0 | K33: no | N33: {=IFERROR(calcDefaultValueOfProjectTask(M33),"error")} | T33: no | V33: =IF(J33<>"",IFERROR(J33-SUM(W33:AZ33),0),"")
A34: T-27 | B34: Testing & QA | C34: Unit test development | D34: QA | E34: 30 | J34: 0 | K34: yes | M34: max([#projectlength]*ifs([#total1]<200,0.5,[#total1]<500,1,[#total1]<1000,1.5,[#total1]<2000,2,true,3),10%*[#total1]) | N34: {=IFERROR(calcDefaultValueOfProjectTask(M34),"error")} | T34: no | V34: =IF(J34<>"",IFERROR(J34-SUM(W34:AZ34),0),"") | X34: =100%*$J$34
A35: T-28 | B35: Testing & QA | C35: Integration testing | D35: QA | E35: 25 | J35: 0 | K35: no | N35: {=IFERROR(calcDefaultValueOfProjectTask(M35),"error")} | T35: no | V35: =IF(J35<>"",IFERROR(J35-SUM(W35:AZ35),0),"") | AB35: =100%*$J$35
A36: T-29 | B36: Testing & QA | C36: E2E testing (Playwright) | D36: QA | E36: 30 | J36: 0 | K36: no | N36: {=IFERROR(calcDefaultValueOfProjectTask(M36),"error")} | T36: no | V36: =IF(J36<>"",IFERROR(J36-SUM(W36:AZ36),0),"") | Y36: =100%*$J$36
A37: T-30 | B37: Testing & QA | C37: Performance testing | D37: QA | E37: 16 | J37: 0 | K37: no | N37: {=IFERROR(calcDefaultValueOfProjectTask(M37),"error")} | T37: no | V37: =IF(J37<>"",IFERROR(J37-SUM(W37:AZ37),0),"") | AE37: =100%*$J$37
A38: T-31 | B38: Testing & QA | C38: Security audit | D38: QA | E38: 16 | J38: 0 | K38: no | N38: {=IFERROR(calcDefaultValueOfProjectTask(M38),"error")} | T38: no | V38: =IF(J38<>"",IFERROR(J38-SUM(W38:AZ38),0),"") | X38: =100%*$J$38
A39: T-32 | B39: Testing & QA | C39: UAT coordination | D39: PM | E39: 12 | J39: 0 | K39: no | N39: {=IFERROR(calcDefaultValueOfProjectTask(M39),"error")} | T39: no | V39: =IF(J39<>"",IFERROR(J39-SUM(W39:AZ39),0),"") | W39: =100%*$J$39
A40: T-33 | B40: Deployment | C40: Staging deployment | D40: DevOps | E40: 8 | G40: TT | J40: 0 | K40: no | L40: [traveltime] | N40: {=IFERROR(calcDefaultValueOfProjectTask(M40),"error")} | T40: no | V40: =IF(J40<>"",IFERROR(J40-SUM(W40:AZ40),0),"") | W40: =100%*$J$40
A41: T-34 | B41: Deployment | C41: Production deployment | D41: DevOps | E41: 12 | G41: RIS | J41: =RI_WeightedImpact | L41: [risks] | N41: {=IFERROR(calcDefaultValueOfProjectTask(M41),"error")} | T41: no | V41: =IF(J41<>"",IFERROR(J41-SUM(W41:AZ41),0),"") | W41: =100%*$J$41
A42: T-35 | B42: Deployment | C42: DNS and SSL configuration | D42: DevOps | E42: 6 | G42: WA | J42: 0 | K42: yes | L42: [warranty] | M42: 10%*[#total1] | N42: {=IFERROR(calcDefaultValueOfProjectTask(M42),"error")} | T42: no | V42: =IF(J42<>"",IFERROR(J42-SUM(W42:AZ42),0),"") | W42: =100%*$J$42
A43: T-36 | B43: Deployment | C43: Monitoring setup (Azure Monitor) | D43: DevOps | E43: 10 | N43: {=IFERROR(calcDefaultValueOfProjectTask(M43),"error")} | V43: =IF(J43<>"",IFERROR(J43-SUM(W43:AZ43),0),"")
A44: T-37 | B44: Deployment | C44: Backup strategy implementation | D44: DevOps | E44: 8 | N44: {=IFERROR(calcDefaultValueOfProjectTask(M44),"error")} | V44: =IF(J44<>"",IFERROR(J44-SUM(W44:AZ44),0),"")
A45: T-38 | B45: Project Management | C45: Weekly status meetings | D45: PM | E45: 40 | N45: {=IFERROR(calcDefaultValueOfProjectTask(M45),"error")} | V45: =IF(J45<>"",IFERROR(J45-SUM(W45:AZ45),0),"")
A46: T-39 | B46: Project Management | C46: Documentation and handover | D46: PM | E46: 24 | N46: {=IFERROR(calcDefaultValueOfProjectTask(M46),"error")} | V46: =IF(J46<>"",IFERROR(J46-SUM(W46:AZ46),0),"")
N47: {=IFERROR(calcDefaultValueOfProjectTask(M47),"error")} | V47: =IF(J47<>"",IFERROR(J47-SUM(W47:AZ47),0),"")
N48: {=IFERROR(calcDefaultValueOfProjectTask(M48),"error")} | V48: =IF(J48<>"",IFERROR(J48-SUM(W48:AZ48),0),"")
N49: {=IFERROR(calcDefaultValueOfProjectTask(M49),"error")} | V49: =IF(J49<>"",IFERROR(J49-SUM(W49:AZ49),0),"")
N50: {=IFERROR(calcDefaultValueOfProjectTask(M50),"error")} | V50: =IF(J50<>"",IFERROR(J50-SUM(W50:AZ50),0),"")
N51: {=IFERROR(calcDefaultValueOfProjectTask(M51),"error")} | V51: =IF(J51<>"",IFERROR(J51-SUM(W51:AZ51),0),"")
N52: {=IFERROR(calcDefaultValueOfProjectTask(M52),"error")} | V52: =IF(J52<>"",IFERROR(J52-SUM(W52:AZ52),0),"")
N53: {=IFERROR(calcDefaultValueOfProjectTask(M53),"error")} | V53: =IF(J53<>"",IFERROR(J53-SUM(W53:AZ53),0),"")
N54: {=IFERROR(calcDefaultValueOfProjectTask(M54),"error")} | V54: =IF(J54<>"",IFERROR(J54-SUM(W54:AZ54),0),"")
N55: {=IFERROR(calcDefaultValueOfProjectTask(M55),"error")} | V55: =IF(J55<>"",IFERROR(J55-SUM(W55:AZ55),0),"")
N56: {=IFERROR(calcDefaultValueOfProjectTask(M56),"error")} | V56: =IF(J56<>"",IFERROR(J56-SUM(W56:AZ56),0),"")
N57: {=IFERROR(calcDefaultValueOfProjectTask(M57),"error")} | V57: =IF(J57<>"",IFERROR(J57-SUM(W57:AZ57),0),"")
N58: {=IFERROR(calcDefaultValueOfProjectTask(M58),"error")} | V58: =IF(J58<>"",IFERROR(J58-SUM(W58:AZ58),0),"")
... N68: {=IFERROR(calcDefaultValueOfProjectTask(M68),"error")} | V68: =IF(J68<>"",IFERROR(J68-SUM(W68:AZ68),0),"")
A69: Last row. Don't override this row. Please insert new rows before this row! Don't insert or delete rows manually! Only use the menu items above "Insert row" and "Delete row" or short keys CTRL+ or CTRL-.
P70: =_xlfn.MINIFS(P12:P69,T12:T69,"yes") | Q70: =_xlfn.MAXIFS(Q12:Q69,T12:T69,"yes") | W70: Use short characters: f[<percent>] = full effort, r[<percent>] = remaining effort, c<value> = constant effort, =<formula> = own formula
I71: Feature effort (FT): | J71: =SUMIFS($J:$J,$G:$G,"FT*") | M71: Special variables:
I73: Travel time (TT): | J73: =SUMIFS($J:$J,$G:$G,"TT") | M73: [#total1] = Total effort without warranty and travel time and risks (days) | V73: =IFERROR(J73/N5/GT_ProjectLength,0) | W73: =SUMIFS(W:W,$G:$G,"TT") | X73: =SUMIFS(X:X,$G:$G,"TT") | Y73: =SUMIFS(Y:Y,$G:$G,"TT") | Z73: =SUMIFS(Z:Z,$G:$G,"TT") | AA73: =SUMIFS(AA:AA,$G:$G,"TT") | AB73: =SUMIFS(AB:AB,$G:$G,"TT") | AC73: =SUMIFS(AC:AC,$G:$G,"TT") | AD73: =SUMIFS(AD:AD,$G:$G,"TT") | AE73: =SUMIFS(AE:AE,$G:$G,"TT") | AF73: =SUMIFS(AF:AF,$G:$G,"TT") | AG73: =SUMIFS(AG:AG,$G:$G,"TT") | AH73: =SUMIFS(AH:AH,$G:$G,"TT") | AI73: =SUMIFS(AI:AI,$G:$G,"TT") | AJ73: =SUMIFS(AJ:AJ,$G:$G,"TT") | AK73: =SUMIFS(AK:AK,$G:$G,"TT") | AL73: =SUMIFS(AL:AL,$G:$G,"TT") | AM73: =SUMIFS(AM:AM,$G:$G,"TT") | AN73: =SUMIFS(AN:AN,$G:$G,"TT") | AO73: =SUMIFS(AO:AO,$G:$G,"TT") | AP73: =SUMIFS(AP:AP,$G:$G,"TT") | AQ73: =SUMIFS(AQ:AQ,$G:$G,"TT") | AR73: =SUMIFS(AR:AR,$G:$G,"TT") | AS73: =SUMIFS(AS:AS,$G:$G,"TT") | AT73: =SUMIFS(AT:AT,$G:$G,"TT") | AU73: =SUMIFS(AU:AU,$G:$G,"TT") | AV73: =SUMIFS(AV:AV,$G:$G,"TT") | AW73: =SUMIFS(AW:AW,$G:$G,"TT") | AX73: =SUMIFS(AX:AX,$G:$G,"TT") | AY73: =SUMIFS(AY:AY,$G:$G,"TT") | AZ73: =SUMIFS(AZ:AZ,$G:$G,"TT")
I74: Warranty (WA): | J74: =SUMIFS($J:$J,$G:$G,"WA") | M74: [#total2] = Total effort (days) | W74: =SUMIFS(W:W,$G:$G,"WA") | X74: =SUMIFS(X:X,$G:$G,"WA") | Y74: =SUMIFS(Y:Y,$G:$G,"WA") | Z74: =SUMIFS(Z:Z,$G:$G,"WA") | AA74: =SUMIFS(AA:AA,$G:$G,"WA") | AB74: =SUMIFS(AB:AB,$G:$G,"WA") | AC74: =SUMIFS(AC:AC,$G:$G,"WA") | AD74: =SUMIFS(AD:AD,$G:$G,"WA") | AE74: =SUMIFS(AE:AE,$G:$G,"WA") | AF74: =SUMIFS(AF:AF,$G:$G,"WA") | AG74: =SUMIFS(AG:AG,$G:$G,"WA") | AH74: =SUMIFS(AH:AH,$G:$G,"WA") | AI74: =SUMIFS(AI:AI,$G:$G,"WA") | AJ74: =SUMIFS(AJ:AJ,$G:$G,"WA") | AK74: =SUMIFS(AK:AK,$G:$G,"WA") | AL74: =SUMIFS(AL:AL,$G:$G,"WA") | AM74: =SUMIFS(AM:AM,$G:$G,"WA") | AN74: =SUMIFS(AN:AN,$G:$G,"WA") | AO74: =SUMIFS(AO:AO,$G:$G,"WA") | AP74: =SUMIFS(AP:AP,$G:$G,"WA") | AQ74: =SUMIFS(AQ:AQ,$G:$G,"WA") | AR74: =SUMIFS(AR:AR,$G:$G,"WA") | AS74: =SUMIFS(AS:AS,$G:$G,"WA") | AT74: =SUMIFS(AT:AT,$G:$G,"WA") | AU74: =SUMIFS(AU:AU,$G:$G,"WA") | AV74: =SUMIFS(AV:AV,$G:$G,"WA") | AW74: =SUMIFS(AW:AW,$G:$G,"WA") | AX74: =SUMIFS(AX:AX,$G:$G,"WA") | AY74: =SUMIFS(AY:AY,$G:$G,"WA") | AZ74: =SUMIFS(AZ:AZ,$G:$G,"WA")
I75: Risks (RIS): | J75: =SUMIFS($J:$J,$G:$G,"RIS") | M75: [#projectlength] = Projekt length (weeks) | W75: =SUMIFS(W:W,$G:$G,"RIS") | X75: =SUMIFS(X:X,$G:$G,"RIS") | Y75: =SUMIFS(Y:Y,$G:$G,"RIS") | Z75: =SUMIFS(Z:Z,$G:$G,"RIS") | AA75: =SUMIFS(AA:AA,$G:$G,"RIS") | AB75: =SUMIFS(AB:AB,$G:$G,"RIS") | AC75: =SUMIFS(AC:AC,$G:$G,"RIS") | AD75: =SUMIFS(AD:AD,$G:$G,"RIS") | AE75: =SUMIFS(AE:AE,$G:$G,"RIS") | AF75: =SUMIFS(AF:AF,$G:$G,"RIS") | AG75: =SUMIFS(AG:AG,$G:$G,"RIS") | AH75: =SUMIFS(AH:AH,$G:$G,"RIS") | AI75: =SUMIFS(AI:AI,$G:$G,"RIS") | AJ75: =SUMIFS(AJ:AJ,$G:$G,"RIS") | AK75: =SUMIFS(AK:AK,$G:$G,"RIS") | AL75: =SUMIFS(AL:AL,$G:$G,"RIS") | AM75: =SUMIFS(AM:AM,$G:$G,"RIS") | AN75: =SUMIFS(AN:AN,$G:$G,"RIS") | AO75: =SUMIFS(AO:AO,$G:$G,"RIS") | AP75: =SUMIFS(AP:AP,$G:$G,"RIS") | AQ75: =SUMIFS(AQ:AQ,$G:$G,"RIS") | AR75: =SUMIFS(AR:AR,$G:$G,"RIS") | AS75: =SUMIFS(AS:AS,$G:$G,"RIS") | AT75: =SUMIFS(AT:AT,$G:$G,"RIS") | AU75: =SUMIFS(AU:AU,$G:$G,"RIS") | AV75: =SUMIFS(AV:AV,$G:$G,"RIS") | AW75: =SUMIFS(AW:AW,$G:$G,"RIS") | AX75: =SUMIFS(AX:AX,$G:$G,"RIS") | AY75: =SUMIFS(AY:AY,$G:$G,"RIS") | AZ75: =SUMIFS(AZ:AZ,$G:$G,"RIS")
I76: Customer tasks (CUS): | J76: =SUMIFS($J:$J,$G:$G,"CUS") | M76: [#teamsize] = Team size (FTE) | W76: =SUMIFS(W:W,$G:$G,"CUS") | X76: =SUMIFS(X:X,$G:$G,"CUS") | Y76: =SUMIFS(Y:Y,$G:$G,"CUS") | Z76: =SUMIFS(Z:Z,$G:$G,"CUS") | AA76: =SUMIFS(AA:AA,$G:$G,"CUS") | AB76: =SUMIFS(AB:AB,$G:$G,"CUS") | AC76: =SUMIFS(AC:AC,$G:$G,"CUS") | AD76: =SUMIFS(AD:AD,$G:$G,"CUS") | AE76: =SUMIFS(AE:AE,$G:$G,"CUS") | AF76: =SUMIFS(AF:AF,$G:$G,"CUS") | AG76: =SUMIFS(AG:AG,$G:$G,"CUS") | AH76: =SUMIFS(AH:AH,$G:$G,"CUS") | AI76: =SUMIFS(AI:AI,$G:$G,"CUS") | AJ76: =SUMIFS(AJ:AJ,$G:$G,"CUS") | AK76: =SUMIFS(AK:AK,$G:$G,"CUS") | AL76: =SUMIFS(AL:AL,$G:$G,"CUS") | AM76: =SUMIFS(AM:AM,$G:$G,"CUS") | AN76: =SUMIFS(AN:AN,$G:$G,"CUS") | AO76: =SUMIFS(AO:AO,$G:$G,"CUS") | AP76: =SUMIFS(AP:AP,$G:$G,"CUS") | AQ76: =SUMIFS(AQ:AQ,$G:$G,"CUS") | AR76: =SUMIFS(AR:AR,$G:$G,"CUS") | AS76: =SUMIFS(AS:AS,$G:$G,"CUS") | AT76: =SUMIFS(AT:AT,$G:$G,"CUS") | AU76: =SUMIFS(AU:AU,$G:$G,"CUS") | AV76: =SUMIFS(AV:AV,$G:$G,"CUS") | AW76: =SUMIFS(AW:AW,$G:$G,"CUS") | AX76: =SUMIFS(AX:AX,$G:$G,"CUS") | AY76: =SUMIFS(AY:AY,$G:$G,"CUS") | AZ76: =SUMIFS(AZ:AZ,$G:$G,"CUS")
I77: Effort without warranty, travel time and risks: | J77: =J11-J73-J74-J75-J76 | M77: [#sprints] = Number of sprints | W77: =W11-W73-W74-W75-W76 | X77: =X11-X73-X74-X75-X76 | Y77: =Y11-Y73-Y74-Y75-Y76 | Z77: =Z11-Z73-Z74-Z75-Z76 | AA77: =AA11-AA73-AA74-AA75-AA76 | AB77: =AB11-AB73-AB74-AB75-AB76 | AC77: =AC11-AC73-AC74-AC75-AC76 | AD77: =AD11-AD73-AD74-AD75-AD76 | ... AZ77: =AZ11-AZ73-AZ74-AZ75-AZ76
I78: Optional tasks (OPT): | J78: =SUMIFS($J:$J,$G:$G,"OPT") | W78: =SUMIFS(W:W,$G:$G,"OPT") | X78: =SUMIFS(X:X,$G:$G,"OPT") | Y78: =SUMIFS(Y:Y,$G:$G,"OPT") | Z78: =SUMIFS(Z:Z,$G:$G,"OPT") | AA78: =SUMIFS(AA:AA,$G:$G,"OPT") | AB78: =SUMIFS(AB:AB,$G:$G,"OPT") | AC78: =SUMIFS(AC:AC,$G:$G,"OPT") | AD78: =SUMIFS(AD:AD,$G:$G,"OPT") | AE78: =SUMIFS(AE:AE,$G:$G,"OPT") | AF78: =SUMIFS(AF:AF,$G:$G,"OPT") | AG78: =SUMIFS(AG:AG,$G:$G,"OPT") | AH78: =SUMIFS(AH:AH,$G:$G,"OPT") | AI78: =SUMIFS(AI:AI,$G:$G,"OPT") | AJ78: =SUMIFS(AJ:AJ,$G:$G,"OPT") | AK78: =SUMIFS(AK:AK,$G:$G,"OPT") | AL78: =SUMIFS(AL:AL,$G:$G,"OPT") | AM78: =SUMIFS(AM:AM,$G:$G,"OPT") | AN78: =SUMIFS(AN:AN,$G:$G,"OPT") | AO78: =SUMIFS(AO:AO,$G:$G,"OPT") | AP78: =SUMIFS(AP:AP,$G:$G,"OPT") | AQ78: =SUMIFS(AQ:AQ,$G:$G,"OPT") | AR78: =SUMIFS(AR:AR,$G:$G,"OPT") | AS78: =SUMIFS(AS:AS,$G:$G,"OPT") | AT78: =SUMIFS(AT:AT,$G:$G,"OPT") | AU78: =SUMIFS(AU:AU,$G:$G,"OPT") | AV78: =SUMIFS(AV:AV,$G:$G,"OPT") | AW78: =SUMIFS(AW:AW,$G:$G,"OPT") | AX78: =SUMIFS(AX:AX,$G:$G,"OPT") | AY78: =SUMIFS(AY:AY,$G:$G,"OPT") | AZ78: =SUMIFS(AZ:AZ,$G:$G,"OPT")

Sheet Milestones
A1: Payment milestones
A2: =Start!A2
A4: Milestone | B4: Title | C4: Effort | D4: Date | E4: Depencency
A5: M1 | B5: BzA Modul 1 | E5: eot(P-40)
A6: M2 | B6: Abnahme Modul 1 | E6: eot(P-55)
A11: Milestone | B11: Title | C11: Task group | D11: Summary task | E11: Percentage
A12: M1 | B12: BzA Modul 1 | C12: TP1 | D12: Initialisierung TP1 | E12: 1
A13: M1 | B13: BzA Modul 1 | C13: TP1 | D13: Modul 1 | E13: 0.8
A14: M1 | B14: BzA Modul 1 | C14: Querschnitt | E14: anteilig
A15: M2 | B15: Abnahme Modul 1 | C15: TP1 | D15: Modul 1 | E15: 0.2

Sheet Project risks
G1: =IFERROR(E1*F1,0)
A2: Project risk analysis
A3: =Start!A2
A5: ID | B5: Risk title | C5: Risk description | D5: Risk source (Linked feature ID or project task ID) | E5: Risk likelihood | F5: Risk impact | G5: Weighted risk impact
F6: =SUBTOTAL(9,F7:F33) | G6: =SUBTOTAL(9,G7:G33)
A7: First row. Don't override this row. Please insert new rows after this row! Don't insert or delete rows manually! Only use the menu items above "Insert row" and "Delete row" or short keys CTRL+ or CTRL-.
A8: R-1 | B8: Fiona API changes | C8: External festival API modifications during development | D8: Medium | E8: High | F8: Version locking, abstraction layer, vendor communication | G8: =IFERROR(E8*F8,0)
A9: R-2 | B9: Keycloak SSO complexity | C9: OAuth2 integration more complex than anticipated | D9: Medium | E9: Medium | F9: Early prototype, security expert consultation | G9: =IFERROR(E9*F9,0)
A10: R-3 | B10: Sony VOD DRM requirements | C10: Streaming DRM implementation challenges | D10: High | E10: High | F10: POC before commitment, vendor support contract | G10: =IFERROR(E10*F10,0)
A11: R-4 | B11: Solr search performance | C11: Enterprise search scalability under load | D11: Medium | E11: High | F11: Load testing, caching strategy, index optimization | G11: =IFERROR(E11*F11,0)
A12: R-5 | B12: Migration data quality | C12: Legacy content requires significant cleanup | D12: High | E12: Medium | F12: Early migration tests, data validation scripts | G12: =IFERROR(E12*F12,0)
A13: R-6 | B13: Third-party dependencies | C13: Critical modules become unmaintained | D13: Low | E13: High | F13: Alternative module research, update monitoring | G13: =IFERROR(E13*F13,0)
A14: R-7 | B14: Azure cost overruns | C14: Higher than expected cloud infrastructure costs | D14: Medium | E14: Medium | F14: Cost monitoring, auto-scaling limits, budget alerts | G14: =IFERROR(E14*F14,0)
A15: R-8 | B15: Browser compatibility | C15: Cross-browser issues in complex components | D15: Medium | E15: Low | F15: Early browser testing, progressive enhancement | G15: =IFERROR(E15*F15,0)
A16: R-9 | B16: Performance targets | C16: Page load times exceed 2-second target | D16: Medium | E16: High | F16: Performance budget, CDN optimization, lazy loading | G16: =IFERROR(E16*F16,0)
A17: R-10 | B17: Accessibility compliance | C17: WCAG 2.1 AA compliance gaps discovered late | D17: Low | E17: High | F17: Automated testing from start, accessibility audit | G17: =IFERROR(E17*F17,0)
A18: R-11 | B18: Scope creep | C18: Uncontrolled feature additions during development | D18: High | E18: Medium | F18: Change request process, backlog prioritization | G18: =IFERROR(E18*F18,0)
A19: R-12 | B19: Resource availability | C19: Key team members unavailable during critical phases | D19: Medium | E19: High | F19: Knowledge sharing, documentation, backup resources | G19: =IFERROR(E19*F19,0)
G20: =IFERROR(E20*F20,0)
G21: =IFERROR(E21*F21,0)
G22: =IFERROR(E22*F22,0)
G23: =IFERROR(E23*F23,0)
G24: =IFERROR(E24*F24,0)
G25: =IFERROR(E25*F25,0)
G26: =IFERROR(E26*F26,0)
G27: =IFERROR(E27*F27,0)
G28: =IFERROR(E28*F28,0)
G29: =IFERROR(E29*F29,0)
G30: =IFERROR(E30*F30,0)
G31: =IFERROR(E31*F31,0)
G32: =IFERROR(E32*F32,0)
A33: Last row. Don't override this row. Please insert new rows before this row! Don't insert or delete rows manually! Only use the menu items above "Insert row" and "Delete row" or short keys CTRL+ or CTRL-.

Sheet Project roles
G1: any | H1: =_xlfn.XLOOKUP(G1,tblCompanies[Company],tblCompanies[Accounting-related company],"") | I1: any | J1: =_xlfn.XLOOKUP(I1,tblCountries[Country],tblCountries[Inflation rate],0) | K1: any | L1: any | N1: =SUMIFS(tblDataPool[Effort],tblDataPool[Project Role],B1,tblDataPool[Sub role],E1)-T1 | O1: =SUMIFS(tblDataPool[Costs],tblDataPool[Project Role],B1,tblDataPool[Sub role],E1)-U1 | P1: 0 | Q1: =SUMIFS(tblDataPool[Price],tblDataPool[Project Role],B1,tblDataPool[Sub role],E1)-W1 | R1: 0 | T1: =SUMIFS(tblDataPool[Effort],tblDataPool[Project Role],B1,tblDataPool[Sub role],E1,tblDataPool[Item type],"Travel time") | U1: =SUMIFS(tblDataPool[Costs],tblDataPool[Project Role],B1,tblDataPool[Sub role],E1,tblDataPool[Item type],"Travel time") | V1: =P1 | W1: =SUMIFS(tblDataPool[Price],tblDataPool[Project Role],B1,tblDataPool[Sub role],E1,tblDataPool[Item type],"Travel time") | X1: 0 | Z1: =Q1+W1-O1-U1 | AA1: =IF(OR(ST_Contractor=G1,AND(ST_AccountingRelatedCompany="yes",H1="yes")),Q1+W1,Z1) | AB1: =IF(OR(ST_Contractor=G1,AND(ST_AccountingRelatedCompany="yes",H1="yes")),N1+T1,0) | AC1: =IF(AB1>0,AA1/AB1,0)
B2: Projectroles and pricing
B3: =Start!A2
B5: Only use menu item above "Edit project roles" or "Edit sub roles" for adding, renaming or rearranging project roles or sub roles. New rows cannot be inserted or deleted manually! | N5: Use the menu item above "Recalculate role sheet" or "Refresh tables/charts" to recalculate the efforts.
G6: Role details | N6: Daily rates and costs of project roles (without travel) | T6: Daily rates and costs of travel time
A7: Role ID | B7: Project Role | C7: ColNo | D7: Sub Role ID | E7: Sub role | F7: Percentage | G7: Company | H7: Accounting-related company | I7: Country | J7: Inflation rate p.a. | K7: Location | L7: Seniority Level | N7: Effort | O7: ="Costs [" & CF_Currency & "]" | P7: ="Daily costs [" & CF_Currency & "]" | Q7: ="Price [" & CF_Currency & "]" | R7: ="Daily rate [" & CF_Currency & "]" | T7: Travel time | U7: ="Costs [" & CF_Currency & "]" | V7: ="Daily costs [" & CF_Currency & "]" | W7: ="Price [" & CF_Currency & "]" | X7: ="Daily rate [" & CF_Currency & "]" | Z7: ="Margin [" & CF_Currency & "]" | AA7: ="Gross profit [" & CF_Currency & "]" | AB7: Effort of contractor | AC7: ="Gross profit ratio [" & CF_Currency & "/day]"
A8: R-1 | B8: Project manager | C8: Senior | D8: Responsible for overall project delivery, stakeholder communication, timeline and budget management | E8: 0.3 | N8: =SUM(N9:N27) | O8: =SUM(O9:O27) | P8: =IFERROR(O8/N8,0) | Q8: =SUM(Q9:Q27) | R8: =IFERROR(Q8/(N8-'Project tasks'!J76),0) | T8: =SUM(T9:T27) | U8: =SUM(U9:U27) | V8: =IFERROR(U8/T8,0) | W8: =SUM(W9:W27) | X8: =IFERROR(W8/T8,0) | Z8: =SUM(Z9:Z27) | AA8: =SUM(AA9:AA27) | AB8: =SUM(AB9:AB27) | AC8: =IF(AB8>0,AA8/AB8,0)
A9: R-2 | B9: Software architect | C9: Expert | D9: Technical lead, system architecture design, code reviews, integration strategy | E9: 0.5 | F9: 1 | G9: any | H9: =_xlfn.XLOOKUP(G9,tblCompanies[Company],tblCompanies[Accounting-related company],"") | I9: any | J9: =_xlfn.XLOOKUP(I9,tblCountries[Country],tblCountries[Inflation rate],0) | K9: any | L9: any | N9: =SUMIFS(tblDataPool[Effort],tblDataPool[Project Role],B9,tblDataPool[Sub role],E9)-T9 | O9: =SUMIFS(tblDataPool[Costs],tblDataPool[Project Role],B9,tblDataPool[Sub role],E9)-U9 | P9: 500 | Q9: =SUMIFS(tblDataPool[Price],tblDataPool[Project Role],B9,tblDataPool[Sub role],E9)-W9 | R9: 900 | T9: =SUMIFS(tblDataPool[Effort],tblDataPool[Project Role],B9,tblDataPool[Sub role],E9,tblDataPool[Item type],"Travel time") | U9: =SUMIFS(tblDataPool[Costs],tblDataPool[Project Role],B9,tblDataPool[Sub role],E9,tblDataPool[Item type],"Travel time") | V9: 500 | W9: =SUMIFS(tblDataPool[Price],tblDataPool[Project Role],B9,tblDataPool[Sub role],E9,tblDataPool[Item type],"Travel time") | X9: 450 | Z9: =Q9+W9-O9-U9 | AA9: =IF(OR(ST_Contractor=G9,AND(ST_AccountingRelatedCompany="yes",H9="yes")),Q9+W9,Z9) | AB9: =IF(OR(ST_Contractor=G9,AND(ST_AccountingRelatedCompany="yes",H9="yes")),N9+T9,0) | AC9: =IF(AB9>0,AA9/AB9,0)
A10: R-3 | B10: Developer | C10: Senior | D10: Backend development #1: Content types, migrations, Keycloak SSO, Fiona API | E10: 1 | F10: 1 | G10: any | H10: =_xlfn.XLOOKUP(G10,tblCompanies[Company],tblCompanies[Accounting-related company],"") | I10: any | J10: =_xlfn.XLOOKUP(I10,tblCountries[Country],tblCountries[Inflation rate],0) | K10: any | L10: high | N10: =SUMIFS(tblDataPool[Effort],tblDataPool[Project Role],B10,tblDataPool[Sub role],E10)-T10 | O10: =SUMIFS(tblDataPool[Costs],tblDataPool[Project Role],B10,tblDataPool[Sub role],E10)-U10 | P10: 500 | Q10: =SUMIFS(tblDataPool[Price],tblDataPool[Project Role],B10,tblDataPool[Sub role],E10)-W10 | R10: 900 | T10: =SUMIFS(tblDataPool[Effort],tblDataPool[Project Role],B10,tblDataPool[Sub role],E10,tblDataPool[Item type],"Travel time") | U10: =SUMIFS(tblDataPool[Costs],tblDataPool[Project Role],B10,tblDataPool[Sub role],E10,tblDataPool[Item type],"Travel time") | V10: 500 | W10: =SUMIFS(tblDataPool[Price],tblDataPool[Project Role],B10,tblDataPool[Sub role],E10,tblDataPool[Item type],"Travel time") | X10: 450 | Z10: =Q10+W10-O10-U10 | AA10: =IF(OR(ST_Contractor=G10,AND(ST_AccountingRelatedCompany="yes",H10="yes")),Q10+W10,Z10) | AB10: =IF(OR(ST_Contractor=G10,AND(ST_AccountingRelatedCompany="yes",H10="yes")),N10+T10,0) | AC10: =IF(AB10>0,AA10/AB10,0)
A11: R-4 | B11: Developer | C11: Senior | D11: Backend development #2: Sony VOD, Solr search, mobile API, custom modules | E11: 1 | F11: 0 | G11: any | H11: =_xlfn.XLOOKUP(G11,tblCompanies[Company],tblCompanies[Accounting-related company],"") | I11: any | J11: =_xlfn.XLOOKUP(I11,tblCountries[Country],tblCountries[Inflation rate],0) | K11: any | L11: middle | N11: =SUMIFS(tblDataPool[Effort],tblDataPool[Project Role],B11,tblDataPool[Sub role],E11)-T11 | O11: =SUMIFS(tblDataPool[Costs],tblDataPool[Project Role],B11,tblDataPool[Sub role],E11)-U11 | P11: 500 | Q11: =SUMIFS(tblDataPool[Price],tblDataPool[Project Role],B11,tblDataPool[Sub role],E11)-W11 | R11: 900 | T11: =SUMIFS(tblDataPool[Effort],tblDataPool[Project Role],B11,tblDataPool[Sub role],E11,tblDataPool[Item type],"Travel time") | U11: =SUMIFS(tblDataPool[Costs],tblDataPool[Project Role],B11,tblDataPool[Sub role],E11,tblDataPool[Item type],"Travel time") | V11: 500 | W11: =SUMIFS(tblDataPool[Price],tblDataPool[Project Role],B11,tblDataPool[Sub role],E11,tblDataPool[Item type],"Travel time") | X11: 450 | Z11: =Q11+W11-O11-U11 | AA11: =IF(OR(ST_Contractor=G11,AND(ST_AccountingRelatedCompany="yes",H11="yes")),Q11+W11,Z11) | AB11: =IF(OR(ST_Contractor=G11,AND(ST_AccountingRelatedCompany="yes",H11="yes")),N11+T11,0) | AC11: =IF(AB11>0,AA11/AB11,0)
A12: R-5 | B12: Developer | C12: Middle | D12: Frontend development: Storybook components, Tailwind CSS, accessibility, responsive design | E12: 1 | F12: 1 | G12: any | H12: =_xlfn.XLOOKUP(G12,tblCompanies[Company],tblCompanies[Accounting-related company],"") | I12: any | J12: =_xlfn.XLOOKUP(I12,tblCountries[Country],tblCountries[Inflation rate],0) | K12: any | L12: high | N12: =SUMIFS(tblDataPool[Effort],tblDataPool[Project Role],B12,tblDataPool[Sub role],E12)-T12 | O12: =SUMIFS(tblDataPool[Costs],tblDataPool[Project Role],B12,tblDataPool[Sub role],E12)-U12 | P12: 500 | Q12: =SUMIFS(tblDataPool[Price],tblDataPool[Project Role],B12,tblDataPool[Sub role],E12)-W12 | R12: 900 | T12: =SUMIFS(tblDataPool[Effort],tblDataPool[Project Role],B12,tblDataPool[Sub role],E12,tblDataPool[Item type],"Travel time") | U12: =SUMIFS(tblDataPool[Costs],tblDataPool[Project Role],B12,tblDataPool[Sub role],E12,tblDataPool[Item type],"Travel time") | V12: 500 | W12: =SUMIFS(tblDataPool[Price],tblDataPool[Project Role],B12,tblDataPool[Sub role],E12,tblDataPool[Item type],"Travel time") | X12: 450 | Z12: =Q12+W12-O12-U12 | AA12: =IF(OR(ST_Contractor=G12,AND(ST_AccountingRelatedCompany="yes",H12="yes")),Q12+W12,Z12) | AB12: =IF(OR(ST_Contractor=G12,AND(ST_AccountingRelatedCompany="yes",H12="yes")),N12+T12,0) | AC12: =IF(AB12>0,AA12/AB12,0)
A13: R-6 | B13: UI/UX Designer | C13: Middle | D13: Design system, component wireframes, user flows, accessibility compliance | E13: 0.4 | F13: 0 | G13: any | H13: =_xlfn.XLOOKUP(G13,tblCompanies[Company],tblCompanies[Accounting-related company],"") | I13: any | J13: =_xlfn.XLOOKUP(I13,tblCountries[Country],tblCountries[Inflation rate],0) | K13: any | L13: low | N13: =SUMIFS(tblDataPool[Effort],tblDataPool[Project Role],B13,tblDataPool[Sub role],E13)-T13 | O13: =SUMIFS(tblDataPool[Costs],tblDataPool[Project Role],B13,tblDataPool[Sub role],E13)-U13 | P13: 500 | Q13: =SUMIFS(tblDataPool[Price],tblDataPool[Project Role],B13,tblDataPool[Sub role],E13)-W13 | R13: 900 | T13: =SUMIFS(tblDataPool[Effort],tblDataPool[Project Role],B13,tblDataPool[Sub role],E13,tblDataPool[Item type],"Travel time") | U13: =SUMIFS(tblDataPool[Costs],tblDataPool[Project Role],B13,tblDataPool[Sub role],E13,tblDataPool[Item type],"Travel time") | V13: 500 | W13: =SUMIFS(tblDataPool[Price],tblDataPool[Project Role],B13,tblDataPool[Sub role],E13,tblDataPool[Item type],"Travel time") | X13: 450 | Z13: =Q13+W13-O13-U13 | AA13: =IF(OR(ST_Contractor=G13,AND(ST_AccountingRelatedCompany="yes",H13="yes")),Q13+W13,Z13) | AB13: =IF(OR(ST_Contractor=G13,AND(ST_AccountingRelatedCompany="yes",H13="yes")),N13+T13,0) | AC13: =IF(AB13>0,AA13/AB13,0)
A14: R-7 | B14: DevOps Engineer | C14: Middle | D14: Azure infrastructure, CI/CD pipelines, monitoring, performance optimization | E14: 0.5 | F14: 1 | G14: any | H14: =_xlfn.XLOOKUP(G14,tblCompanies[Company],tblCompanies[Accounting-related company],"") | I14: any | J14: =_xlfn.XLOOKUP(I14,tblCountries[Country],tblCountries[Inflation rate],0) | K14: any | L14: middle | N14: =SUMIFS(tblDataPool[Effort],tblDataPool[Project Role],B14,tblDataPool[Sub role],E14)-T14 | O14: =SUMIFS(tblDataPool[Costs],tblDataPool[Project Role],B14,tblDataPool[Sub role],E14)-U14 | P14: 500 | Q14: =SUMIFS(tblDataPool[Price],tblDataPool[Project Role],B14,tblDataPool[Sub role],E14)-W14 | R14: 900 | T14: =SUMIFS(tblDataPool[Effort],tblDataPool[Project Role],B14,tblDataPool[Sub role],E14,tblDataPool[Item type],"Travel time") | U14: =SUMIFS(tblDataPool[Costs],tblDataPool[Project Role],B14,tblDataPool[Sub role],E14,tblDataPool[Item type],"Travel time") | V14: 500 | W14: =SUMIFS(tblDataPool[Price],tblDataPool[Project Role],B14,tblDataPool[Sub role],E14,tblDataPool[Item type],"Travel time") | X14: 450 | Z14: =Q14+W14-O14-U14 | AA14: =IF(OR(ST_Contractor=G14,AND(ST_AccountingRelatedCompany="yes",H14="yes")),Q14+W14,Z14) | AB14: =IF(OR(ST_Contractor=G14,AND(ST_AccountingRelatedCompany="yes",H14="yes")),N14+T14,0) | AC14: =IF(AB14>0,AA14/AB14,0)
A15: R-8 | B15: Test Engineer | C15: Middle | D15: Test automation (Playwright), quality assurance, security testing, UAT coordination | E15: 0.5 | F15: 0 | G15: any | H15: =_xlfn.XLOOKUP(G15,tblCompanies[Company],tblCompanies[Accounting-related company],"") | I15: any | J15: =_xlfn.XLOOKUP(I15,tblCountries[Country],tblCountries[Inflation rate],0) | K15: any | L15: high | N15: =SUMIFS(tblDataPool[Effort],tblDataPool[Project Role],B15,tblDataPool[Sub role],E15)-T15 | O15: =SUMIFS(tblDataPool[Costs],tblDataPool[Project Role],B15,tblDataPool[Sub role],E15)-U15 | P15: 500 | Q15: =SUMIFS(tblDataPool[Price],tblDataPool[Project Role],B15,tblDataPool[Sub role],E15)-W15 | R15: 900 | T15: =SUMIFS(tblDataPool[Effort],tblDataPool[Project Role],B15,tblDataPool[Sub role],E15,tblDataPool[Item type],"Travel time") | U15: =SUMIFS(tblDataPool[Costs],tblDataPool[Project Role],B15,tblDataPool[Sub role],E15,tblDataPool[Item type],"Travel time") | V15: 500 | W15: =SUMIFS(tblDataPool[Price],tblDataPool[Project Role],B15,tblDataPool[Sub role],E15,tblDataPool[Item type],"Travel time") | X15: 450 | Z15: =Q15+W15-O15-U15 | AA15: =IF(OR(ST_Contractor=G15,AND(ST_AccountingRelatedCompany="yes",H15="yes")),Q15+W15,Z15) | AB15: =IF(OR(ST_Contractor=G15,AND(ST_AccountingRelatedCompany="yes",H15="yes")),N15+T15,0) | AC15: =IF(AB15>0,AA15/AB15,0)
A16: 5 | B16: UI/UX Designer | C16: 5 | D16: 8 | E16: UI/UX Designer (Junior) | F16: 0 | G16: any | H16: =_xlfn.XLOOKUP(G16,tblCompanies[Company],tblCompanies[Accounting-related company],"") | I16: any | J16: =_xlfn.XLOOKUP(I16,tblCountries[Country],tblCountries[Inflation rate],0) | K16: any | L16: low | N16: =SUMIFS(tblDataPool[Effort],tblDataPool[Project Role],B16,tblDataPool[Sub role],E16)-T16 | O16: =SUMIFS(tblDataPool[Costs],tblDataPool[Project Role],B16,tblDataPool[Sub role],E16)-U16 | P16: 500 | Q16: =SUMIFS(tblDataPool[Price],tblDataPool[Project Role],B16,tblDataPool[Sub role],E16)-W16 | R16: 900 | T16: =SUMIFS(tblDataPool[Effort],tblDataPool[Project Role],B16,tblDataPool[Sub role],E16,tblDataPool[Item type],"Travel time") | U16: =SUMIFS(tblDataPool[Costs],tblDataPool[Project Role],B16,tblDataPool[Sub role],E16,tblDataPool[Item type],"Travel time") | V16: 500 | W16: =SUMIFS(tblDataPool[Price],tblDataPool[Project Role],B16,tblDataPool[Sub role],E16,tblDataPool[Item type],"Travel time") | X16: 450 | Z16: =Q16+W16-O16-U16 | AA16: =IF(OR(ST_Contractor=G16,AND(ST_AccountingRelatedCompany="yes",H16="yes")),Q16+W16,Z16) | AB16: =IF(OR(ST_Contractor=G16,AND(ST_AccountingRelatedCompany="yes",H16="yes")),N16+T16,0) | AC16: =IF(AB16>0,AA16/AB16,0)
A17: 5 | B17: UI/UX Designer | C17: 5 | D17: 9 | E17: UI/UX Designer (Middle) | F17: 1 | G17: any | H17: =_xlfn.XLOOKUP(G17,tblCompanies[Company],tblCompanies[Accounting-related company],"") | I17: any | J17: =_xlfn.XLOOKUP(I17,tblCountries[Country],tblCountries[Inflation rate],0) | K17: any | L17: middle | N17: =SUMIFS(tblDataPool[Effort],tblDataPool[Project Role],B17,tblDataPool[Sub role],E17)-T17 | O17: =SUMIFS(tblDataPool[Costs],tblDataPool[Project Role],B17,tblDataPool[Sub role],E17)-U17 | P17: 500 | Q17: =SUMIFS(tblDataPool[Price],tblDataPool[Project Role],B17,tblDataPool[Sub role],E17)-W17 | R17: 900 | T17: =SUMIFS(tblDataPool[Effort],tblDataPool[Project Role],B17,tblDataPool[Sub role],E17,tblDataPool[Item type],"Travel time") | U17: =SUMIFS(tblDataPool[Costs],tblDataPool[Project Role],B17,tblDataPool[Sub role],E17,tblDataPool[Item type],"Travel time") | V17: 500 | W17: =SUMIFS(tblDataPool[Price],tblDataPool[Project Role],B17,tblDataPool[Sub role],E17,tblDataPool[Item type],"Travel time") | X17: 450 | Z17: =Q17+W17-O17-U17 | AA17: =IF(OR(ST_Contractor=G17,AND(ST_AccountingRelatedCompany="yes",H17="yes")),Q17+W17,Z17) | AB17: =IF(OR(ST_Contractor=G17,AND(ST_AccountingRelatedCompany="yes",H17="yes")),N17+T17,0) | AC17: =IF(AB17>0,AA17/AB17,0)
A18: 5 | B18: UI/UX Designer | C18: 5 | D18: 10 | E18: UI/UX Designer (Senior) | F18: 0 | G18: any | H18: =_xlfn.XLOOKUP(G18,tblCompanies[Company],tblCompanies[Accounting-related company],"") | I18: any | J18: =_xlfn.XLOOKUP(I18,tblCountries[Country],tblCountries[Inflation rate],0) | K18: any | L18: high | N18: =SUMIFS(tblDataPool[Effort],tblDataPool[Project Role],B18,tblDataPool[Sub role],E18)-T18 | O18: =SUMIFS(tblDataPool[Costs],tblDataPool[Project Role],B18,tblDataPool[Sub role],E18)-U18 | P18: 500 | Q18: =SUMIFS(tblDataPool[Price],tblDataPool[Project Role],B18,tblDataPool[Sub role],E18)-W18 | R18: 900 | T18: =SUMIFS(tblDataPool[Effort],tblDataPool[Project Role],B18,tblDataPool[Sub role],E18,tblDataPool[Item type],"Travel time") | U18: =SUMIFS(tblDataPool[Costs],tblDataPool[Project Role],B18,tblDataPool[Sub role],E18,tblDataPool[Item type],"Travel time") | V18: 500 | W18: =SUMIFS(tblDataPool[Price],tblDataPool[Project Role],B18,tblDataPool[Sub role],E18,tblDataPool[Item type],"Travel time") | X18: 450 | Z18: =Q18+W18-O18-U18 | AA18: =IF(OR(ST_Contractor=G18,AND(ST_AccountingRelatedCompany="yes",H18="yes")),Q18+W18,Z18) | AB18: =IF(OR(ST_Contractor=G18,AND(ST_AccountingRelatedCompany="yes",H18="yes")),N18+T18,0) | AC18: =IF(AB18>0,AA18/AB18,0)
A19: 6 | B19: Test manager | C19: 6 | D19: 11 | E19: Test manager | F19: 1 | G19: any | H19: =_xlfn.XLOOKUP(G19,tblCompanies[Company],tblCompanies[Accounting-related company],"") | I19: any | J19: =_xlfn.XLOOKUP(I19,tblCountries[Country],tblCountries[Inflation rate],0) | K19: any | L19: high | N19: =SUMIFS(tblDataPool[Effort],tblDataPool[Project Role],B19,tblDataPool[Sub role],E19)-T19 | O19: =SUMIFS(tblDataPool[Costs],tblDataPool[Project Role],B19,tblDataPool[Sub role],E19)-U19 | P19: 500 | Q19: =SUMIFS(tblDataPool[Price],tblDataPool[Project Role],B19,tblDataPool[Sub role],E19)-W19 | R19: 900 | T19: =SUMIFS(tblDataPool[Effort],tblDataPool[Project Role],B19,tblDataPool[Sub role],E19,tblDataPool[Item type],"Travel time") | U19: =SUMIFS(tblDataPool[Costs],tblDataPool[Project Role],B19,tblDataPool[Sub role],E19,tblDataPool[Item type],"Travel time") | V19: 500 | W19: =SUMIFS(tblDataPool[Price],tblDataPool[Project Role],B19,tblDataPool[Sub role],E19,tblDataPool[Item type],"Travel time") | X19: 450 | Z19: =Q19+W19-O19-U19 | AA19: =IF(OR(ST_Contractor=G19,AND(ST_AccountingRelatedCompany="yes",H19="yes")),Q19+W19,Z19) | AB19: =IF(OR(ST_Contractor=G19,AND(ST_AccountingRelatedCompany="yes",H19="yes")),N19+T19,0) | AC19: =IF(AB19>0,AA19/AB19,0)
A20: 7 | B20: Test Engineer | C20: 7 | D20: 12 | E20: Test Engineer (Junior) | F20: 0 | G20: any | H20: =_xlfn.XLOOKUP(G20,tblCompanies[Company],tblCompanies[Accounting-related company],"") | I20: any | J20: =_xlfn.XLOOKUP(I20,tblCountries[Country],tblCountries[Inflation rate],0) | K20: any | L20: low | N20: =SUMIFS(tblDataPool[Effort],tblDataPool[Project Role],B20,tblDataPool[Sub role],E20)-T20 | O20: =SUMIFS(tblDataPool[Costs],tblDataPool[Project Role],B20,tblDataPool[Sub role],E20)-U20 | P20: 500 | Q20: =SUMIFS(tblDataPool[Price],tblDataPool[Project Role],B20,tblDataPool[Sub role],E20)-W20 | R20: 900 | T20: =SUMIFS(tblDataPool[Effort],tblDataPool[Project Role],B20,tblDataPool[Sub role],E20,tblDataPool[Item type],"Travel time") | U20: =SUMIFS(tblDataPool[Costs],tblDataPool[Project Role],B20,tblDataPool[Sub role],E20,tblDataPool[Item type],"Travel time") | V20: 500 | W20: =SUMIFS(tblDataPool[Price],tblDataPool[Project Role],B20,tblDataPool[Sub role],E20,tblDataPool[Item type],"Travel time") | X20: 450 | Z20: =Q20+W20-O20-U20 | AA20: =IF(OR(ST_Contractor=G20,AND(ST_AccountingRelatedCompany="yes",H20="yes")),Q20+W20,Z20) | AB20: =IF(OR(ST_Contractor=G20,AND(ST_AccountingRelatedCompany="yes",H20="yes")),N20+T20,0) | AC20: =IF(AB20>0,AA20/AB20,0)
A21: 7 | B21: Test Engineer | C21: 7 | D21: 13 | E21: Test engineer (Middle) | F21: 1 | G21: any | H21: =_xlfn.XLOOKUP(G21,tblCompanies[Company],tblCompanies[Accounting-related company],"") | I21: any | J21: =_xlfn.XLOOKUP(I21,tblCountries[Country],tblCountries[Inflation rate],0) | K21: any | L21: middle | N21: =SUMIFS(tblDataPool[Effort],tblDataPool[Project Role],B21,tblDataPool[Sub role],E21)-T21 | O21: =SUMIFS(tblDataPool[Costs],tblDataPool[Project Role],B21,tblDataPool[Sub role],E21)-U21 | P21: 500 | Q21: =SUMIFS(tblDataPool[Price],tblDataPool[Project Role],B21,tblDataPool[Sub role],E21)-W21 | R21: 900 | T21: =SUMIFS(tblDataPool[Effort],tblDataPool[Project Role],B21,tblDataPool[Sub role],E21,tblDataPool[Item type],"Travel time") | U21: =SUMIFS(tblDataPool[Costs],tblDataPool[Project Role],B21,tblDataPool[Sub role],E21,tblDataPool[Item type],"Travel time") | V21: 500 | W21: =SUMIFS(tblDataPool[Price],tblDataPool[Project Role],B21,tblDataPool[Sub role],E21,tblDataPool[Item type],"Travel time") | X21: 450 | Z21: =Q21+W21-O21-U21 | AA21: =IF(OR(ST_Contractor=G21,AND(ST_AccountingRelatedCompany="yes",H21="yes")),Q21+W21,Z21) | AB21: =IF(OR(ST_Contractor=G21,AND(ST_AccountingRelatedCompany="yes",H21="yes")),N21+T21,0) | AC21: =IF(AB21>0,AA21/AB21,0)
A22: 7 | B22: Test Engineer | C22: 7 | D22: 14 | E22: Test Engineer (Senior) | F22: 0 | G22: any | H22: =_xlfn.XLOOKUP(G22,tblCompanies[Company],tblCompanies[Accounting-related company],"") | I22: any | J22: =_xlfn.XLOOKUP(I22,tblCountries[Country],tblCountries[Inflation rate],0) | K22: any | L22: high | N22: =SUMIFS(tblDataPool[Effort],tblDataPool[Project Role],B22,tblDataPool[Sub role],E22)-T22 | O22: =SUMIFS(tblDataPool[Costs],tblDataPool[Project Role],B22,tblDataPool[Sub role],E22)-U22 | P22: 500 | Q22: =SUMIFS(tblDataPool[Price],tblDataPool[Project Role],B22,tblDataPool[Sub role],E22)-W22 | R22: 900 | T22: =SUMIFS(tblDataPool[Effort],tblDataPool[Project Role],B22,tblDataPool[Sub role],E22,tblDataPool[Item type],"Travel time") | U22: =SUMIFS(tblDataPool[Costs],tblDataPool[Project Role],B22,tblDataPool[Sub role],E22,tblDataPool[Item type],"Travel time") | V22: 500 | W22: =SUMIFS(tblDataPool[Price],tblDataPool[Project Role],B22,tblDataPool[Sub role],E22,tblDataPool[Item type],"Travel time") | X22: 450 | Z22: =Q22+W22-O22-U22 | AA22: =IF(OR(ST_Contractor=G22,AND(ST_AccountingRelatedCompany="yes",H22="yes")),Q22+W22,Z22) | AB22: =IF(OR(ST_Contractor=G22,AND(ST_AccountingRelatedCompany="yes",H22="yes")),N22+T22,0) | AC22: =IF(AB22>0,AA22/AB22,0)
A23: 8 | B23: Developer | C23: 8 | D23: 15 | E23: Developer (Junior) | F23: 0 | G23: any | H23: =_xlfn.XLOOKUP(G23,tblCompanies[Company],tblCompanies[Accounting-related company],"") | I23: any | J23: =_xlfn.XLOOKUP(I23,tblCountries[Country],tblCountries[Inflation rate],0) | K23: any | L23: low | N23: =SUMIFS(tblDataPool[Effort],tblDataPool[Project Role],B23,tblDataPool[Sub role],E23)-T23 | O23: =SUMIFS(tblDataPool[Costs],tblDataPool[Project Role],B23,tblDataPool[Sub role],E23)-U23 | P23: 500 | Q23: =SUMIFS(tblDataPool[Price],tblDataPool[Project Role],B23,tblDataPool[Sub role],E23)-W23 | R23: 900 | T23: =SUMIFS(tblDataPool[Effort],tblDataPool[Project Role],B23,tblDataPool[Sub role],E23,tblDataPool[Item type],"Travel time") | U23: =SUMIFS(tblDataPool[Costs],tblDataPool[Project Role],B23,tblDataPool[Sub role],E23,tblDataPool[Item type],"Travel time") | V23: 500 | W23: =SUMIFS(tblDataPool[Price],tblDataPool[Project Role],B23,tblDataPool[Sub role],E23,tblDataPool[Item type],"Travel time") | X23: 450 | Z23: =Q23+W23-O23-U23 | AA23: =IF(OR(ST_Contractor=G23,AND(ST_AccountingRelatedCompany="yes",H23="yes")),Q23+W23,Z23) | AB23: =IF(OR(ST_Contractor=G23,AND(ST_AccountingRelatedCompany="yes",H23="yes")),N23+T23,0) | AC23: =IF(AB23>0,AA23/AB23,0)
A24: 8 | B24: Developer | C24: 8 | D24: 16 | E24: Developer (Middle) | F24: 1 | G24: any | H24: =_xlfn.XLOOKUP(G24,tblCompanies[Company],tblCompanies[Accounting-related company],"") | I24: any | J24: =_xlfn.XLOOKUP(I24,tblCountries[Country],tblCountries[Inflation rate],0) | K24: any | L24: middle | N24: =SUMIFS(tblDataPool[Effort],tblDataPool[Project Role],B24,tblDataPool[Sub role],E24)-T24 | O24: =SUMIFS(tblDataPool[Costs],tblDataPool[Project Role],B24,tblDataPool[Sub role],E24)-U24 | P24: 900 | Q24: =SUMIFS(tblDataPool[Price],tblDataPool[Project Role],B24,tblDataPool[Sub role],E24)-W24 | R24: 900 | T24: =SUMIFS(tblDataPool[Effort],tblDataPool[Project Role],B24,tblDataPool[Sub role],E24,tblDataPool[Item type],"Travel time") | U24: =SUMIFS(tblDataPool[Costs],tblDataPool[Project Role],B24,tblDataPool[Sub role],E24,tblDataPool[Item type],"Travel time") | V24: 900 | W24: =SUMIFS(tblDataPool[Price],tblDataPool[Project Role],B24,tblDataPool[Sub role],E24,tblDataPool[Item type],"Travel time") | X24: 450 | Z24: =Q24+W24-O24-U24 | AA24: =IF(OR(ST_Contractor=G24,AND(ST_AccountingRelatedCompany="yes",H24="yes")),Q24+W24,Z24) | AB24: =IF(OR(ST_Contractor=G24,AND(ST_AccountingRelatedCompany="yes",H24="yes")),N24+T24,0) | AC24: =IF(AB24>0,AA24/AB24,0)
A25: 8 | B25: Developer | C25: 8 | D25: 17 | E25: Developer (Senior) | F25: 0 | G25: any | H25: =_xlfn.XLOOKUP(G25,tblCompanies[Company],tblCompanies[Accounting-related company],"") | I25: any | J25: =_xlfn.XLOOKUP(I25,tblCountries[Country],tblCountries[Inflation rate],0) | K25: any | L25: high | N25: =SUMIFS(tblDataPool[Effort],tblDataPool[Project Role],B25,tblDataPool[Sub role],E25)-T25 | O25: =SUMIFS(tblDataPool[Costs],tblDataPool[Project Role],B25,tblDataPool[Sub role],E25)-U25 | P25: 500 | Q25: =SUMIFS(tblDataPool[Price],tblDataPool[Project Role],B25,tblDataPool[Sub role],E25)-W25 | R25: 900 | T25: =SUMIFS(tblDataPool[Effort],tblDataPool[Project Role],B25,tblDataPool[Sub role],E25,tblDataPool[Item type],"Travel time") | U25: =SUMIFS(tblDataPool[Costs],tblDataPool[Project Role],B25,tblDataPool[Sub role],E25,tblDataPool[Item type],"Travel time") | V25: 500 | W25: =SUMIFS(tblDataPool[Price],tblDataPool[Project Role],B25,tblDataPool[Sub role],E25,tblDataPool[Item type],"Travel time") | X25: 450 | Z25: =Q25+W25-O25-U25 | AA25: =IF(OR(ST_Contractor=G25,AND(ST_AccountingRelatedCompany="yes",H25="yes")),Q25+W25,Z25) | AB25: =IF(OR(ST_Contractor=G25,AND(ST_AccountingRelatedCompany="yes",H25="yes")),N25+T25,0) | AC25: =IF(AB25>0,AA25/AB25,0)
A26: 9 | B26: DevOps Engineer | C26: 9 | D26: 18 | E26: DevOps Engineer | F26: 1 | G26: any | H26: =_xlfn.XLOOKUP(G26,tblCompanies[Company],tblCompanies[Accounting-related company],"") | I26: any | J26: =_xlfn.XLOOKUP(I26,tblCountries[Country],tblCountries[Inflation rate],0) | K26: any | L26: middle | N26: =SUMIFS(tblDataPool[Effort],tblDataPool[Project Role],B26,tblDataPool[Sub role],E26)-T26 | O26: =SUMIFS(tblDataPool[Costs],tblDataPool[Project Role],B26,tblDataPool[Sub role],E26)-U26 | P26: 500 | Q26: =SUMIFS(tblDataPool[Price],tblDataPool[Project Role],B26,tblDataPool[Sub role],E26)-W26 | R26: 900 | T26: =SUMIFS(tblDataPool[Effort],tblDataPool[Project Role],B26,tblDataPool[Sub role],E26,tblDataPool[Item type],"Travel time") | U26: =SUMIFS(tblDataPool[Costs],tblDataPool[Project Role],B26,tblDataPool[Sub role],E26,tblDataPool[Item type],"Travel time") | V26: 500 | W26: =SUMIFS(tblDataPool[Price],tblDataPool[Project Role],B26,tblDataPool[Sub role],E26,tblDataPool[Item type],"Travel time") | X26: 450 | Z26: =Q26+W26-O26-U26 | AA26: =IF(OR(ST_Contractor=G26,AND(ST_AccountingRelatedCompany="yes",H26="yes")),Q26+W26,Z26) | AB26: =IF(OR(ST_Contractor=G26,AND(ST_AccountingRelatedCompany="yes",H26="yes")),N26+T26,0) | AC26: =IF(AB26>0,AA26/AB26,0)
B27: Last row. Don't override this row. Only use menu item above "Edit project roles" or "Edit sub roles".

Sheet Other costs
A1: Other costs
A2: =Start!A2
A4: ID | B4: Description | C4: Assumptions | D4: ="Costs [" & CF_Currency & "]" | E4: ="Costs to be charged [" & CF_Currency & "]"
D5: =SUBTOTAL(9,D6:D36) | E5: =SUBTOTAL(9,E6:E36)
A6: C-10 | B6: Travel Costs | E6: =$D$6
A7: C-20 | E7: =$D$7
A8: C-30 | E8: =$D$8
A9: C-40 | E9: =$D$9
A10: C-50 | E10: =$D$10
A11: C-60 | E11: =$D$11
A12: C-70 | E12: =$D$12
A13: C-80 | E13: =$D$13
A14: C-90 | E14: =$D$14
A15: C-100 | E15: =$D$15
A16: C-110 | E16: =$D$16
A17: C-120 | E17: =$D$17
A18: C-130 | E18: =$D$18
A19: C-140 | E19: =$D$19
A20: C-150 | E20: =$D$20
A21: C-160 | E21: =$D$21
A22: C-170 | E22: =$D$22
A23: C-180 | E23: =$D$23
A24: C-190 | E24: =$D$24
A25: C-200 | E25: =$D$25
A26: C-210 | E26: =$D$26
A27: C-220 | E27: =$D$27
A28: C-230 | E28: =$D$28
A29: C-240 | E29: =$D$29
A30: C-250 | E30: =$D$30
A31: C-260 | E31: =$D$31
A32: C-270 | E32: =$D$32
A33: C-280 | E33: =$D$33
A34: C-290 | E34: =$D$34
A35: C-300 | E35: =$D$35
A36: Last row. Don't override this row. New rows cannot be inserted oder added.
D38: Costs to be charged (without travel costs): | E38: =E5-E6

Sheet Change history
A1: History of changes
A2: =Start!A2
A4: Changes are entered automatically! But you can also add your own entries. Please use the tabulator key in the last column of the last row for adding a new row.
A5: Date of change | B5: Description | C5: Author
A6: 28.03.2025 | B6: Preparation: total effort (without risks) = 0,00 days, feature effort = 0,00 days, weighted risk impact = 0,00 days, total price = 0,00 €, total adjusted price = 0,00 € | C6: g.wichert
A7: 10.11.2025 | B7: Preparation: total effort (without risks) = 0,00 days, feature effort = 0,00 days, weighted risk impact = 0,00 days, total price = 0,00 €, total adjusted price = 0,00 €

Sheet Summary
A1: Summary | D1: ="Gross profit ratio [" & CF_Currency & "/day]:" | E1: =IFERROR(GETPIVOTDATA("Total Gross profit",$A$18)/GETPIVOTDATA("Total Effort Contractor",$A$18),0)
A2: =Start!A2 | D2: ="Gross profit ratio [" & CF_Currency & "/hour]:" | E2: =E1/8
G3: Use menu above "Confirm adjusted total price" to adjust all daily rates.
A4: Position | B4: Total effort | D4: ="Avg. daily rate [" & CF_Currency & "]" | E4: ="Total price [" & CF_Currency & "]" | G4: ="Adjusted total price [" & CF_Currency & "]" | H4: Difference
B5: =SUBTOTAL(9,B6:B12)-B7 | C5: =SUBTOTAL(9,C6:C12)-C7 | E5: =SUBTOTAL(9,E6:E12)-E7 | F5: =IF(ABS(E5-G5)<0.001,1,0) | G5: =$E$5
A6: Project tasks and features | B6: =GT_EffortWithoutWAAndTTAndRisks | C6: =IFERROR(B6/$B$5,0) | D6: ='Project roles'!$R$8 | E6: =B6*D6 | G6: =B6*D6*(100%+H6) | H6: =IFERROR((G5-E10-E12)/(E5-E10-E12)-100%,0)
A7: included optional tasks | B7: ='Project tasks'!J78 | D7: ='Project roles'!$R$8 | E7: =B7*D7 | G7: =B7*D7*(100%+H7) | H7: =H6
A8: Risks | B8: ='Project tasks'!J75 | C8: =IFERROR(B8/$B$5,0) | D8: ='Project roles'!$R$8 | E8: =B8*D8 | G8: =B8*D8*(100%+H8) | H8: =H6
A9: Travel time | B9: ='Project tasks'!J73 | C9: =IFERROR(B9/$B$5,0) | D9: ='Project roles'!X8 | E9: =B9*D9 | G9: =B9*D9*(100%+H9) | H9: =H6
A10: Travel costs | E10: ='Other costs'!E6 | G10: =E10 | H10: 0
A11: Warranty | B11: ='Project tasks'!J74 | C11: =IFERROR(B11/$B$5,0) | D11: ='Project roles'!$R$8 | E11: =B11*D11 | G11: =B11*D11*(100%+H11) | H11: =H8
A12: Other costs (without travel costs) | E12: ='Other costs'!E38 | G12: =E12 | H12: 0
A15: The following pivot tables show the costs and price structure from different perspectives:
C17: Costs without inflation. Use menu above 'Edit options' to change this option.
A18: Item Type | B18: Total effort | C18: Total Costs | D18: Total Price | E18: Total Margin | F18: Total Gross profit | G18: Total Effort Contractor
A19: Task | B19: 0 | C19: 0 | D19: 0 | E19: 0 | F19: 0 | G19: 0
A20: Travel time | B20: 0 | C20: 0 | D20: 0 | E20: 0 | F20: 0 | G20: 0
A21: Warranty | B21: 0 | C21: 0 | D21: 0 | E21: 0 | F21: 0 | G21: 0
A22: Gesamtergebnis | B22: 0 | C22: 0 | D22: 0 | E22: 0 | F22: 0 | G22: 0
E29: =SU_Info
A30: Task group | B30: Summary task | C30: Item type | D30: Total effort | E30: Total Costs | F30: Total Price | G30: Total Margin | I30: Feature group | J30: Feature sub group | K30: Item type | L30: Total effort
A31: (Leer) | B31: Gewährleistung | C31: Warranty | D31: 0 | E31: 0 | F31: 0 | G31: 0 | I31: (Leer) | J31: (Leer) | K31: Task | L31: 0
B32: Implementierung | C32: Task | D32: 0 | E32: 0 | F32: 0 | G32: 0 | K32: Travel time | L32: 0
B33: Inititialisierung | C33: Task | D33: 0 | E33: 0 | F33: 0 | G33: 0 | K33: Warranty | L33: 0
B34: Übergreifende Aufgaben | C34: Task | D34: 0 | E34: 0 | F34: 0 | G34: 0 | I34: Gesamtergebnis | L34: 0
C35: Travel time | D35: 0 | E35: 0 | F35: 0 | G35: 0
A36: Gesamtergebnis | D36: 0 | E36: 0 | F36: 0 | G36: 0

Sheet Chart | GANTT
A1: GANTT Chart | D1: Use the menu above "Refresh tables/charts" to rebuild this chart.
A2: =Start!A2
A4: Task group | B4: Summary task | C4: ID | D4: Task | E4: Start | F4: Duration | G4: Dependency | H4: Finish

Sheet Chart | Risks
A1: Risks Chart | D1: Use the menu above "Refresh tables/charts" to rebuild this chart.
A2: =Start!A2
O4: ID | P4: Risk title | Q4: Risk likelihood | R4: Risk impact | S4: Weighted risk impact
O6: Ergebnis | S6: =SUBTOTAL(109,tblRisksForChart[Weighted risk impact])

Sheet Data pool
A1: Data pool | C1: 25 / 23 | D1: 32 / 30
A2: =Start!A2
A4: 0 | B4: 1 | D4: 2 | E4: 3 | F4: 4 | I4: 8 | J4: 5 | K4: 6 | L4: 7 | M4: 9 | N4: 10 | O4: 11 | P4: 12 | Q4: 13 | R4: 14 | S4: 15 | T4: 16 | U4: 17 | V4: 18 | W4: 19 | X4: 20 | Y4: 21 | Z4: 22 | AA4: 23 | AJ4: 24 | AK4: 25 | AL4: 26 | AM4: 27 | AN4: 28 | AO4: 29 | AP4: 30 | AQ4: 31
A5: Item type | B5: Task id | C5: Task group | D5: Summary task | E5: Task | F5: Feature id | G5: Feature range | H5: Feature group | I5: Feature sub group | J5: Feature task no | K5: Feature | L5: Sub feature | M5: Costs id | N5: Cost descr | O5: Assumptions | P5: Ref. id | Q5: Risks | R5: Risk id | S5: Risk title | T5: Risk description | U5: Risk likelihood | V5: Risk likelihood (first team) | W5: Risk likelihood (second team) | X5: Risk impact | Y5: Risk impact (first team) | Z5: Risk impact (second team) | AA5: Project Role | AB5: Sub role | AC5: Sub role percentage | AD5: Company | AE5: Country | AF5: Inflation rate | AG5: Location | AH5: Seniority Level | AI5: Period start | AJ5: Effort | AK5: Effort (first team) | AL5: Effort (second team) | AM5: Daily costs | AN5: Costs | AO5: Daily rate | AP5: Price | AQ5: Margin | AR5: Gross profit | AS5: Effort contractor
A6: Task | B6: P-10 | D6: Inititialisierung | E6: Projektinitialisierung und -planung | U6: 0 | V6: 0 | W6: 0 | X6: 0 | Y6: 0 | Z6: 0 | AA6: Any role | AB6: Any role | AC6: 1 | AD6: any | AE6: any | AF6: 0.02 | AG6: any | AH6: any | AJ6: 0 | AK6: 0 | AL6: 0 | AM6: 500 | AN6: 0 | AO6: 900 | AP6: 0 | AQ6: 0 | AR6: 0 | AS6: 0
A7: Task | B7: P-20 | D7: Inititialisierung | E7: Planung und Durchführung Projekt Kick Off-Meeting | U7: 0 | V7: 0 | W7: 0 | X7: 0 | Y7: 0 | Z7: 0 | AA7: Any role | AB7: Any role | AC7: 1 | AD7: any | AE7: any | AF7: 0.02 | AG7: any | AH7: any | AJ7: 0 | AK7: 0 | AL7: 0 | AM7: 500 | AN7: 0 | AO7: 900 | AP7: 0 | AQ7: 0 | AR7: 0 | AS7: 0
A8: Task | B8: P-30 | D8: Inititialisierung | E8: Erstellung Software Architekturkonzept | U8: 0 | V8: 0 | W8: 0 | X8: 0 | Y8: 0 | Z8: 0 | AA8: Any role | AB8: Any role | AC8: 1 | AD8: any | AE8: any | AF8: 0.02 | AG8: any | AH8: any | AJ8: 0 | AK8: 0 | AL8: 0 | AM8: 500 | AN8: 0 | AO8: 900 | AP8: 0 | AQ8: 0 | AR8: 0 | AS8: 0
A9: Task | B9: P-40 | D9: Inititialisierung | E9: Erstellung Testkonzept | U9: 0 | V9: 0 | W9: 0 | X9: 0 | Y9: 0 | Z9: 0 | AA9: Any role | AB9: Any role | AC9: 1 | AD9: any | AE9: any | AF9: 0.02 | AG9: any | AH9: any | AJ9: 0 | AK9: 0 | AL9: 0 | AM9: 500 | AN9: 0 | AO9: 900 | AP9: 0 | AQ9: 0 | AR9: 0 | AS9: 0
A10: Task | B10: P-50 | D10: Inititialisierung | E10: Aufbau Entwicklungsumgebung | U10: 0 | V10: 0 | W10: 0 | X10: 0 | Y10: 0 | Z10: 0 | AA10: Any role | AB10: Any role | AC10: 1 | AD10: any | AE10: any | AF10: 0.02 | AG10: any | AH10: any | AJ10: 0 | AK10: 0 | AL10: 0 | AM10: 500 | AN10: 0 | AO10: 900 | AP10: 0 | AQ10: 0 | AR10: 0 | AS10: 0
A11: Task | B11: P-60 | D11: Implementierung | E11: Analyse & Software Design | U11: 0 | V11: 0 | W11: 0 | X11: 0 | Y11: 0 | Z11: 0 | AA11: Any role | AB11: Any role | AC11: 1 | AD11: any | AE11: any | AF11: 0.02 | AG11: any | AH11: any | AJ11: 0 | AK11: 0 | AL11: 0 | AM11: 500 | AN11: 0 | AO11: 900 | AP11: 0 | AQ11: 0 | AR11: 0 | AS11: 0
A12: Task | B12: P-70 | D12: Implementierung | E12: Software-entwicklung | U12: 0 | V12: 0 | W12: 0 | X12: 0 | Y12: 0 | Z12: 0 | AA12: Any role | AB12: Any role | AC12: 1 | AD12: any | AE12: any | AF12: 0.02 | AG12: any | AH12: any | AJ12: 0 | AK12: 0 | AL12: 0 | AM12: 500 | AN12: 0 | AO12: 900 | AP12: 0 | AQ12: 0 | AR12: 0 | AS12: 0
A13: Task | B13: P-80 | D13: Implementierung | E13: Softwaretest | U13: 0 | V13: 0 | W13: 0 | X13: 0 | Y13: 0 | Z13: 0 | AA13: Any role | AB13: Any role | AC13: 1 | AD13: any | AE13: any | AF13: 0.02 | AG13: any | AH13: any | AJ13: 0 | AK13: 0 | AL13: 0 | AM13: 500 | AN13: 0 | AO13: 900 | AP13: 0 | AQ13: 0 | AR13: 0 | AS13: 0
A14: Task | B14: P-90 | D14: Implementierung | E14: Entwicklung und Wartung Testautomatisierung | U14: 0 | V14: 0 | W14: 0 | X14: 0 | Y14: 0 | Z14: 0 | AA14: Any role | AB14: Any role | AC14: 1 | AD14: any | AE14: any | AF14: 0.02 | AG14: any | AH14: any | AJ14: 0 | AK14: 0 | AL14: 0 | AM14: 500 | AN14: 0 | AO14: 900 | AP14: 0 | AQ14: 0 | AR14: 0 | AS14: 0
A15: Task | B15: P-100 | D15: Implementierung | E15: Performance Test | U15: 0 | V15: 0 | W15: 0 | X15: 0 | Y15: 0 | Z15: 0 | AA15: Any role | AB15: Any role | AC15: 1 | AD15: any | AE15: any | AF15: 0.02 | AG15: any | AH15: any | AJ15: 0 | AK15: 0 | AL15: 0 | AM15: 500 | AN15: 0 | AO15: 900 | AP15: 0 | AQ15: 0 | AR15: 0 | AS15: 0
A16: Task | B16: P-110 | D16: Implementierung | E16: Sicherheitsprüfung | U16: 0 | V16: 0 | W16: 0 | X16: 0 | Y16: 0 | Z16: 0 | AA16: Any role | AB16: Any role | AC16: 1 | AD16: any | AE16: any | AF16: 0.02 | AG16: any | AH16: any | AJ16: 0 | AK16: 0 | AL16: 0 | AM16: 500 | AN16: 0 | AO16: 900 | AP16: 0 | AQ16: 0 | AR16: 0 | AS16: 0
A17: Task | B17: P-120 | D17: Implementierung | E17: Erstellung Anwenderhandbuch | U17: 0 | V17: 0 | W17: 0 | X17: 0 | Y17: 0 | Z17: 0 | AA17: Any role | AB17: Any role | AC17: 1 | AD17: any | AE17: any | AF17: 0.02 | AG17: any | AH17: any | AJ17: 0 | AK17: 0 | AL17: 0 | AM17: 500 | AN17: 0 | AO17: 900 | AP17: 0 | AQ17: 0 | AR17: 0 | AS17: 0
... A29: Warranty | B29: P-250 | D29: Gewährleistung | E29: Gewährleistung | U29: 0 | V29: 0 | W29: 0 | X29: 0 | Y29: 0 | Z29: 0 | AA29: Any role | AB29: Any role | AC29: 1 | AD29: any | AE29: any | AF29: 0.02 | AG29: any | AH29: any | AJ29: 0 | AK29: 0 | AL29: 0 | AM29: 500 | AN29: 0 | AO29: 900 | AP29: 0 | AQ29: 0 | AR29: 0 | AS29: 0

Sheet Chart | Item types
A1: Item types
A2: =Start!A2
M4: Zeilenbeschriftungen | N4: _Price
M5: Task | N5: 0
M6: Travel time | N6: 0
M7: Warranty | N7: 0
M8: Gesamtergebnis | N8: 0

Sheet Pivot | Tasks
A1: Project tasks
A2: =Start!A2
A4: Task group | B4: Summary task | C4: Task | D4: Item type | E4: _Effort | F4: _Costs | G4: _Price | H4: _Margin
A5: (Leer) | B5: Gewährleistung | C5: Gewährleistung | D5: Warranty | E5: 0 | F5: 0 | G5: 0 | H5: 0
B6: Implementierung | C6: Fehlerbearb. nach BzA | D6: Task | E6: 0 | F6: 0 | G6: 0 | H6: 0
C7: Performance Test | D7: Task | E7: 0 | F7: 0 | G7: 0 | H7: 0
C8: Software-entwicklung | D8: Task | E8: 0 | F8: 0 | G8: 0 | H8: 0
C9: Erstellung Anwenderhandbuch | D9: Task | E9: 0 | F9: 0 | G9: 0 | H9: 0
C10: Datenmigration | D10: Task | E10: 0 | F10: 0 | G10: 0 | H10: 0
C11: Softwaretest | D11: Task | E11: 0 | F11: 0 | G11: 0 | H11: 0
C12: Entwicklung und Wartung Testautomatisierung | D12: Task | E12: 0 | F12: 0 | G12: 0 | H12: 0
C13: Sicherheitsprüfung | D13: Task | E13: 0 | F13: 0 | G13: 0 | H13: 0
C14: Kundenschulung | D14: Task | E14: 0 | F14: 0 | G14: 0 | H14: 0
C15: Unterstützung des Kunden bei der Installation und Konfiguration der Software | D15: Task | E15: 0 | F15: 0 | G15: 0 | H15: 0
C16: Analyse & Software Design | D16: Task | E16: 0 | F16: 0 | G16: 0 | H16: 0
B17: Übergreifende Aufgaben | C17: DevOps Support | D17: Task | E17: 0 | F17: 0 | G17: 0 | H17: 0
C18: Reisezeiten | D18: Travel time | E18: 0 | F18: 0 | G18: 0 | H18: 0
C19: Projektmanagement | D19: Task | E19: 0 | F19: 0 | G19: 0 | H19: 0
C20: Testmanagement | D20: Task | E20: 0 | F20: 0 | G20: 0 | H20: 0
C21: Projektmeetings | D21: Task | E21: 0 | F21: 0 | G21: 0 | H21: 0
C22: Architekturmanagement | D22: Task | E22: 0 | F22: 0 | G22: 0 | H22: 0
C23: Smartshoremanagement | D23: Task | E23: 0 | F23: 0 | G23: 0 | H23: 0
B24: Inititialisierung | C24: Projektinitialisierung und -planung | D24: Task | E24: 0 | F24: 0 | G24: 0 | H24: 0
C25: Erstellung Testkonzept | D25: Task | E25: 0 | F25: 0 | G25: 0 | H25: 0
C26: Planung und Durchführung Projekt Kick Off-Meeting | D26: Task | E26: 0 | F26: 0 | G26: 0 | H26: 0
C27: Erstellung Software Architekturkonzept | D27: Task | E27: 0 | F27: 0 | G27: 0 | H27: 0
C28: Aufbau Entwicklungsumgebung | D28: Task | E28: 0 | F28: 0 | G28: 0 | H28: 0
A29: (Leer) Ergebnis | E29: 0 | F29: 0 | G29: 0 | H29: 0
A30: Gesamtergebnis | E30: 0 | F30: 0 | G30: 0 | H30: 0

Sheet Pivot | Tasks over time 
A1: Project tasks over time
A2: =Start!A2
A4: _Effort | E4: Period start
A5: Task group | B5: Summary task | C5: Task | D5: Item type | E5: Gesamtergebnis
A6: Gesamtergebnis

Sheet Chart | Tasks over time 
A1: Project tasks over time
A2: =Start!A2
A31: _Effort | B31: Task group
A32: Period start | B32: Gesamtergebnis
A33: Gesamtergebnis

Sheet Pivot | Features
A1: Features
A2: =Start!A2
A4: Feature group | B4: Feature sub group | C4: Feature | D4: Sub feature | E4: Feature id | F4: Item type | G4: _Effort | H4: _Costs | I4: _Price | J4: _Margin
A5: Gesamtergebnis

Sheet Pivot | Roles
A1: Project roles
A2: =Start!A2
A4: Item type | B4: (Alle)
A6: Project Role | B6: Company | C6: Country | D6: Location | E6: Seniority Level | F6: _Effort | G6: _Costs | H6: _Price | I6: _Margin
A7: Any role | B7: any | C7: any | D7: any | E7: any | F7: 0 | G7: 0 | H7: 0 | I7: 0
A8: Gesamtergebnis | F8: 0 | G8: 0 | H8: 0 | I8: 0

Sheet Chart | Roles
A1: Project roles over time
A2: =Start!A2
A31: Company | B31: (Alle)
A32: Country | B32: (Alle)
A33: Location | B33: (Alle)
A34: Seniority Level | B34: (Alle)
A36: Project Role | B36: Summe von Effort
A37: Any role | B37: 0
A38: Gesamtergebnis | B38: 0

Sheet Pivot | Roles over time
A1: Project roles over time
A2: =Start!A2
A4: Summe von Effort | F4: Period start
A5: Project Role | B5: Company | C5: Country | D5: Location | E5: Seniority Level | F5: (Leer) | G5: Gesamtergebnis
A6: Any role | B6: any | C6: any | D6: any | E6: any | F6: 0 | G6: 0
A7: Gesamtergebnis | F7: 0 | G7: 0

Sheet Chart | Roles over time
A1: Project roles over time
A2: =Start!A2
A31: Company | B31: (Alle)
A32: Country | B32: (Alle)
A33: Location | B33: (Alle)
A34: Seniority Level | B34: (Alle)
A36: Summe von Effort | B36: Project Role
A37: Period start | B37: Gesamtergebnis
A38: Gesamtergebnis

Sheet Pivot | Risks
A1: Project risks
A2: =Start!A2
A4: Item type | B4: (Mehrere Elemente)
A6: Risk id | B6: Risk title | C6: _Risk impact | D6: _Risk likelihood | E6: Weighted risk impact | F6: _Costs | G6: _Price | H6: _Margin
A7: Gesamtergebnis

Sheet Pivot | Calc teams efforts
A1: Calc teams efforts
A2: =Start!A2
A4: Item type | B4: Task | C4: Task id | D4: Total Effort | E4: Total Effort (first team) | F4: Total effort (second team)
A5: Task | B5: DevOps Support | C5: P-200 | D5: 0 | E5: 0 | F5: 0
B6: Fehlerbearb. nach BzA | C6: P-140 | D6: 0 | E6: 0 | F6: 0
B7: Performance Test | C7: P-100 | D7: 0 | E7: 0 | F7: 0
B8: Projektinitialisierung und -planung | C8: P-10 | D8: 0 | E8: 0 | F8: 0
B9: Erstellung Testkonzept | C9: P-40 | D9: 0 | E9: 0 | F9: 0
B10: Software-entwicklung | C10: P-70 | D10: 0 | E10: 0 | F10: 0
B11: Erstellung Anwenderhandbuch | C11: P-120 | D11: 0 | E11: 0 | F11: 0
B12: Projektmanagement | C12: P-170 | D12: 0 | E12: 0 | F12: 0
B13: Testmanagement | C13: P-180 | D13: 0 | E13: 0 | F13: 0
B14: Planung und Durchführung Projekt Kick Off-Meeting | C14: P-20 | D14: 0 | E14: 0 | F14: 0
B15: Erstellung Software Architekturkonzept | C15: P-30 | D15: 0 | E15: 0 | F15: 0
B16: Aufbau Entwicklungsumgebung | C16: P-50 | D16: 0 | E16: 0 | F16: 0
B17: Projektmeetings | C17: P-220 | D17: 0 | E17: 0 | F17: 0
... B26: Analyse & Software Design | C26: P-60 | D26: 0 | E26: 0 | F26: 0
A27: Task Ergebnis | D27: 0 | E27: 0 | F27: 0
A28: Travel time | B28: Reisezeiten | C28: P-230 | D28: 0 | E28: 0 | F28: 0
A29: Travel time Ergebnis | D29: 0 | E29: 0 | F29: 0
A30: Warranty | B30: Gewährleistung | C30: P-250 | D30: 0 | E30: 0 | F30: 0
A31: Warranty Ergebnis | D31: 0 | E31: 0 | F31: 0
A32: Gesamtergebnis | D32: 0 | E32: 0 | F32: 0

Sheet Countries
A1: Countries
A3: You can add your own entries. Please use the tabulator key in the last column of the last row for adding a new row.
A4: First row should contain the entry "any".
A6: Country | B6: Inflation rate
A7: any | B7: 0.02
A8: Germany | B8: 0.02
A9: Austria | B9: 0.035
A10: Bulgaria | B10: 0.03
A11: Finland | B11: 0.015
A12: Hungary | B12: 0.035
A13: India | B13: 0.055
A14: Italy | B14: 0.015
A15: Netherlands | B15: 0.025
A16: Romania | B16: 0.06
A17: Spain | B17: 0.025
A18: Sweden | B18: 0.025
... A20: Turkey | B20: 0.5

Sheet Companies
A1: Companies
A3: You can add your own entries. Please use the tabulator key in the last column of the last row for adding a new row.
A4: First row should contain the entry "any".
A6: Company | B6: Accounting-related company
A7: any | B7: no
A8: adesso SE | B8: yes
A9: adesso as a service | B9: no
A10: adesso Austria | B10: no
A11: adesso benefit solutions | B11: no
A12: adesso Bulgaria | B12: no
A13: adesso Finland | B13: no
A14: adesso health solutions | B14: no
A15: adesso Hungary | B15: no
A16: adesso India | B16: no
A17: adesso insurance solutions | B17: yes
... A38: WEPEX | B38: no

Sheet Locations
A1: Locations
A3: You can add your own entries. Please use the tabulator key in the last column of the last row for adding a new row.
A4: First row should contain the entry "any".
A6: Location
A7: any
A8: Onsite
A9: Offsite
A10: On-/Offsite
A11: Nearshore
A12: Offshore

Sheet Seniority Levels
A1: Seniority levels
A3: You can add your own entries. Please use the tabulator key in the last column of the last row for adding a new row.
A4: First row should contain the entry "any".
A6: Seniority Level
A7: any
A8: very low
A9: low
A10: middle
A11: high
A12: very high

Sheet Log
A1: Log
A3: Number of infos logs: | B3: =COUNTIF(tblLog[Log type],"Info")
A4: Number of warning logs: | B4: =COUNTIF(tblLog[Log type],"Warning")
A5: Number of error logs: | B5: =COUNTIF(tblLog[Log type],"Error")
A7: Date/Time | B7: Log type | C7: Log description

Sheet (Templates)
A1: Templates
A3: Template | B3: Description | C3: Created | D3: Last updated | E3: Company | F3: Business Area/Line
A4: general_dev_de | B4: Einfaches Entwicklungsprojekt (Ansprechpartner: Georg Wichert) | C4: 45658 | D4: 45664 | E4: any | F4: any
A5: general_dev_en | B5: A simple development project (contact: Georg Wichert) | C5: 45649 | D5: 45654 | E5: any | F5: any
A6: ams_appdev1_de | B6: Featurebasierte Kalkulation für die Entwicklung von mobilen Applikationen ohne Backend-Entwicklung (Ansprechpartner: Jana Pelz) | C6: 45658 | D6: 45663 | E6: adesso mobile solutions | F6: any
A7: ams_appdev1_en | B7: Feature-based calculation for the development of mobile applications without backend development (contact: Jana Pelz) | C7: 45663 | D7: 45663 | E7: adesso mobile solutions | F7: any
A8: ams_a11y_de | B8: Die Vorlage unterstützt die Kalkulation von Angeboten für Barrierefreiheitsprüfungen (a11y) in unterschiedlich starken Ausprägungen. (Ansprechpartner: Jana Pelz) | C8: 45664 | D8: 45664 | E8: adesso mobile solutions | F8: any
A9: bank_afp_de | B9: Implementierung und Erweiterung/Anpassung (Entwicklung) der adesso financial plattform (aFP). Diese Vorlage basiert auf einem Projekt basierend auf der adesso Financial Plattform von der LOB Banking (https://www.adesso.de/de/branchen/banken-finanzdienstleister/leistungen/adesso-financial-platform/index.jsp). Planungsgrundlage ist hier eine typische B2B Web-Plattform, die als Microservice(s) mit Angular Frontend in einem Cluster (Kubernetes o.ä.) entweder on-prem oder in der Public Cloud betrieben wird. Hierbei werden die typischerweise anfallenden Bereitstellungsaufwände der benötigten aFP-Module, sowie aus der Erfahrung basierende DevOps Aufwände berücksichtigt. Die fachliche Umsetzung ist dann in Form von Features zu erfassen. Die Go-Live Phase geht von einer intensiven Begleitung des Projekts, sowie der Übergabe (Transition) an das Application Management aus. Das gesamte Projekt findet inhouse statt. (Ansprechpartner: Christopher Trampisch und Andrea Peiffer) | C9: 45663 | D9: 45663 | E9: adesso SE | F9: Banking
A10: at_devops_en | B10: Die Kalkulationsvorlage unterstützt Projektleiter und Angebotsmanager beim Schätzen von DevOps-Projekten (hier für den Kunden BMW). Bei dieser Art von Projekten übernehmen wir Applikationen von einem Vor-Dienstleister (Transition IN) und entwickeln diese Applikationen weiter und übernehmen den Betrieb mit einem 24/7 Support. Die Beauftragung der Entwicklungsaufwände erfolgt über User Stories (Feature) im Festpreis. Alle Aufwände wie Development, Testing usw. bis hin zum Overhead (agile Meetings, PL, PMO, usw.) werden über diese User Stories finanziert und müssen deshalb in der Schätzung auf Feature-Ebene enthalten sein. Der Operationsbereich wird meist über ein festes Budget beauftragt und muss eventuell separat ausgewiesen werden. Die Aufwände sind aber im adesso calculator enthalten. Da diese Art von Projekten nur mit einem Smartshore Ansatz lukrativ für adesso sind, ist dieser Ansatz hier berücksichtigt. Es ist ein Verhältnis von 80% Onsite und 20% Smarthshore (Erfahrungswert) im Entwicklungs- und Testbereich im Template hinterlegt. (Ansprechpartner: Olaf Boczan) | C10: 45664 | D10: 45664 | E10: adesso SE | F10: Automotive/BMW
A11: test_simple_en | B11: Simple demo development project for testing and presentation | C11: 45654 | D11: 45654 | E11: any | F11: any
A12: test_complex_en | B12: Complex demo development project for testing and presentation | C12: 45653 | D12: 45654 | E12: any | F12: any

Sheet <general_dev_de>
A1: Key | B1: Value
A2: Proposal title | B2: <title of proposal>
A3: Contract type | B3: Work contract (fixed price)
A4: Customer | B4: <name of customer>
A5: Contractor | B5: any
A6: Calculation process | B6: Calculation with two teams
A7: Currency | B7: €
A8: Time period type | B8: 0
A9: Include inflation | B9: no
A10: No prior sorted tasks for GANTT chart | B10: yes
A11: Allocate first role efforts to other roles | B11: no
A12: FTE days | B12: 220
A13: Project length | B13: 20
A14: Team size | B14: 0
A15: Number of sprints | B15: 0
A17: Team member | B17: Team member role in proposal process
A20: Description | B20: Assumptions | C20: Costs | D20: Costs to be charged
A23: ID | B23: Risk title | C23: Risk description | D23: Linked items | E23: Risk likelihood | F23: Risk impact
A26: ID | B26: Task group | C26: Summary task | D26: Task | E26: Description | F26: Special task or feature query | G26: Assumptions | H26: Reference ID | I26: Effort | J26: Variable | K26: Formula | L26: Start | M26: Finish | N26: Duration | O26: Dependency | P26: GANTT | Q26: Role 1 | R26: Role 2 | S26: Role 3 | T26: Role 4 | U26: Role 5 | V26: Role 6 | W26: Role 7 | X26: Role 8 | Y26: Role 9 | Z26: Role 10 | AA26: Role 11 | AB26: Role 12 | AC26: Role 13 | AD26: Role 14 | AE26: Role 15 | AF26: Role 16 | AG26: Role 17 | AH26: Role 18 | AI26: Role 19 | AJ26: Role 20 | AK26: Role 21 | AL26: Role 22 | AM26: Role 23 | AN26: Role 24 | AO26: Role 25 | AP26: Role 26 | AQ26: Role 27 | AR26: Role 28 | AS26: Role 29 | AT26: Role 30
A27: P-10 | C27: Inititialisierung | D27: Projektinitialisierung und -planung | E27: Initialisierung und Planung des Projektes; Erstellung eines Projekthandbuchs, Beschaffung der Ressourcen, Aufsetzen des Projektcontrollings usw - Details siehe adesso-Intranet | I27: 0 | P27: no | R27: f100
A28: P-20 | C28: Inititialisierung | D28: Planung und Durchführung Projekt Kick Off-Meeting | E28: Internes und ggf. externes Meeting organisieren und durchführen | I28: 0 | P28: no | R28: f100
A29: P-30 | C29: Inititialisierung | D29: Erstellung Software Architekturkonzept | E29: Architekturkonzept erstellen | I29: 0 | P29: no | S29: f100
A30: P-40 | C30: Inititialisierung | D30: Erstellung Testkonzept | E30: Testkonzept erstellen | I30: 0 | P30: no | V30: f100
A31: P-50 | C31: Inititialisierung | D31: Aufbau Entwicklungsumgebung | E31: Aufbau Entwicklung-, Test- und Abnahmeumgebung | I31: 0 | P31: no | Y31: f100
A32: P-60 | C32: Implementierung | D32: Analyse und Software Design | E32: Feature task 'Analyse & Software Design' | F32: FT#1 | I32: 0 | J32: [design] | P32: no | S32: f20 | T32: f80
A33: P-70 | C33: Implementierung | D33: Softwareentwicklung | E33: Feature task 'Software-entwicklung' | F33: FT#2 | I33: 0 | J33: [dev] | P33: no | X33: f100
A34: P-80 | C34: Implementierung | D34: Softwaretest | E34: Feature task 'Softwaretest' | F34: FT#3 | I34: 0 | J34: [test] | P34: no | W34: f100
A35: P-90 | C35: Implementierung | D35: Entwicklung und Wartung Testautomatisierung | E35: Entwicklung und Wartung Testautomatisierung | I35: 0 | P35: no | V35: f20 | W35: f80
A36: P-100 | C36: Implementierung | D36: Performance Test | E36: Performance Test | I36: 0 | P36: no | S36: f20 | Y36: f80
A37: P-110 | C37: Implementierung | D37: Sicherheitsprüfung | E37: Statische Codeanalyse, Bedrohungsmodell (Bedrohungsanalyse); weitere Informationen unter security-check@adesso.de | I37: 0 | P37: no | S37: f20 | Y37: f80
A38: P-120 | C38: Implementierung | D38: Erstellung Anwenderhandbuch | E38: Erstellung, Korrektur und Übergabe eines Benutzerhandbuchs | I38: 0 | P38: no | T38: f100
A39: P-130 | C39: Implementierung | D39: Kundenschulung | E39: Vorbereitung und Durchführung von Kundenschulungen | I39: 0 | P39: no | T39: f100
A40: P-140 | C40: Implementierung | D40: Fehlerbearbeitung nach Bereitstellung zur Abnahme | E40: Feature task 'Fehlerbearb. nach BzA' | F40: FT#4 | I40: 0 | J40: [bugfix] | P40: no | W40: f20 | X40: f80
A41: P-150 | C41: Implementierung | D41: Datenmigration | E41: Datenmigration vom Altsystem in das neue System | I41: 0 | P41: no | T41: f50 | X41: f50
A42: P-160 | C42: Implementierung | D42: Unterstützung des Kunden bei der Installation und Konfiguration der Software | E42: Unterstützung des Kunden bei der Installation und Konfiguration der Software | I42: 0 | P42: no | Y42: f100
A43: P-170 | C43: Übergreifende Aufgaben | D43: Projektmanagement | E43: Projektsteuerung, Ressourcen-, Stakeholder-, Risiko- und Eskalationsmanagement, Planungsaktualisierungen usw. | I43: 0 | K43: max([#projectlength]*ifs([#total1]<200,0.5,[#total1]<500,1,[#total1]<1000,1.5,[#total1]<2000,2,true,3),10%*[#total1]) | P43: no | R43: f100
A44: P-180 | C44: Übergreifende Aufgaben | D44: Testmanagement | E44: Übergreifendes Test- und Qualitätsmanagement | I44: 0 | P44: no | V44: f100
A45: P-190 | C45: Übergreifende Aufgaben | D45: Architekturmanagement | E45: Übergreifendes Software-Architekturmanagement | I45: 0 | P45: no | S45: f100
A46: P-200 | C46: Übergreifende Aufgaben | D46: DevOps Support | E46: Übergreifender DevOps Support | I46: 0 | P46: no | Y46: f100
A47: P-210 | C47: Übergreifende Aufgaben | D47: Smartshoremanagement | E47: Übergreifende Steuerung der Smartshore-Ressourcen | I47: 0 | P47: no | R47: f100
A48: P-220 | C48: Übergreifende Aufgaben | D48: Projektmeetings | E48: Meetings > 1 Stunde, z.B. für Scrum Ereignisse | I48: 0 | P48: no | Q48: f100
A49: P-230 | C49: Übergreifende Aufgaben | D49: Reisezeiten | E49: Reisezeiten | F49: TT | I49: 0 | J49: [traveltime] | P49: no | Q49: f100
A50: P-240 | C50: Übergreifende Aufgaben | D50: Risiken | E50: Risiken | F50: RIS | I50: 0 | J50: [risks] | P50: no | Q50: f100
A51: P-250 | C51: Gewährleistung | D51: Gewährleistung | E51: Gewährleistung | F51: WA | I51: 0 | J51: [warranty] | K51: 10%*[#total1] | P51: no | Q51: f100
A53: Seniority Level
A54: any
A55: very low
A56: low
A57: middle
A58: high
A59: very high
A61: Location
A62: any
A63: Onsite
A64: Offsite
A65: On-/Offsite
... A67: Offshore
A69: Company | B69: Accounting-related company
A70: any | B70: no
A71: adesso SE | B71: yes
A72: adesso as a service | B72: no
A73: adesso Austria | B73: no
A74: adesso benefit solutions | B74: no
A75: adesso Bulgaria | B75: no
A76: adesso Finland | B76: no
A77: adesso health solutions | B77: no
A78: adesso Hungary | B78: no
A79: adesso India | B79: no
A80: adesso insurance solutions | B80: yes
... A103: Country | B103: Inflation rate
A104: any | B104: 0.02
A105: Germany | B105: 0.02
A106: Austria | B106: 0.035
A107: Bulgaria | B107: 0.03
A108: Finland | B108: 0.015
A109: Hungary | B109: 0.035
A110: India | B110: 0.055
A111: Italy | B111: 0.015
A112: Netherlands | B112: 0.025
A113: Romania | B113: 0.06
A114: Spain | B114: 0.025
A115: Sweden | B115: 0.025
... A117: Turkey | B117: 0.5
A119: Project role | B119: Sub role | C119: Percentage | D119: Company | E119: Country | F119: Location | G119: Seniority Level | H119: Daily costs | I119: Daily rate | J119: Daily costs (travel time) | K119: Daily rate (travel time)
A120: Any role | B120: Any role | C120: 1 | D120: any | E120: any | F120: any | G120: any | H120: 500 | I120: 900 | J120: 500 | K120: 450
A121: Project manager | B121: Project manager | C121: 1 | D121: any | E121: any | F121: any | G121: high | H121: 500 | I121: 900 | J121: 500 | K121: 450
A122: Project manager | B122: Project Office | C122: 0 | D122: any | E122: any | F122: any | G122: middle | H122: 500 | I122: 900 | J122: 500 | K122: 450
A123: Software architect | B123: Software Architect | C123: 1 | D123: any | E123: any | F123: any | G123: high | H123: 500 | I123: 900 | J123: 500 | K123: 450
A124: Requirement Engineer | B124: Requirement Engineer (Junior) | C124: 0 | D124: any | E124: any | F124: any | G124: low | H124: 500 | I124: 900 | J124: 500 | K124: 450
A125: Requirement Engineer | B125: Requirement Engineer (Middle) | C125: 1 | D125: any | E125: any | F125: any | G125: middle | H125: 500 | I125: 900 | J125: 500 | K125: 450
A126: Requirement Engineer | B126: Requirement Engineer (Senior) | C126: 0 | D126: any | E126: any | F126: any | G126: high | H126: 500 | I126: 900 | J126: 500 | K126: 450
A127: UI/UX Designer | B127: UI/UX Designer (Junior) | C127: 0 | D127: any | E127: any | F127: any | G127: low | H127: 500 | I127: 900 | J127: 500 | K127: 450
A128: UI/UX Designer | B128: UI/UX Designer (Middle) | C128: 1 | D128: any | E128: any | F128: any | G128: middle | H128: 500 | I128: 900 | J128: 500 | K128: 450
A129: UI/UX Designer | B129: UI/UX Designer (Senior) | C129: 0 | D129: any | E129: any | F129: any | G129: high | H129: 500 | I129: 900 | J129: 500 | K129: 450
A130: Test manager | B130: Test manager | C130: 1 | D130: any | E130: any | F130: any | G130: high | H130: 500 | I130: 900 | J130: 500 | K130: 450
A131: Test Engineer | B131: Test Engineer (Junior) | C131: 0 | D131: any | E131: any | F131: any | G131: low | H131: 500 | I131: 900 | J131: 500 | K131: 450
... A137: DevOps Engineer | B137: DevOps Engineer | C137: 1 | D137: any | E137: any | F137: any | G137: middle | H137: 500 | I137: 900 | J137: 500 | K137: 450
A139: ID | B139: Range (for query) | C139: Feature group | D139: Feature sub group | E139: Feature | F139: Sub feature | G139: Description | H139: Assumptions | I139: Reference ID | J139: Feature task 1 | K139: Feature task 2 | L139: Feature task 3 | M139: Feature task 4 | N139: Feature task 5 | O139: Feature task 6 | P139: Feature task 7 | Q139: Feature task 8 | R139: Feature task 9 | S139: Feature task 10
A142: Feature task | B142: Description | C142: Average Percentage | D142: Key task
A143: Analyse & Software Design | B143: Aufnahme, Analyse und Spezifikation der Software-Anforderungen, Teilnahme an Meetings < 1 Stunde | C143: 0.25 | D143: no
...

Sheet <general_dev_en>
A1: Key | B1: Value
A2: Proposal title | B2: <title of proposal>
A3: Contract type | B3: Work contract (fixed price)
A4: Customer | B4: <name of customer>
A5: Contractor | B5: any
A6: Calculation process | B6: Calculation with two teams
A7: Currency | B7: €
A8: Time period type | B8: 0
A9: Include inflation | B9: no
A10: No prior sorted tasks for GANTT chart | B10: yes
A11: Allocate first role efforts to other roles | B11: no
A12: FTE days | B12: 220
A13: Project length | B13: 20
A14: Team size | B14: 0
A15: Number of sprints | B15: 0
A17: Team member | B17: Team member role in proposal process
A20: Description | B20: Assumptions | C20: Costs | D20: Costs to be charged
A23: ID | B23: Risk title | C23: Risk description | D23: Linked items | E23: Risk likelihood | F23: Risk impact
A26: ID | B26: Task group | C26: Summary task | D26: Task | E26: Description | F26: Special task or feature query | G26: Assumptions | H26: Reference ID | I26: Effort | J26: Variable | K26: Formula | L26: Start | M26: Finish | N26: Duration | O26: Dependency | P26: GANTT | Q26: Role 1 | R26: Role 2 | S26: Role 3 | T26: Role 4 | U26: Role 5 | V26: Role 6 | W26: Role 7 | X26: Role 8 | Y26: Role 9 | Z26: Role 10 | AA26: Role 11 | AB26: Role 12 | AC26: Role 13 | AD26: Role 14 | AE26: Role 15 | AF26: Role 16 | AG26: Role 17 | AH26: Role 18 | AI26: Role 19 | AJ26: Role 20 | AK26: Role 21 | AL26: Role 22 | AM26: Role 23 | AN26: Role 24 | AO26: Role 25 | AP26: Role 26 | AQ26: Role 27 | AR26: Role 28 | AS26: Role 29 | AT26: Role 30
A27: P-10 | C27: Planning | D27: Project initialization and planning | E27: Initialization and planning of project; creation of a project manual, procurement of resources, setting up project controlling, etc. | I27: 0 | P27: no | R27: f100
A28: P-20 | C28: Planning | D28: Project kick-off meeting | E28: Internal and if necessary external meeting, participation, preparation and follow-up | I28: 0 | P28: no | R28: f100
A29: P-30 | C29: Planning | D29: Creation of software architecture concept | E29: Setting up a sustainable and stable architecture for the targeted application and documentation | I29: 0 | P29: no | S29: f100
A30: P-40 | C30: Planning | D30: Creation of test concept | E30: Creation of test concept, definition of test execution strategy and processes, preparation of test toolchain | I30: 0 | P30: no | V30: f100
A31: P-50 | C31: Planning | D31: Setup development environment | E31: Setup development, test and acceptance environment | I31: 0 | P31: no | Y31: f100
A32: P-60 | C32: Implementation | D32: Analysis & software design | E32: Feature task 'Analysis & software design' | F32: FT#1 | I32: 0 | J32: [design] | P32: no | S32: f20 | T32: f80
A33: P-70 | C33: Implementation | D33: Software development | E33: Feature task 'Software development' | F33: FT#2 | I33: 0 | J33: [dev] | P33: no | X33: f100
A34: P-80 | C34: Implementation | D34: Software test | E34: Feature task 'Software test' | F34: FT#3 | I34: 0 | J34: [test] | P34: no | W34: f100
A35: P-90 | C35: Implementation | D35: Development of test automation scripts | E35: Implementation and maintenance of test cases based on test concept and acceptance criteria | I35: 0 | P35: no | V35: f20 | W35: f80
A36: P-100 | C36: Implementation | D36: Performance test | E36: Performance test | I36: 0 | P36: no | S36: f20 | Y36: f80
A37: P-110 | C37: Implementation | D37: Security check | E37: Static code analysis, threat model (threat analysis); further information at security-check@adesso.de | I37: 0 | P37: no | S37: f20 | Y37: f80
A38: P-120 | C38: Implementation | D38: Writing user manual | E38: Writing, correction and handover of a user manual | I38: 0 | P38: no | T38: f100
A39: P-130 | C39: Implementation | D39: Customer training | E39: Prepare and conduct customer training courses | I39: 0 | P39: no | T39: f100
A40: P-140 | C40: Implementation | D40: Bug fixing after delivery for acceptance | E40: Feature task 'Bug fixing after final acceptance' | F40: FT#4 | I40: 0 | J40: [bugfix] | P40: no | W40: f20 | X40: f80
A41: P-150 | C41: Implementation | D41: Data migration | E41: Data migration from existing systems to the new application | I41: 0 | P41: no | T41: f50 | X41: f50
A42: P-160 | C42: Implementation | D42: Support installation and configuration of the software at the customer | E42: Support installation and configuration of the software at the customer | I42: 0 | P42: no | Y42: f100
A43: P-170 | C43: Overall tasks | D43: Project management | E43: Project management and control, resource, stakeholder, risk and escalation management, planning updates, etc. Test management Comprehensive test management etc. | I43: 0 | K43: max([#projectlength]*ifs([#total1]<200,0.5,[#total1]<500,1,[#total1]<1000,1.5,[#total1]<2000,2,true,3),10%*[#total1]) | P43: no | R43: f100
A44: P-180 | C44: Overall tasks | D44: Test management | E44: Comprehensive test and quality management | I44: 0 | P44: no | V44: f100
A45: P-190 | C45: Overall tasks | D45: Software architecture management | E45: Comprehensive software architecture management | I45: 0 | P45: no | S45: f100
A46: P-200 | C46: Overall tasks | D46: DevOps support | E46: Comprehensive DevOps support | I46: 0 | P46: no | Y46: f100
A47: P-210 | C47: Overall tasks | D47: Smartshore management/support | E47: Managing and supporting smartshore resources | I47: 0 | P47: no | R47: f100
A48: P-220 | C48: Overall tasks | D48: Project meetings | E48: Meetings > 1 hour, e.g. for Scrum events or similar | I48: 0 | P48: no | Q48: f100
A49: P-230 | C49: Overall tasks | D49: Travel times | F49: TT | I49: 0 | J49: [traveltime] | P49: no | Q49: f100
A50: P-240 | C50: Overall tasks | D50: Risks | F50: RIS | I50: 0 | J50: [risks] | P50: no | Q50: f100
A51: P-250 | C51: Warranty | D51: Warranty | F51: WA | I51: 0 | J51: [warranty] | K51: 10%*[#total1] | P51: no | Q51: f100
A53: Seniority Level
A54: any
A55: very low
A56: low
A57: middle
A58: high
A59: very high
A61: Location
A62: any
A63: Onsite
A64: Offsite
A65: On-/Offsite
... A67: Offshore
A69: Company | B69: Accounting-related company
A70: any | B70: no
A71: adesso SE | B71: yes
A72: adesso as a service | B72: no
A73: adesso Austria | B73: no
A74: adesso benefit solutions | B74: no
A75: adesso Bulgaria | B75: no
A76: adesso Finland | B76: no
A77: adesso health solutions | B77: no
A78: adesso Hungary | B78: no
A79: adesso India | B79: no
A80: adesso insurance solutions | B80: yes
... A103: Country | B103: Inflation rate
A104: any | B104: 0.02
A105: Germany | B105: 0.02
A106: Austria | B106: 0.035
A107: Bulgaria | B107: 0.03
A108: Finland | B108: 0.015
A109: Hungary | B109: 0.035
A110: India | B110: 0.055
A111: Italy | B111: 0.015
A112: Netherlands | B112: 0.025
A113: Romania | B113: 0.06
A114: Spain | B114: 0.025
A115: Sweden | B115: 0.025
... A117: Turkey | B117: 0.5
A119: Project role | B119: Sub role | C119: Percentage | D119: Company | E119: Country | F119: Location | G119: Seniority Level | H119: Daily costs | I119: Daily rate | J119: Daily costs (travel time) | K119: Daily rate (travel time)
A120: Any role | B120: Any role | C120: 1 | D120: any | E120: any | F120: any | G120: any | H120: 500 | I120: 900 | J120: 500 | K120: 450
A121: Project manager | B121: Project manager | C121: 1 | D121: any | E121: any | F121: any | G121: high | H121: 500 | I121: 900 | J121: 500 | K121: 450
A122: Project manager | B122: Project Office | C122: 0 | D122: any | E122: any | F122: any | G122: middle | H122: 500 | I122: 900 | J122: 500 | K122: 450
A123: Software architect | B123: Software Architect | C123: 1 | D123: any | E123: any | F123: any | G123: high | H123: 500 | I123: 900 | J123: 500 | K123: 450
A124: Requirement Engineer | B124: Requirement Engineer (Junior) | C124: 0 | D124: any | E124: any | F124: any | G124: low | H124: 500 | I124: 900 | J124: 500 | K124: 450
A125: Requirement Engineer | B125: Requirement Engineer (Middle) | C125: 1 | D125: any | E125: any | F125: any | G125: middle | H125: 500 | I125: 900 | J125: 500 | K125: 450
A126: Requirement Engineer | B126: Requirement Engineer (Senior) | C126: 0 | D126: any | E126: any | F126: any | G126: high | H126: 500 | I126: 900 | J126: 500 | K126: 450
A127: UI/UX Designer | B127: UI/UX Designer (Junior) | C127: 0 | D127: any | E127: any | F127: any | G127: low | H127: 500 | I127: 900 | J127: 500 | K127: 450
A128: UI/UX Designer | B128: UI/UX Designer (Middle) | C128: 1 | D128: any | E128: any | F128: any | G128: middle | H128: 500 | I128: 900 | J128: 500 | K128: 450
A129: UI/UX Designer | B129: UI/UX Designer (Senior) | C129: 0 | D129: any | E129: any | F129: any | G129: high | H129: 500 | I129: 900 | J129: 500 | K129: 450
A130: Test manager | B130: Test manager | C130: 1 | D130: any | E130: any | F130: any | G130: high | H130: 500 | I130: 900 | J130: 500 | K130: 450
A131: Test Engineer | B131: Test Engineer (Junior) | C131: 0 | D131: any | E131: any | F131: any | G131: low | H131: 500 | I131: 900 | J131: 500 | K131: 450
... A137: DevOps Engineer | B137: DevOps Engineer | C137: 1 | D137: any | E137: any | F137: any | G137: middle | H137: 500 | I137: 900 | J137: 500 | K137: 450
A139: ID | B139: Range (for query) | C139: Feature group | D139: Feature sub group | E139: Feature | F139: Sub feature | G139: Description | H139: Assumptions | I139: Reference ID | J139: Feature task 1 | K139: Feature task 2 | L139: Feature task 3 | M139: Feature task 4 | N139: Feature task 5 | O139: Feature task 6 | P139: Feature task 7 | Q139: Feature task 8 | R139: Feature task 9 | S139: Feature task 10
A142: Feature task | B142: Description | C142: Average Percentage | D142: Key task
A143: Analysis & software design | B143: Recording, analysis and detailed specification of software requirements | C143: 0.25 | D143: no
...

Sheet <ams_appdev1_de>
A1: Key | B1: Value
A2: Proposal title | B2: <title of proposal>
A3: Contract type | B3: Work contract (fixed price)
A4: Customer | B4: <name of customer>
A5: Contractor | B5: adesso mobile solutions
A6: Calculation process | B6: Calculation with two teams
A7: Currency | B7: €
A8: Time period type | B8: 0
A9: Include inflation | B9: no
A10: No prior sorted tasks for GANTT chart | B10: yes
A11: Allocate first role efforts to other roles | B11: no
A12: FTE days | B12: 220
A13: Project length | B13: 0
A14: Team size | B14: 0
A15: Number of sprints | B15: 0
A17: Team member | B17: Team member role in proposal process
A20: Description | B20: Assumptions | C20: Costs | D20: Costs to be charged
A23: ID | B23: Risk title | C23: Risk description | D23: Linked items | E23: Risk likelihood | F23: Risk impact
A26: ID | B26: Task group | C26: Summary task | D26: Task | E26: Description | F26: Special task or feature query | G26: Assumptions | H26: Reference ID | I26: Effort | J26: Variable | K26: Formula | L26: Start | M26: Finish | N26: Duration | O26: Dependency | P26: GANTT | Q26: Role 1 | R26: Role 2 | S26: Role 3 | T26: Role 4 | U26: Role 5 | V26: Role 6 | W26: Role 7 | X26: Role 8 | Y26: Role 9 | Z26: Role 10 | AA26: Role 11 | AB26: Role 12 | AC26: Role 13 | AD26: Role 14 | AE26: Role 15 | AF26: Role 16 | AG26: Role 17 | AH26: Role 18 | AI26: Role 19 | AJ26: Role 20 | AK26: Role 21 | AL26: Role 22 | AM26: Role 23 | AN26: Role 24 | AO26: Role 25 | AP26: Role 26 | AQ26: Role 27 | AR26: Role 28 | AS26: Role 29 | AT26: Role 30
A27: P-10 | C27: 10_Planung | D27: Projektinitialisierung und -planung | E27: Initialisierung und Planung des Projektes; Erstellung eines Projekthandbuchs, Beschaffung der Ressourcen, Aufsetzen des Projektcontrollings usw - Details siehe ams-Wiki "Projektmanagement" | I27: 0 | K27: min(1%*[#total1],5) | P27: no | R27: f100
A28: P-20 | C28: 10_Planung | D28: Projekt Kick Off-Meeting | E28: Internes und ggf. externes Meeting, Teilnahme, Vor- und Nachbereitung | I28: 0 | K28: [#teamsize]*0.25+1 | P28: no | Q28: f75 | R28: f20 | S28: f5
A29: P-30 | C29: 10_Planung | D29: Aufbau Testumgebung | E29: Veröffentlichung von Testversionen: Einrichtung AppCenter oder andere kundenspezifischer System (MDM) | I29: 0 | K29: 1.5 | P29: no | S29: f100
A30: P-40 | C30: 10_Planung | D30: Initialisierung Scrum | E30: Onboarding Kunden PO, Regelmeetings aufsetzen, Dokumentation der Vorgehensweise - wird auf Basis des PM Aufwands berechnet | I30: 0 | K30: 1%*[pmeff] | P30: no | R30: f100
A31: P-50 | C31: 10_Planung | D31: Durchführung Kundenworkshops | E31: Workshops zur Aufnahme und Konkretisierung von Anforderungen | I31: 0 | P31: no | R31: f10 | S31: f20 | W31: f50 | X31: f20
A32: P-60 | C32: 10_Planung | D32: Erstellung Testkonzept | E32: Erstellung Testkonzept, Entwicklung der Strategie und Prozesse zur Testdurchführung, Vorbereitung Test-Toolchain | I32: 0 | J32: [testcon] | K32: min(10%*[test],15) | P32: no | T32: f100
A33: P-70 | C33: 10_Planung | D33: Erstellung Architektur-Konzept | E33: Aufsetzen einer dauerhaft tragfähigen und robusten Architektur für die angestrebte Lösung und Dokumentation | I33: 0 | J33: [archcon] | K33: 5%*[dev] | P33: no | S33: f100
A34: P-80 | C34: 20_Durchführung | D34: UX Design | E34: Entwicklung von Wireframes, Prototypen, Featuremap, Durchführung User Research | F34: FT#1 | I34: 0 | P34: no | W34: f100
A35: P-90 | C35: 20_Durchführung | D35: UI Design | E35: Gestaltung User Interface, Screens und Views, Entwicklung Designkonzept | F35: FT#2 | I35: 0 | P35: no | X35: f100
A36: P-100 | C36: 20_Durchführung | D36: Anforderungsmanagement und Business Analyse | E36: Identifikation und Analyse der Benutzer-, Geschäfts- und technischen Anforderungen | I36: 0 | P36: no | S36: f20 | U36: f30 | W36: f50
A37: P-110 | C37: 20_Durchführung | D37: Software-Entwicklung | E37: Entwicklung der mobilen Anwendungen und Entwicklertests | F37: FT#3 | I37: 0 | J37: [dev] | P37: no | AB37: f50 | AC37: f50
A38: P-120 | C38: 20_Durchführung | D38: Software-Test | E38: Testfallerstellung und System-, Integrations- und User Acceptance-Test; Retests bei Defects im Entwicklungsprozess sowie Regressionstests bei mehreren Auslieferungen | F38: FT#4 | I38: 0 | J38: [test] | P38: no | T38: f20 | AA38: f80
A39: P-130 | C39: 20_Durchführung | D39: Erstellung Testautomatisierungsskripte | E39: Implementierung und Aktualisierung der Testfälle auf Basis Testkonzept und Akzeptanzkriterien | I39: 0 | K39: 65%*30%*[test] | P39: no | Z39: f100
A40: P-140 | C40: 20_Durchführung | D40: Hochladen Release in App Store | E40: Vorbereitung und Durchführung des Uploads des Release Candidate in den plattformspezifischen App Stores damit das Review durch App Store erfolgen kann | I40: 0 | K40: 1.25 | P40: no | AC40: f100
A41: P-150 | C41: 20_Durchführung | D41: Erstellung Anwenderhandbuch | E41: Erstellung, Korrektur und Übergabe eines Anwenderhandbuchs | I41: 0 | P41: no | S41: f20 | W41: f80
A42: P-160 | C42: 20_Durchführung | D42: Begleitung Abnahmetest | E42: Vorbereitung, Dokumentation und Schulung des Abnahmeprozesses, Unterstützung des Kunden bei Provisionierung | I42: 0 | K42: if([test]<0.25*[dev],[dev]*15%,[dev]*5%) | P42: no | R42: f100
A43: P-170 | C43: 20_Durchführung | D43: Fehlerbearbeitung nach BzA | E43: Fehlerbearbeitung nach Bereitstellung zur Abnahme (BzA); Leistung beinhaltet Entwicklung und Test | F43: FT#5 | I43: 0 | P43: no | Q43: f100
A44: P-180 | C44: 30_Abschluss | D44: Übergabe an Kunde | E44: Vorbereitende Tätigkeit für die Übergabe der Anwendung und Dokumentation an den Kunden - ohne AM | I44: 0 | K44: if([#projectlength]>52,[#total1]*5%,2) | P44: no | R44: f50 | S44: f50
A45: P-190 | C45: 30_Abschluss | D45: Übergabe an Application Management | E45: Vorbereitende Tätigkeiten für und Übergabe an das AM, Onboarding AM Mitarbeiter | I45: 0 | K45: 3 | P45: no | R45: f50 | S45: f40 | T45: f10
A46: P-200 | C46: 10_Übergreifende Aufgaben | D46: Projektmanagement | E46: PL begleitet über alle Projektphasen hinweg. U.a. zur Koordination der Abläufe, Kommunikation, Reporting, Risiko-, Stakeholdermgmt, Ressourcenmgmt | I46: 0 | J46: [pmeff] | K46: max([#projectlength]*ifs([#total1]<100,1,[#total1]<250,2,[#total1]<500,4,true,5),15%*[#total1]) | P46: no | R46: f100
A47: P-210 | C47: 10_Übergreifende Aufgaben | D47: Testmanagement | E47: Prüfung der Einhaltung der Teststrategie, Anleitung des Testteams, ggf. Anpassung Testkonzept | I47: 0 | K47: if([testcon]>1,[#sprints]*0.125,0) | P47: no | T47: f100
A48: P-220 | C48: 10_Übergreifende Aufgaben | D48: Achitekturmanagement | E48: Überwachung der strukturellen Qualität der Anwendung und Einhaltung der Architektur-Vorgaben, ggf Anpassung und Erweiterung der Architektur | I48: 0 | K48: if([archcon]>1,[#sprints]*25%,0) | P48: no | S48: f100
A49: P-230 | C49: 10_Übergreifende Aufgaben | D49: Smartshore Management | E49: Nur erforderlich wenn Smartshore eingesetzt wird - zusätzlicher Koordinations- und Kommunikationsaufwand | I49: 0 | P49: no | R49: f100
A50: P-240 | C50: 10_Übergreifende Aufgaben | D50: Durchführung Meetings inkl. Scrum-Meetings | E50: Daily, Sprint Planning, Retrospektive, Backlog Refinement, Sprint Review (auf Basis voraussichtliche Anzahl Teammitglieder, Projektdauer) | I50: 0 | K50: [#projectlength]*[#teamsize]*0.15625+[#sprints]*[#teamsize]*0.5+[#sprints]*50% | P50: no | Q50: f100
A51: P-250 | C51: 10_Übergreifende Aufgaben | D51: Berücksichtigung Sicherheitsanforderungen | E51: Sicherheitsanforderungen nehmen Einfluss auf die Aufwände zur Anwendungsentwicklung. Nachdem der Fragebogen (https://forms.office.com/e/dGK99KPKcr) ausgefüllt wurde, können Architekten, Lead Developer (idealerweise Security Champions) und Angebotsmanager auf Basis der Antworten geeignete Aufgabenpakete einplanen bzw. diese bei der Aufwandsabschätzung berücksichtigen. Kontakt: software-security-group@adesso-mobile.de | I51: 0 | P51: no | W51: f100
A52: P-260 | C52: 10_Übergreifende Aufgaben | D52: Durchführung BITV QuickCheck | E52: Bewertung des Barrierefreiheitsgrades der in Entwicklung befindlichen Anwendung und Ermittlung notwendiger Optimierungsmaßnahmen Ansprechpartner: barrierefreiheit@adesso.de | I52: 0 | P52: no | S52: f25 | T52: f20 | W52: f15 | AB52: f20 | AC52: f20
A53: P-270 | C53: 90_Reisezeiten | D53: Reisezeiten | F53: TT | I53: 0 | J53: [traveltime] | K53: 10%*[#total1] | P53: no | Q53: f100
A54: P-280 | C54: 91_Gewährleistung | D54: Gewährleistung | E54: Erforderlich bei Projekten die als Gewerk angeboten werden, 2 - 4 % des Gesamtaufwands | F54: WA | I54: 0 | J54: [warranty] | K54: 3%*[#total1] | P54: no | Q54: f100
A55: P-290 | C55: 92_Risken | D55: Risiken | F55: RIS | I55: 0 | P55: no | Q55: f100
A57: Seniority Level
A58: any
A59: very low
A60: low
A61: middle
A62: high
A63: very high
A65: Location
A66: any
A67: Onsite
A68: Offsite
A69: On-/Offsite
... A71: Offshore
A73: Company | B73: Accounting-related company
A74: any | B74: no
A75: adesso SE | B75: yes
A76: adesso as a service | B76: no
A77: adesso Austria | B77: no
A78: adesso benefit solutions | B78: no
A79: adesso Bulgaria | B79: no
A80: adesso Finland | B80: no
A81: adesso health solutions | B81: no
A82: adesso Hungary | B82: no
A83: adesso India | B83: no
A84: adesso insurance solutions | B84: yes
... A107: Country | B107: Inflation rate
A108: any | B108: 0.02
A109: Germany | B109: 0.02
A110: Austria | B110: 0.035
A111: Bulgaria | B111: 0.03
A112: Finland | B112: 0.015
A113: Hungary | B113: 0.035
A114: India | B114: 0.055
A115: Italy | B115: 0.015
A116: Netherlands | B116: 0.025
A117: Romania | B117: 0.06
A118: Spain | B118: 0.025
A119: Sweden | B119: 0.025
... A121: Turkey | B121: 0.5
A123: Project role | B123: Sub role | C123: Percentage | D123: Company | E123: Country | F123: Location | G123: Seniority Level | H123: Daily costs | I123: Daily rate | J123: Daily costs (travel time) | K123: Daily rate (travel time)
A124: Any role | B124: Any role | C124: 1 | D124: adesso mobile solutions | E124: Germany | F124: any | G124: any | H124: 600 | I124: 1000 | J124: 600 | K124: 500
A125: Project manager | B125: Project manager | C125: 1 | D125: adesso mobile solutions | E125: Germany | F125: any | G125: very high | H125: 600 | I125: 1000 | J125: 600 | K125: 500
A126: Software architect | B126: Software Architect | C126: 1 | D126: adesso mobile solutions | E126: Germany | F126: any | G126: high | H126: 600 | I126: 1000 | J126: 600 | K126: 500
A127: Test manager | B127: Test manager | C127: 1 | D127: adesso mobile solutions | E127: Germany | F127: any | G127: high | H127: 600 | I127: 1000 | J127: 600 | K127: 500
A128: (Proxy) Product owner | B128: (Proxy) Product owner | C128: 1 | D128: adesso mobile solutions | E128: Germany | F128: any | G128: high | H128: 600 | I128: 1000 | J128: 600 | K128: 500
A129: Requirement Engineer | B129: Requirement Engineer | C129: 1 | D129: adesso mobile solutions | E129: Germany | F129: any | G129: middle | H129: 600 | I129: 1000 | J129: 600 | K129: 500
A130: UX Designer | B130: UX Designer | C130: 1 | D130: adesso mobile solutions | E130: Germany | F130: any | G130: middle | H130: 600 | I130: 1000 | J130: 600 | K130: 500
A131: UX Designer | B131: UX Designer (Smartshore) | C131: 0 | D131: any | E131: any | F131: any | G131: high | H131: 250 | I131: 300 | J131: 250 | K131: 150
A132: UI Designer | B132: UI Designer | C132: 1 | D132: adesso mobile solutions | E132: Germany | F132: any | G132: middle | H132: 600 | I132: 1000 | J132: 600 | K132: 500
A133: UI Designer | B133: UI Designer (Smartshore) | C133: 0 | D133: any | E133: any | F133: any | G133: any | H133: 250 | I133: 300 | J133: 250 | K133: 150
A134: Technical consultant | B134: Technical consultant | C134: 1 | D134: adesso mobile solutions | E134: Germany | F134: any | G134: middle | H134: 600 | I134: 1000 | J134: 600 | K134: 500
A135: Test Engineer | B135: Test engineer | C135: 1 | D135: adesso mobile solutions | E135: Germany | F135: any | G135: middle | H135: 600 | I135: 1000 | J135: 600 | K135: 500
...

Sheet <ams_appdev1_en>
A1: Key | B1: Value
A2: Proposal title | B2: <title of proposal>
A3: Contract type | B3: Work contract (fixed price)
A4: Customer | B4: <name of customer>
A5: Contractor | B5: adesso mobile solutions
A6: Calculation process | B6: Calculation with two teams
A7: Currency | B7: €
A8: Time period type | B8: 0
A9: Include inflation | B9: no
A10: No prior sorted tasks for GANTT chart | B10: yes
A11: Allocate first role efforts to other roles | B11: no
A12: FTE days | B12: 220
A13: Project length | B13: 0
A14: Team size | B14: 0
A15: Number of sprints | B15: 0
A17: Team member | B17: Team member role in proposal process
A20: Description | B20: Assumptions | C20: Costs | D20: Costs to be charged
A23: ID | B23: Risk title | C23: Risk description | D23: Linked items | E23: Risk likelihood | F23: Risk impact
A26: ID | B26: Task group | C26: Summary task | D26: Task | E26: Description | F26: Special task or feature query | G26: Assumptions | H26: Reference ID | I26: Effort | J26: Variable | K26: Formula | L26: Start | M26: Finish | N26: Duration | O26: Dependency | P26: GANTT | Q26: Role 1 | R26: Role 2 | S26: Role 3 | T26: Role 4 | U26: Role 5 | V26: Role 6 | W26: Role 7 | X26: Role 8 | Y26: Role 9 | Z26: Role 10 | AA26: Role 11 | AB26: Role 12 | AC26: Role 13 | AD26: Role 14 | AE26: Role 15 | AF26: Role 16 | AG26: Role 17 | AH26: Role 18 | AI26: Role 19 | AJ26: Role 20 | AK26: Role 21 | AL26: Role 22 | AM26: Role 23 | AN26: Role 24 | AO26: Role 25 | AP26: Role 26 | AQ26: Role 27 | AR26: Role 28 | AS26: Role 29 | AT26: Role 30
A27: P-10 | C27: 10_Planning | D27: Projektinitialisierung und -planung | I27: 0 | K27: min(1%*[#total1],5) | P27: no | R27: f100
A28: P-20 | C28: 10_Planning | D28: Project Kick Off-Meeting | I28: 0 | K28: [#teamsize]*0.25+1 | P28: no | Q28: f75 | R28: f20 | S28: f5
A29: P-30 | C29: 10_Planning | D29: Development Test environment | I29: 0 | K29: 1.5 | P29: no | S29: f100
A30: P-40 | C30: 10_Planning | D30: Initializing Scrum | I30: 0 | K30: 1%*[pmeff] | P30: no | R30: f100
A31: P-50 | C31: 10_Planning | D31: Execution customer workshops | I31: 0 | P31: no | R31: f10 | S31: f20 | W31: f50 | X31: f20
A32: P-60 | C32: 10_Planning | D32: Preparation test concept | I32: 0 | J32: [testcon] | K32: min(10%*[test],15) | P32: no | T32: f100
A33: P-70 | C33: 10_Planning | D33: Creation architecture concept | I33: 0 | J33: [archcon] | K33: 5%*[dev] | P33: no | S33: f100
A34: P-80 | C34: 20_Implementation | D34: UX Design | E34: Feature task 'UX Design' | F34: FT#1 | I34: 0 | P34: no | W34: f100
A35: P-90 | C35: 20_Implementation | D35: UI Design | E35: Feature task 'UI Design' | F35: FT#2 | I35: 0 | P35: no | X35: f100
A36: P-100 | C36: 20_Implementation | D36: Requirements engineering and business analysis | I36: 0 | P36: no | S36: f20 | U36: f30 | W36: f50
A37: P-110 | C37: 20_Implementation | D37: Software development | E37: Feature task 'Development' | F37: FT#3 | I37: 0 | J37: [dev] | P37: no | AB37: f50 | AC37: f50
A38: P-120 | C38: 20_Implementation | D38: Software test | E38: Feature task 'Quality assurance' | F38: FT#4 | I38: 0 | J38: [test] | P38: no | T38: f20 | AA38: f80
A39: P-130 | C39: 20_Implementation | D39: Development of test automation scripts | I39: 0 | K39: 65%*30%*[test] | P39: no | Z39: f100
A40: P-140 | C40: 20_Implementation | D40: Upload Release in App Store | I40: 0 | K40: 1.25 | P40: no | AC40: f100
A41: P-150 | C41: 20_Implementation | D41: Writing user manual | I41: 0 | P41: no | S41: f20 | W41: f80
A42: P-160 | C42: 20_Implementation | D42: Accompany acceptance test | I42: 0 | K42: if([test]<0.25*[dev],[dev]*15%,[dev]*5%) | P42: no | R42: f100
A43: P-170 | C43: 20_Implementation | D43: Bug fixing | E43: Feature task 'Bug fixing' | F43: FT#5 | I43: 0 | P43: no | Q43: f100
A44: P-180 | C44: 30_Closing | D44: Handover Customer | I44: 0 | K44: if([#projectlength]>52,[#total1]*5%,2) | P44: no | R44: f50 | S44: f50
A45: P-190 | C45: 30_Closing | D45: Handover Application Mgmt (AM) | I45: 0 | K45: 3 | P45: no | R45: f50 | S45: f40 | T45: f10
A46: P-200 | C46: 10_Overall Tasks | D46: Projectmanagement | I46: 0 | J46: [pmeff] | K46: max([#projectlength]*ifs([#total1]<100,1,[#total1]<250,2,[#total1]<500,4,true,5),15%*[#total1]) | P46: no | R46: f100
A47: P-210 | C47: 10_Overall Tasks | D47: Testmanagement | I47: 0 | K47: if([testcon]>1,[#sprints]*0.125,0) | P47: no | T47: f100
A48: P-220 | C48: 10_Overall Tasks | D48: Architecture management | I48: 0 | K48: if([archcon]>1,[#sprints]*25%,0) | P48: no | S48: f100
A49: P-230 | C49: 10_Overall Tasks | D49: Smartshore Management | I49: 0 | P49: no | R49: f100
A50: P-240 | C50: 10_Overall Tasks | D50: Execution and participation of meetings, incl. Scrum artefacts | I50: 0 | K50: [#projectlength]*[#teamsize]*0.15625+[#sprints]*[#teamsize]*0.5+[#sprints]*50% | P50: no | Q50: f100
A51: P-250 | C51: 10_Overall Tasks | D51: Execution of BITV QuickCheck | I51: 0 | P51: no | W51: f100
A52: P-260 | C52: 10_Overall Tasks | D52: Consideration of security requirements | I52: 0 | P52: no | S52: f25 | T52: f20 | W52: f15 | AB52: f20 | AC52: f20
A53: P-270 | C53: 90_Traveltime | D53: Travel time | F53: TT | I53: 0 | J53: [traveltime] | K53: 10%*[#total1] | P53: no | Q53: f100
A54: P-280 | C54: 91_Warranty | D54: Warranty | F54: WA | I54: 0 | J54: [warranty] | K54: 3%*[#total1] | P54: no | Q54: f100
A55: P-290 | C55: 92_Risks | D55: Risks | F55: RIS | I55: 0 | P55: no | Q55: f100
A57: Seniority Level
A58: any
A59: very low
A60: low
A61: middle
A62: high
A63: very high
A65: Location
A66: any
A67: Onsite
A68: Offsite
A69: On-/Offsite
... A71: Offshore
A73: Company | B73: Accounting-related company
A74: any | B74: no
A75: adesso SE | B75: yes
A76: adesso as a service | B76: no
A77: adesso Austria | B77: no
A78: adesso benefit solutions | B78: no
A79: adesso Bulgaria | B79: no
A80: adesso Finland | B80: no
A81: adesso health solutions | B81: no
A82: adesso Hungary | B82: no
A83: adesso India | B83: no
A84: adesso insurance solutions | B84: yes
... A107: Country | B107: Inflation rate
A108: any | B108: 0.02
A109: Germany | B109: 0.02
A110: Austria | B110: 0.035
A111: Bulgaria | B111: 0.03
A112: Finland | B112: 0.015
A113: Hungary | B113: 0.035
A114: India | B114: 0.055
A115: Italy | B115: 0.015
A116: Netherlands | B116: 0.025
A117: Romania | B117: 0.06
A118: Spain | B118: 0.025
A119: Sweden | B119: 0.025
... A121: Turkey | B121: 0.5
A123: Project role | B123: Sub role | C123: Percentage | D123: Company | E123: Country | F123: Location | G123: Seniority Level | H123: Daily costs | I123: Daily rate | J123: Daily costs (travel time) | K123: Daily rate (travel time)
A124: Any role | B124: Any role | C124: 1 | D124: adesso mobile solutions | E124: Germany | F124: any | G124: any | H124: 600 | I124: 1000 | J124: 600 | K124: 500
A125: Project manager | B125: Project manager | C125: 1 | D125: adesso mobile solutions | E125: Germany | F125: any | G125: very high | H125: 600 | I125: 1000 | J125: 600 | K125: 500
A126: Software architect | B126: Software Architect | C126: 1 | D126: adesso mobile solutions | E126: Germany | F126: any | G126: high | H126: 600 | I126: 1000 | J126: 600 | K126: 500
A127: Test manager | B127: Test manager | C127: 1 | D127: adesso mobile solutions | E127: Germany | F127: any | G127: high | H127: 600 | I127: 1000 | J127: 600 | K127: 500
A128: (Proxy) Product owner | B128: (Proxy) Product owner | C128: 1 | D128: adesso mobile solutions | E128: Germany | F128: any | G128: high | H128: 600 | I128: 1000 | J128: 600 | K128: 500
A129: Requirement Engineer | B129: Requirement Engineer | C129: 1 | D129: adesso mobile solutions | E129: Germany | F129: any | G129: middle | H129: 600 | I129: 1000 | J129: 600 | K129: 500
A130: UX Designer | B130: UX Designer | C130: 1 | D130: adesso mobile solutions | E130: Germany | F130: any | G130: middle | H130: 600 | I130: 1000 | J130: 600 | K130: 500
A131: UX Designer | B131: UX Designer (Smartshore) | C131: 0 | D131: any | E131: any | F131: any | G131: high | H131: 250 | I131: 300 | J131: 250 | K131: 150
A132: UI Designer | B132: UI Designer | C132: 1 | D132: adesso mobile solutions | E132: Germany | F132: any | G132: middle | H132: 600 | I132: 1000 | J132: 600 | K132: 500
A133: UI Designer | B133: UI Designer (Smartshore) | C133: 0 | D133: any | E133: any | F133: any | G133: any | H133: 250 | I133: 300 | J133: 250 | K133: 150
A134: Technical consultant | B134: Technical consultant | C134: 1 | D134: adesso mobile solutions | E134: Germany | F134: any | G134: middle | H134: 600 | I134: 1000 | J134: 600 | K134: 500
A135: Test Engineer | B135: Test engineer | C135: 1 | D135: adesso mobile solutions | E135: Germany | F135: any | G135: middle | H135: 600 | I135: 1000 | J135: 600 | K135: 500
...

Sheet <ams_a11y_de>
A1: Key | B1: Value
A2: Proposal title | B2: Barrierefreiheitsprüfungen (a11y)
A3: Contract type | B3: Service contract (T&M)
A4: Customer | B4: <name of customer>
A5: Contractor | B5: adesso mobile solutions
A6: Calculation process | B6: Calculation with two teams
A7: Currency | B7: €
A8: Time period type | B8: 0
A9: Include inflation | B9: no
A10: No prior sorted tasks for GANTT chart | B10: yes
A11: Allocate first role efforts to other roles | B11: no
A12: FTE days | B12: 220
A13: Project length | B13: 0
A14: Team size | B14: 0
A15: Number of sprints | B15: 0
A17: Team member | B17: Team member role in proposal process
A20: Description | B20: Assumptions | C20: Costs | D20: Costs to be charged
A23: ID | B23: Risk title | C23: Risk description | D23: Linked items | E23: Risk likelihood | F23: Risk impact
A26: ID | B26: Task group | C26: Summary task | D26: Task | E26: Description | F26: Special task or feature query | G26: Assumptions | H26: Reference ID | I26: Effort | J26: Variable | K26: Formula | L26: Start | M26: Finish | N26: Duration | O26: Dependency | P26: GANTT | Q26: Role 1 | R26: Role 2 | S26: Role 3 | T26: Role 4 | U26: Role 5 | V26: Role 6 | W26: Role 7 | X26: Role 8 | Y26: Role 9 | Z26: Role 10 | AA26: Role 11 | AB26: Role 12 | AC26: Role 13 | AD26: Role 14 | AE26: Role 15 | AF26: Role 16 | AG26: Role 17 | AH26: Role 18 | AI26: Role 19 | AJ26: Role 20 | AK26: Role 21 | AL26: Role 22 | AM26: Role 23 | AN26: Role 24 | AO26: Role 25 | AP26: Role 26 | AQ26: Role 27 | AR26: Role 28 | AS26: Role 29 | AT26: Role 30
A27: P-10 | C27: 10_Planung | D27: Projektinitialisierung und -planung | E27: Initialisierung und Planung des Projektes; Erstellung eines Projekthandbuchs, der Berichtsvorlage, Beschaffung der Ressourcen, Aufsetzen des Projektcontrollings usw - Details siehe ams-Wiki "Projektmanagement" | I27: 0 | K27: min(1%*[#total1],0.5) | P27: no | R27: f100
A28: P-20 | C28: 10_Planung | D28: Projekt Kick Off-Meeting | E28: Internes und ggf. externes Meeting, Teilnahme, Vor- und Nachbereitung | I28: 0 | K28: [#teamsize]*0.25+1 | P28: no | R28: f50 | S28: f25 | U28: f25
A29: P-30 | C29: 20_Durchführung | D29: Durchführung & Dokumentation | E29: Feature task 'Durchführung & Dokumentation' | F29: FT#1 | I29: 0 | J29: [dev] | P29: no | S29: f100
A30: P-40 | C30: 20_Durchführung | D30: Qualitätssicherrung | E30: Feature task 'Qualitätssicherung' | F30: FT#2 | I30: 0 | J30: [qs] | P30: no | U30: f100
A31: P-50 | C31: 20_Durchführung | D31: Fehlerbearb. nach QS | E31: Feature task 'Fehlerbearb. nach QS' | F31: FT#3 | I31: 0 | P31: no | S31: f100
A32: P-60 | C32: 30_Abschluss | D32: Übergabe an Kunde | E32: Auf- und Vorbereitung des Prüfberichtes inkl. Erstellung der Präsentation, Vor- und Nachbereitung des Übergabetermins | I32: 0 | K32: max([#total1]*5%,5) | P32: no | R32: f20 | S32: f70 | U32: f10
A33: P-70 | C33: 10_Übergreifende Aufgaben | D33: Projektmanagement | E33: PL begleitet über alle Projektphasen hinweg. U.a. zur Koordination der Abläufe, Kommunikation, Reporting, Risiko-, Stakeholdermgmt, Ressourcenmgmt | I33: 0 | J33: [pmeff] | K33: [#total1]*20% | P33: no | R33: f100
A34: P-80 | C34: 10_Übergreifende Aufgaben | D34: Durchführung Meetings inkl. Scrum-Meetings | E34: Wird ausschließlich für große a11y-Projekte angeraten, Daily, Sprint Planning, Retrospektive, Backlog Refinement, Sprint Review (auf Basis voraussichtliche Anzahl Teammitglieder, Projektdauer) | I34: 0 | K34: [#projectlength]*[#teamsize]*0.15625+[#sprints]*[#teamsize]*0.5+[#sprints]*50% | P34: no | Q34: f100
A35: P-90 | C35: 10_Übergreifende Aufgaben | D35: Meetings & Abstimmungen | E35: Sofern kein Scrum gewählt wird, sind zwingend Aufwände für die Abstimmung zwischen QS, Kunde und Berater einzuplanen. Zu Berücksichtigen ist der erhöhte Beratungsaufwand in a11y Projekten | I35: 0 | K35: [dev]*7% | P35: no | R35: f30 | S35: f35 | U35: f35
A36: P-100 | C36: 90_Reisezeiten | D36: Reisezeiten | E36: Reisezeiten | F36: TT | I36: 0 | J36: [traveltime] | K36: 10%*[#total1] | P36: no | Q36: f100
A38: Seniority Level
A39: any
A40: very low
A41: low
A42: middle
A43: high
A44: very high
A46: Location
A47: any
A48: Onsite
A49: Offsite
A50: On-/Offsite
... A52: Offshore
A54: Company | B54: Accounting-related company
A55: any | B55: no
A56: adesso SE | B56: yes
A57: adesso as a service | B57: no
A58: adesso Austria | B58: no
A59: adesso benefit solutions | B59: no
A60: adesso Bulgaria | B60: no
A61: adesso Finland | B61: no
A62: adesso health solutions | B62: no
A63: adesso Hungary | B63: no
A64: adesso India | B64: no
A65: adesso insurance solutions | B65: yes
... A88: Country | B88: Inflation rate
A89: any | B89: 0.02
A90: Germany | B90: 0.02
A91: Austria | B91: 0.035
A92: Bulgaria | B92: 0.03
A93: Finland | B93: 0.015
A94: Hungary | B94: 0.035
A95: India | B95: 0.055
A96: Italy | B96: 0.015
A97: Netherlands | B97: 0.025
A98: Romania | B98: 0.06
A99: Spain | B99: 0.025
A100: Sweden | B100: 0.025
... A102: Turkey | B102: 0.5
A104: Project role | B104: Sub role | C104: Percentage | D104: Company | E104: Country | F104: Location | G104: Seniority Level | H104: Daily costs | I104: Daily rate | J104: Daily costs (travel time) | K104: Daily rate (travel time)
A105: Any role | B105: Any role | C105: 1 | D105: any | E105: any | F105: any | G105: any | H105: 600 | I105: 1000 | J105: 600 | K105: 0
A106: Projektmanager | B106: Projektmanager | C106: 1 | D106: adesso mobile solutions | E106: Germany | F106: any | G106: very high | H106: 600 | I106: 1000 | J106: 600 | K106: 0
A107: Consultant BF (senior) | B107: Consultant BF (senior) | C107: 1 | D107: adesso mobile solutions | E107: Germany | F107: any | G107: high | H107: 600 | I107: 1000 | J107: 600 | K107: 0
A108: Consultant BF | B108: Consultant BF | C108: 1 | D108: adesso mobile solutions | E108: Germany | F108: any | G108: middle | H108: 600 | I108: 1000 | J108: 600 | K108: 0
A109: Qualitätssicherung | B109: Qualitätssicherung | C109: 1 | D109: adesso mobile solutions | E109: Germany | F109: any | G109: high | H109: 600 | I109: 1000 | J109: 600 | K109: 0
A111: ID | B111: Range (for query) | C111: Feature group | D111: Feature sub group | E111: Feature | F111: Sub feature | G111: Description | H111: Assumptions | I111: Reference ID | J111: Feature task 1 | K111: Feature task 2 | L111: Feature task 3 | M111: Feature task 4 | N111: Feature task 5 | O111: Feature task 6 | P111: Feature task 7 | Q111: Feature task 8 | R111: Feature task 9 | S111: Feature task 10
A114: Feature task | B114: Description | C114: Average Percentage | D114: Key task
A115: Durchführung & Dokumentation | B115: Durchführung der Prüfung und anforderungsgerechte Dokumentation | C115: 0.8 | D115: yes
A116: Qualitätssicherung | B116: Prüfung des erstellen Berichtes duch eine unabhängige dritte Person | C116: 0.18 | D116: no
A117: Fehlerbearb. nach QS | B117: Fehlerbehebung nacch Qualitätssicherung | C117: 0.02 | D117: no

Sheet <bank_afp_de>
A1: Key | B1: Value
A2: Proposal title | B2: AFP-Einführung
A3: Contract type | B3: Work contract (fixed price)
A4: Customer | B4: <kundenname>
A5: Contractor | B5: adesso SE
A6: Calculation process | B6: Calculation with two teams
A7: Currency | B7: €
A8: Time period type | B8: 0
A9: Include inflation | B9: no
A10: No prior sorted tasks for GANTT chart | B10: yes
A11: Allocate first role efforts to other roles | B11: no
A12: FTE days | B12: 220
A13: Project length | B13: 10
A14: Team size | B14: 10
A15: Number of sprints | B15: 0
A17: Team member | B17: Team member role in proposal process
A20: Description | B20: Assumptions | C20: Costs | D20: Costs to be charged
A23: ID | B23: Risk title | C23: Risk description | D23: Linked items | E23: Risk likelihood | F23: Risk impact
A26: ID | B26: Task group | C26: Summary task | D26: Task | E26: Description | F26: Special task or feature query | G26: Assumptions | H26: Reference ID | I26: Effort | J26: Variable | K26: Formula | L26: Start | M26: Finish | N26: Duration | O26: Dependency | P26: GANTT | Q26: Role 1 | R26: Role 2 | S26: Role 3 | T26: Role 4 | U26: Role 5 | V26: Role 6 | W26: Role 7 | X26: Role 8 | Y26: Role 9 | Z26: Role 10 | AA26: Role 11 | AB26: Role 12 | AC26: Role 13 | AD26: Role 14 | AE26: Role 15 | AF26: Role 16 | AG26: Role 17 | AH26: Role 18 | AI26: Role 19 | AJ26: Role 20 | AK26: Role 21 | AL26: Role 22 | AM26: Role 23 | AN26: Role 24 | AO26: Role 25 | AP26: Role 26 | AQ26: Role 27 | AR26: Role 28 | AS26: Role 29 | AT26: Role 30
A27: P-10 | C27: 01_Initialisierung | D27: Projektinitialisierung und -planung | E27: Initialisierung und Planung des Projektes; Erstellung eines Projekthandbuchs, Beschaffung der Ressourcen, Aufsetzen des Projektcontrollings usw - Details siehe adesso-Intranet | I27: 0 | K27: 5%*[dev] | P27: no | Q27: f100
A28: P-20 | C28: 01_Initialisierung | D28: Projekt Kick Off-Meeting | E28: Internes und ggf. externes Meeting organisieren und durchführen (inkl. Arbeitszeit der Entwicker) | I28: 0 | K28: min([#teamsize]*0.5,3) | P28: no | Q28: f100
A29: P-30 | C29: 01_Initialisierung | D29: Einrichtung Arbeitsplatz und fachliche Einarbeitung | E29: Einrichtung Arbeitsplatz und fachliche Einarbeitung für jedes Teammitglied | I29: 0 | K29: [#teamsize]*0.5 | P29: no | Q29: f100
A30: P-40 | C30: 02_Bereitstellung aFP | D30: Einrichtung Identity Management / SSO (ggfs 2FA, Theming Keycloak) | E30: Optionaler aFP Baustein WICHTIG: Geschätzt wird nur die initiale Einrichtung der notwendigen Dienste/Pipelines für die Bereitstellung des Moduls. Die fachlichen Aufwände sind als separates Feature zu schätzen | I30: 0 | K30: 10 | P30: no | V30: f50 | AB30: f25 | AC30: f25
A31: P-50 | C31: 02_Bereitstellung aFP | D31: Erstellung Blueprint Middleware (Spring Boot/Security und User-Service) | E31: Optionaler aFP Baustein WICHTIG: Geschätzt wird nur die initiale Einrichtung der notwendigen Dienste/Pipelines für die Bereitstellung des Moduls. Die fachlichen Aufwände sind als separates Feature zu schätzen | I31: 0 | K31: 10 | P31: no | V31: f50 | Z31: f50
A32: P-60 | C32: 02_Bereitstellung aFP | D32: Einrichtung Frontend | E32: Optionaler aFP Baustein WICHTIG: Geschätzt wird nur die initiale Einrichtung der notwendigen Dienste/Pipelines für die Bereitstellung des Moduls. Die fachlichen Aufwände sind als separates Feature zu schätzen | I32: 0 | K32: 10 | P32: no | V32: f50 | AA32: f50
A33: P-70 | C33: 02_Bereitstellung aFP | D33: Einrichtung Print Service (Dokumenten-Generierung) | E33: Optionaler aFP Baustein WICHTIG: Geschätzt wird nur die initiale Einrichtung der notwendigen Dienste/Pipelines für die Bereitstellung des Moduls. Die fachlichen Aufwände sind als separates Feature zu schätzen | I33: 0 | K33: 5 | P33: no | V33: f50 | Z33: f50
A34: P-80 | C34: 02_Bereitstellung aFP | D34: Einrichtung DMS / Filebrowser (Daten-Upload/Download) & Antivirus & Jackrabbit OAK | E34: Optionaler aFP Baustein WICHTIG: Geschätzt wird nur die initiale Einrichtung der notwendigen Dienste/Pipelines für die Bereitstellung des Moduls. Die fachlichen Aufwände sind als separates Feature zu schätzen | I34: 0 | K34: 5 | P34: no | V34: f50 | Z34: f25 | AA34: f25
A35: P-90 | C35: 02_Bereitstellung aFP | D35: Einrichtung eChart-Service (Charts) | E35: Optionaler aFP Baustein WICHTIG: Geschätzt wird nur die initiale Einrichtung der notwendigen Dienste/Pipelines für die Bereitstellung des Moduls. Die fachlichen Aufwände sind als separates Feature zu schätzen | I35: 0 | K35: 2 | P35: no | V35: f50 | Z35: f25 | AA35: f25
A36: P-100 | C36: 02_Bereitstellung aFP | D36: Einrichtung Map-Service (Geo-Berechnungen und Darstellungen) | E36: Optionaler aFP Baustein. WICHTIG: Geschätzt wird nur die initiale Einrichtung der notwendigen Dienste/Pipelines für die Bereitstellung des Moduls. Die fachlichen Aufwände sind als separates Feature zu schätzen Hinweis: Es wird eine Nominatim Lizenz für Openstreetmap benötigt | I36: 0 | K36: 3 | P36: no | V36: f50 | Z36: f25 | AA36: f25
A37: P-110 | C37: 02_Bereitstellung aFP | D37: Einrichtung Internationalisierung (i18n) | E37: Optionaler aFP Baustein WICHTIG: Geschätzt wird nur die initiale Einrichtung der notwendigen Dienste/Pipelines für die Bereitstellung des Moduls. Die fachlichen Aufwände sind als separates Feature zu schätzen | I37: 0 | K37: 5 | P37: no | V37: f50 | Z37: f50
A38: P-120 | C38: 02_Bereitstellung aFP | D38: Einrichtung Portalrahmen (Mandantenfähigkeit des Portals) | E38: Optionaler aFP Baustein WICHTIG: Geschätzt wird nur die initiale Einrichtung der notwendigen Dienste/Pipelines für die Bereitstellung des Moduls. Die fachlichen Aufwände sind als separates Feature zu schätzen | I38: 0 | K38: 20 | P38: no | V38: f50 | Z38: f25 | AA38: f25
A39: P-130 | C39: 02_Bereitstellung aFP | D39: Einrichtung Postfach | E39: Optionaler aFP Baustein WICHTIG: Geschätzt wird nur die initiale Einrichtung der notwendigen Dienste/Pipelines für die Bereitstellung des Moduls. Die fachlichen Aufwände sind als separates Feature zu schätzen | I39: 0 | K39: 10 | P39: no | V39: f50 | Z39: f25 | AA39: f25
A40: P-140 | C40: 02_Bereitstellung aFP | D40: Einrichtung Spring State Machine / Camunda (allg. Prozessfluss Steuerung) | E40: Optionaler aFP Baustein WICHTIG: Geschätzt wird nur die initiale Einrichtung der notwendigen Dienste/Pipelines für die Bereitstellung des Moduls. Die fachlichen Aufwände sind als separates Feature zu schätzen | I40: 0 | K40: 10 | P40: no | Z40: f50 | AB40: f50
A41: P-150 | C41: 02_Bereitstellung aFP | D41: Datenbank Versionierung (z.B. Flyway) | E41: Optionaler aFP Baustein Einrichtung, sowie genereller Overhead für Versionierung ist hier zu berücksichtigen | I41: 0 | K41: 15 | P41: no | V41: f50 | Z41: f25 | AB41: f25
A42: P-160 | C42: 02_Bereitstellung aFP | D42: Einrichtung SMTP zzgl. Mailhog für Tests | E42: Optionaler aFP Baustein WICHTIG: Geschätzt wird nur die initiale Einrichtung der notwendigen Dienste/Pipelines für die Bereitstellung des Moduls. Die fachlichen Aufwände sind als separates Feature zu schätzen | I42: 0 | K42: 2 | P42: no | V42: f75 | AB42: f25
A43: P-170 | C43: 03_Konzeption | D43: Erstellung Architekturkonzept | E43: Falls abweichend zum standartisierten aFP Deployment | I43: 0 | K43: 4%*[dev] | P43: no | T43: f50 | AB43: f50
A44: P-180 | C44: 03_Konzeption | D44: Erstellung QS-/Testkonzept | E44: Nur zu schätzen, falls das Testmanagement durch adesso (und nicht den Kunden) gesteuert wird | I44: 0 | K44: max([test]*0.02,0.5) | P44: no | X44: f25 | Y44: f75
A45: P-190 | C45: 03_Konzeption | D45: Erstellung Berechtigungskonzept | E45: Generelle Konzeption der Rollen/Reche/Workflow Logik im System. Die Umsetzung ist separat als Feature zu schätzen. | I45: 0 | K45: 4%*[dev] | P45: no | X45: f50 | Y45: f50
A46: P-200 | C46: 03_Konzeption | D46: Erstellung Styleguide | E46: Sofern dies nicht vom Kunden bereitgestellt wird. | I46: 0 | K46: 4%*[dev] | P46: no | X46: f50 | AA46: f50
A47: P-210 | C47: 03_Konzeption | D47: Erstellung Barrierefreiheit-Konzept | E47: Z.B. ARIA | I47: 0 | K47: 2%*[dev] | P47: no | X47: f50 | AA47: f50
A48: P-220 | C48: 03_Konzeption | D48: Erstellung Migrationskonzept | E48: Sofern existierende Daten migriert werden, ist hier der Aufwand für die Konzeption zu schätzen | I48: 0 | P48: no | Z48: f50 | AA48: f50
A49: P-230 | C49: 04_Implementierung | D49: Analyse und Software Design | E49: Feature task 'Analyse und Software Design' | F49: FT#1 | I49: 0 | J49: [analyse] | P49: no | T49: f50 | W49: f50
A50: P-240 | C50: 04_Implementierung | D50: Software -Entwicklung | E50: Feature task 'Software-Entwicklung' | F50: FT#2 | I50: 0 | J50: [dev] | P50: no | Q50: f100
A51: P-250 | C51: 04_Implementierung | D51: Software -Test | E51: Feature task 'Software-Test' | F51: FT#3 | I51: 0 | J51: [test] | P51: no | U51: f100
A52: P-260 | C52: 04_Implementierung | D52: Erstellung Anwenderhandbuch | E52: Sofern vom Kunden gefordert | I52: 0 | K52: 5%*[dev] | P52: no | Q52: f100
A53: P-270 | C53: 04_Implementierung | D53: Herstellung von Testautomatisierungsskripts | E53: Sofern vom Kunden gefordert | I53: 0 | P53: no | X53: f100
A54: P-280 | C54: 04_Implementierung | D54: Herstellung Datenmigrationstool | E54: Sofern existierende Daten migriert werden sollen. Vgl. auch "Erstellung Migrationskonzept" | I54: 0 | P54: no | Z54: f50 | AA54: f50
A55: P-290 | C55: 05_Transition | D55: Datenmigration | E55: Eigentliche, auch mehrfache, Datenmigrationsdurchläufe und Chekcs | I55: 0 | P55: no | Z55: f50 | AA55: f50
A56: P-300 | C56: 05_Transition | D56: Erstellung Schulungsunterlagen | E56: Sofern vom Kunden gefordert | I56: 0 | K56: 30%*[training] | P56: no | X56: f100
A57: P-310 | C57: 05_Transition | D57: Durchführung Schulungen | E57: Sofern vom Kunden gefordert | I57: 0 | J57: [training] | P57: no | X57: f100
A58: P-320 | C58: 05_Transition | D58: Vorbereitung und Unterstützung bei Produktivsetzung | E58: Begleitende Tätigkeit, i.d.R. 0,5 FTE über die Go-Live Phase | I58: 0 | K58: max([dev]*2%,5) | P58: no | Q58: f100
A59: P-330 | C59: 06_Abnahme | D59: Durchführung Security Check, Überprüfung Coding-Richtlinien und Sonarqube-Analyse | E59: Allgemeiner Overhead für Security Check Iterationen | I59: 0 | K59: max([dev]*2%,5) | P59: no | Z59: f50 | AA59: f50
A60: P-340 | C60: 06_Abnahme | D60: Durchführung Pen(etration)-Test | E60: Begleitung des Pen-Test Dienstleisters, Dokumentation und Fehlerbehebung | I60: 0 | K60: [dev] * 5% | P60: no | Q60: f100
A61: P-350 | C61: 06_Abnahme | D61: Durchführung Performance-Test | E61: Begleitung und Dokumentation, sowie Optimierungs-Overhead | I61: 0 | K61: [dev] * 5% | P61: no | Q61: f100
A62: P-360 | C62: 06_Abnahme | D62: BzA: Fehlerbehebungen und Nacharbeiten | E62: Durchführung der Fehlerbehebung nach BzA | I62: 0 | J62: [bza] | K62: 10%*([analyse]+[dev]+[test]) | P62: no | Q62: f100
A63: P-370 | C63: 06_Abnahme | D63: Begleitung und Unterstützung Abnahmetest | E63: z.B. Behebung von Pen -oder Performance-Test Findings, sonstige Betreeuung | I63: 0 | K63: 15%*[bza] | P63: no | Q63: f100
A64: P-380 | C64: 10_Übergreifende Aufgaben | D64: Projektmanagement | E64: Projektplanung/-steuerung, Projektcontrolling, Berichtswesen, Risikomanagement, Eskalationsmanagement, Ressourcenmanagement, Projektdokumentation u.a. | I64: 0 | K64: max([#projectlength]*5*90%,10%*[dev]) | P64: no | R64: f90 | S64: f10
A65: P-390 | C65: 10_Übergreifende Aufgaben | D65: Scrum Prozess / Meetings | E65: Durchführung eines agilen Projekts mit Scrum Elementen (wie z.B. Daily, Review, etc…) | I65: 0 | K65: max([#projectlength]*80%*[#teamsize],10%*[dev]) | P65: no | Q65: f100
A66: P-400 | C66: 10_Übergreifende Aufgaben | D66: QS-/Testmanagement | E66: z.B. dedizierter Tester | I66: 0 | K66: 50%*[test] | P66: no | U66: f100
A67: P-410 | C67: 10_Übergreifende Aufgaben | D67: Softwarearchitektur-Management | E67: Kommunikation und Dokumentation mit Kunden | I67: 0 | P67: no | T67: f100
A68: P-420 | C68: 10_Übergreifende Aufgaben | D68: DevOps Support | E68: Aufsetzen der Umgebungen (DEV, TEST, etc..), sowie laufendee Betreuung Infrastruktur während der Projektlaufzeit | I68: 0 | K68: max([#projectlength]*5*50%,10%*[dev]) | P68: no | V68: f100
A69: P-430 | C69: 10_Übergreifende Aufgaben | D69: Smartshore Management/Support | E69: Sofern Smartshore Projekt | I69: 0 | P69: no | Q69: f100
A70: P-440 | C70: 90_Reisezeiten | D70: Reisezeiten | F70: TT | I70: 0 | J70: [traveltime] | P70: no | Q70: f100
A71: P-450 | C71: 91_Gewährleistung | D71: Gewährleistung | F71: WA | I71: 0 | J71: [warranty] | K71: 10%*[#total1] | P71: no | Q71: f100
A72: P-460 | C72: 92_Risiken | D72: Risiken | F72: RIS | I72: 0 | P72: no | Q72: f100
A74: Seniority Level
A75: any
A76: very low
A77: low
A78: middle
A79: high
A80: very high
A82: Location
A83: any
A84: Onsite
A85: Offsite
A86: On-/Offsite
... A88: Offshore
A90: Company | B90: Accounting-related company
A91: any | B91: no
A92: adesso SE | B92: yes
A93: adesso as a service | B93: no
A94: adesso Austria | B94: no
A95: adesso benefit solutions | B95: no
A96: adesso Bulgaria | B96: no
A97: adesso Finland | B97: no
A98: adesso health solutions | B98: no
A99: adesso Hungary | B99: no
A100: adesso India | B100: no
A101: adesso insurance solutions | B101: yes
... A124: Country | B124: Inflation rate
A125: any | B125: 0.02
A126: Germany | B126: 0.02
A127: Austria | B127: 0.035
A128: Bulgaria | B128: 0.03
A129: Finland | B129: 0.015
A130: Hungary | B130: 0.035
A131: India | B131: 0.055
A132: Italy | B132: 0.015
A133: Netherlands | B133: 0.025
...

Sheet <at_devops_en>
A1: Key | B1: Value
A2: Proposal title | B2: DevOps…
A3: Contract type | B3: Work contract (fixed price)
A4: Customer | B4: BMW
A5: Contractor | B5: adesso SE
A6: Calculation process | B6: Calculation with two teams
A7: Currency | B7: €
A8: Time period type | B8: 0
A9: Include inflation | B9: no
A10: No prior sorted tasks for GANTT chart | B10: yes
A11: Allocate first role efforts to other roles | B11: no
A12: FTE days | B12: 220
A13: Project length | B13: 0
A14: Team size | B14: 0
A15: Number of sprints | B15: 0
A17: Team member | B17: Team member role in proposal process
A20: Description | B20: Assumptions | C20: Costs | D20: Costs to be charged
A23: ID | B23: Risk title | C23: Risk description | D23: Linked items | E23: Risk likelihood | F23: Risk impact
A26: ID | B26: Task group | C26: Summary task | D26: Task | E26: Description | F26: Special task or feature query | G26: Assumptions | H26: Reference ID | I26: Effort | J26: Variable | K26: Formula | L26: Start | M26: Finish | N26: Duration | O26: Dependency | P26: GANTT | Q26: Role 1 | R26: Role 2 | S26: Role 3 | T26: Role 4 | U26: Role 5 | V26: Role 6 | W26: Role 7 | X26: Role 8 | Y26: Role 9 | Z26: Role 10 | AA26: Role 11 | AB26: Role 12 | AC26: Role 13 | AD26: Role 14 | AE26: Role 15 | AF26: Role 16 | AG26: Role 17 | AH26: Role 18 | AI26: Role 19 | AJ26: Role 20 | AK26: Role 21 | AL26: Role 22 | AM26: Role 23 | AN26: Role 24 | AO26: Role 25 | AP26: Role 26 | AQ26: Role 27 | AR26: Role 28 | AS26: Role 29 | AT26: Role 30
A27: P-10 | D27: Project setup | E27: Development of project controlling, project system, administration | I27: 0 | K27: 5%*[#total1] | P27: no | R27: f50 | S27: f50
A28: P-20 | D28: Project kickoff | E28: Kick off with the project team | I28: 0 | K28: [#teamsize]*0.5 | P28: no | R28: f12 | S28: f8 | T28: f8 | U28: f8 | V28: f8 | W28: f8 | X28: f8 | Y28: f16 | Z28: f8 | AA28: f8 | AB28: f8
A29: P-30 | D29: Transition IN | E29: Takeover of the applications from the previous service provider | I29: 0 | K29: [#teamsize]*20 | P29: no | T29: f5 | U29: f5 | V29: f10 | W29: f10 | X29: f60 | AB29: f10
A30: P-40 | D30: Setup development environment | E30: Setting up the development environment and the deployment line | I30: 0 | K30: [#teamsize]*3 | P30: no | T30: f20 | U30: f10 | V30: f10 | X30: f12 | Y30: f40 | AA30: f4 | AB30: f4
A31: P-50 | D31: RE/Analysis/Refinement | E31: Feature task 'RE/Analysis/Refinement' | F31: FT#1 | I31: 0 | J31: [re] | P31: no | W31: f80 | Z31: f20
A32: P-60 | D32: Software development | E32: Feature task 'Software development' | F32: FT#2 | I32: 0 | J32: [dev] | P32: no | T32: f2 | X32: f5 | Y32: f78 | AB32: f15
A33: P-70 | D33: Deployment | E33: Feature task 'Deployment' | F33: FT#3 | I33: 0 | J33: [deploy] | P33: no | Y33: f100
A34: P-80 | D34: Testing and documentation | E34: Feature task 'Testing and documentation' | F34: FT#4 | I34: 0 | J34: [test] | P34: no | U34: f10 | W34: f10 | X34: f50 | Y34: f20 | AA34: f10
A35: P-90 | D35: Defects | E35: Feature task 'Defects' | F35: FT#5 | I35: 0 | J35: [defect] | P35: no | Y35: f80 | AB35: f20
A36: P-100 | D36: Feature-Risks | E36: Feature task 'Risks' | F36: FT#6 | I36: 0 | J36: [risiko] | P36: no | Q36: f100
A37: P-110 | D37: Overhead (agil Meetings/PL/SM/PMO) | E37: Feature task 'Overhead (agile meetings/pm/sm/pmo)' | F37: FT#7 | I37: 0 | J37: [overhead] | P37: no | R37: f40 | S37: f40 | T37: f10 | V37: f10
A38: P-120 | D38: Transition OUT | E38: Handover of the applications to the next service provider | I38: 0 | K38: [#teamsize]*20 | P38: no | T38: f10 | U38: f10 | V38: f10 | W38: f10 | Y38: f60
A39: P-130 | D39: Documentation (End) | E39: Final documentation incl. YPA | I39: 0 | P39: no | R39: f10 | S39: f10 | W39: f80
A40: P-140 | D40: QA management | E40: Cross-cutting tasks Test Management | I40: 0 | K40: 5%*[test] | P40: no | U40: f80 | X40: f20
A41: P-150 | D41: DevOps support | I41: 0 | K41: 15%*[#projectlength]*5 | P41: no | V41: f100
A42: P-160 | D42: Smartshore management/support | I42: 0 | P42: no | R42: f50 | S42: f50
A43: P-170 | D43: Travel Time | F43: TT | I43: 0 | J43: [traveltime] | K43: 10%*[#total1] | P43: no | Q43: f100
A44: P-180 | D44: Warranty | F44: WA | I44: 0 | J44: [warranty] | K44: 6%*[#total1] | P44: no | Q44: f100
A45: P-190 | D45: Risks | F45: RIS | I45: 0 | P45: no | Q45: f100
A47: Seniority Level
A48: any
A49: very low
A50: low
A51: middle
A52: high
A53: very high
A55: Location
A56: any
A57: Onsite
A58: Offsite
A59: On-/Offsite
... A61: Offshore
A63: Company | B63: Accounting-related company
A64: any | B64: no
A65: adesso SE | B65: yes
A66: adesso as a service | B66: no
A67: adesso Austria | B67: no
A68: adesso benefit solutions | B68: no
A69: adesso Bulgaria | B69: no
A70: adesso Finland | B70: no
A71: adesso health solutions | B71: no
A72: adesso Hungary | B72: no
A73: adesso India | B73: no
A74: adesso insurance solutions | B74: yes
... A97: Country | B97: Inflation rate
A98: any | B98: 0.02
A99: Germany | B99: 0.02
A100: Austria | B100: 0.035
A101: Bulgaria | B101: 0.03
A102: Finland | B102: 0.015
A103: Hungary | B103: 0.035
A104: India | B104: 0.055
A105: Italy | B105: 0.015
A106: Netherlands | B106: 0.025
A107: Romania | B107: 0.06
A108: Spain | B108: 0.025
A109: Sweden | B109: 0.025
... A111: Turkey | B111: 0.5
A113: Project role | B113: Sub role | C113: Percentage | D113: Company | E113: Country | F113: Location | G113: Seniority Level | H113: Daily costs | I113: Daily rate | J113: Daily costs (travel time) | K113: Daily rate (travel time)
A114: Any role | B114: Any role | C114: 1 | D114: any | E114: any | F114: any | G114: any | H114: 605 | I114: 720 | J114: 605 | K114: 0
A115: Project manager | B115: Project manager | C115: 1 | D115: adesso SE | E115: Germany | F115: any | G115: very high | H115: 780 | I115: 720 | J115: 780 | K115: 0
A116: Project assistance | B116: Project assistance | C116: 1 | D116: adesso SE | E116: Germany | F116: any | G116: low | H116: 605 | I116: 720 | J116: 605 | K116: 0
A117: Software architect | B117: Software architect | C117: 1 | D117: adesso SE | E117: Germany | F117: any | G117: high | H117: 680 | I117: 720 | J117: 680 | K117: 0
A118: Testmanager | B118: Testmanager | C118: 1 | D118: adesso SE | E118: Germany | F118: any | G118: high | H118: 680 | I118: 720 | J118: 680 | K118: 0
A119: DevOps engineer | B119: DevOps engineer | C119: 1 | D119: adesso SE | E119: Germany | F119: any | G119: high | H119: 680 | I119: 720 | J119: 680 | K119: 0
A120: Requirement engineer | B120: Requirement engineer | C120: 1 | D120: adesso SE | E120: Germany | F120: any | G120: middle | H120: 650 | I120: 720 | J120: 650 | K120: 0
A121: Test engineer | B121: Test engineer | C121: 1 | D121: adesso SE | E121: Germany | F121: any | G121: low | H121: 520 | I121: 720 | J121: 520 | K121: 0
A122: Software developer | B122: Software developer | C122: 0.5 | D122: adesso SE | E122: Germany | F122: any | G122: low | H122: 520 | I122: 720 | J122: 520 | K122: 0
A123: Software developer | B123: Software developer (senior) | C123: 0.5 | D123: adesso SE | E123: Germany | F123: any | G123: high | H123: 680 | I123: 720 | J123: 680 | K123: 0
A124: Requirement engineer (smartshore) | B124: Requirement engineer (smartshore) | C124: 1 | D124: any | E124: any | F124: any | G124: any | H124: 310 | I124: 350 | J124: 310 | K124: 0
A125: Test engineer (smartshore) | B125: Test engineer (smartshore) | C125: 1 | D125: any | E125: any | F125: any | G125: any | H125: 310 | I125: 350 | J125: 310 | K125: 0
A126: Software developer (smartshore) | B126: Software developer (smartshore) | C126: 1 | D126: any | E126: any | F126: any | G126: any | H126: 310 | I126: 350 | J126: 310 | K126: 0
A128: ID | B128: Range (for query) | C128: Feature group | D128: Feature sub group | E128: Feature | F128: Sub feature | G128: Description | H128: Assumptions | I128: Reference ID | J128: Feature task 1 | K128: Feature task 2 | L128: Feature task 3 | M128: Feature task 4 | N128: Feature task 5 | O128: Feature task 6 | P128: Feature task 7 | Q128: Feature task 8 | R128: Feature task 9 | S128: Feature task 10
A131: Feature task | B131: Description | C131: Average Percentage | D131: Key task
A132: RE/Analysis/Refinement | B132: Requirement Engineering, analysis of the user stories, agile refinements | C132: 0.1 | D132: no
A133: Software development | B133: Development of the software with unit test and documentation of the code | C133: 0.48 | D133: yes
A134: Deployment | B134: Deployment to the integration and productive environment | C134: 0.03 | D134: no
A135: Testing and documentation | B135: Test data generation and integration test on the INT environment | C135: 0.08 | D135: no
A136: Defects | B136: Defects elimination | C136: 0.06 | D136: no
A137: Risks | B137: Risks | C137: 0.06 | D137: no
A138: Overhead (agile meetings/pm/sm/pmo) | B138: Project overhead incl. agile meetings | C138: 0.19 | D138: no

Sheet <test_complex_en>
A1: Key | B1: Value
A2: Proposal title | B2: Test and demo project
A3: Contract type | B3: Work contract (fixed price)
A4: Customer | B4: Test customer
A5: Contractor | B5: adesso SE
A6: Calculation process | B6: Calculation with two teams
A7: Currency | B7: €
A8: Time period type | B8: 0
A9: Include inflation | B9: no
A10: No prior sorted tasks for GANTT chart | B10: yes
A11: Allocate first role efforts to other roles | B11: no
A12: FTE days | B12: 220
A13: Project length | B13: 44
A14: Team size | B14: 5
A15: Number of sprints | B15: 0
A17: Team member | B17: Team member role in proposal process
A18: Georg Wichert | B18: Calculation manager
A19: Paula Schmidt | B19: Software architect
A20: Hans Klausen | B20: Test manager
A21: Luisa Paulsen | B21: Requirement engineer
A23: Description | B23: Assumptions | C23: Costs | D23: Costs to be charged
A24: Travel costs | C24: 2000 | D24: 2000
A25: Hosting dev infrastructure | C25: 2500 | D25: 2500
A27: ID | B27: Risk title | C27: Risk description | D27: Linked items | E27: Risk likelihood | F27: Risk impact
A28: R-10 | B28: Risk A | C28: Risk A | D28: F-10,P-30 | E28: 0.27934206 | F28: 10.1
A29: R-20 | B29: Risk B | C29: Risk B | D29: F-10 | E29: 0.82460213 | F29: 7.5
A30: R-30 | B30: Risk C | C30: Risk C | D30: F-50 | E30: 0.98609316 | F30: 11
A31: R-40 | B31: Risk D | C31: Risk D | D31: P-30 | E31: 0.22686601 | F31: 8.6000004
A32: R-50 | B32: Risk E | C32: Risk E | D32: P-120 | E32: 0.98000324 | F32: 3.7
A33: R-60 | B33: Risk F | C33: Risk F | E33: 0.53387308 | F33: 2.2
A34: R-70 | B34: Risk G | C34: Risk G | E34: 0.99941456 | F34: 8.3999996
A36: ID | B36: Task group | C36: Summary task | D36: Task | E36: Description | F36: Special task or feature query | G36: Assumptions | H36: Reference ID | I36: Effort | J36: Variable | K36: Formula | L36: Start | M36: Finish | N36: Duration | O36: Dependency | P36: GANTT | Q36: Role 1 | R36: Role 2 | S36: Role 3 | T36: Role 4 | U36: Role 5 | V36: Role 6 | W36: Role 7 | X36: Role 8 | Y36: Role 9 | Z36: Role 10 | AA36: Role 11 | AB36: Role 12 | AC36: Role 13 | AD36: Role 14 | AE36: Role 15 | AF36: Role 16 | AG36: Role 17 | AH36: Role 18 | AI36: Role 19 | AJ36: Role 20 | AK36: Role 21 | AL36: Role 22 | AM36: Role 23 | AN36: Role 24 | AO36: Role 25 | AP36: Role 26 | AQ36: Role 27 | AR36: Role 28 | AS36: Role 29 | AT36: Role 30
A37: P-10 | B37: Start | C37: Planning | D37: Project initialization and planning | E37: Initialization and planning of project; creation of a project manual, procurement of resources, setting up project controlling, etc. | I37: 4.9540612 | K37: 2%*[#total1] | L37: 45658 | M37: 45688 | N37: 1m | P37: yes | R37: f100
A38: P-20 | B38: Start | C38: Planning | D38: Project kick-off meeting | E38: Internal and if necessary external meeting, participation, preparation and follow-up | I38: 1.25 | K38: [#teamsize]*0.25 | L38: 45689 | M38: 45702 | N38: 2w | O38: aft(P-10) | P38: yes | Q38: f50 | R38: f50
A39: P-30 | B39: Start | C39: Planning | D39: Setup development environment | E39: Setup development, test and acceptance environment | I39: 5 | L39: 45658 | M39: 45688 | N39: 1m | O39: bot(P-10) | P39: yes | Y39: f100
A40: P-40 | B40: Implementation Module 1 | C40: Planning | D40: Project initialization and planning | E40: Initialization and planning of project; creation of a project manual, procurement of resources, setting up project controlling, etc. | I40: 2 | L40: 45703 | M40: 45716 | N40: 2w | O40: aft(P-20) | P40: yes | R40: f100
A41: P-50 | B41: Implementation Module 1 | C41: Planning | D41: Project kick-off meeting | E41: Internal and if necessary external meeting, participation, preparation and follow-up | I41: 1 | L41: 45717 | M41: 45723 | N41: 1w | O41: aft(P-40) | P41: yes | Q41: f50 | R41: f50
A42: P-60 | B42: Implementation Module 1 | C42: Planning | D42: Creation of software architecture concept | E42: Setting up a sustainable and stable architecture for the targeted application and documentation | I42: 2 | L42: 45703 | M42: 45730 | N42: 1m | O42: bot(P-40) | P42: yes | S42: f100
A43: P-70 | B43: Implementation Module 1 | C43: Planning | D43: Creation of test concept | E43: Creation of test concept, definition of test execution strategy and processes, preparation of test toolchain | I43: 2 | L43: 45703 | M43: 45730 | N43: 1m | O43: bot(P-40) | P43: yes | V43: f100
A44: P-80 | B44: Implementation Module 1 | C44: Implementation | D44: Analysis & software design | E44: Feature task 'Analysis & software design' | F44: FT(A)#1 | I44: 5.125 | L44: 45724 | M44: 45784 | N44: 2m | O44: aft(P-50) | P44: yes | T44: f100
A45: P-90 | B45: Implementation Module 1 | C45: Implementation | D45: Software development | E45: Feature task 'Software development' | F45: FT(A)#2 | I45: 10.25 | J45: [dev1] | L45: 45738 | M45: 45798 | N45: 2m | O45: bot(P-80)+2w | P45: yes | X45: f100
A46: P-100 | B46: Implementation Module 1 | C46: Implementation | D46: Writing user manual | E46: Writing, correction and handover of a user manual | I46: 1.025 | K46: 10%*[dev1] | L46: 45799 | M46: 45829 | N46: 1m | O46: aft(P-90) | P46: yes | T46: f100
A47: P-110 | B47: Implementation Module 1 | C47: Implementation | D47: Software test | E47: Feature task 'Software test' | F47: FT(A)#3 | I47: 3.075 | J47: [test1] | L47: 45738 | M47: 45829 | N47: 3m | O47: bot(P-90) | P47: yes | W47: f100
A48: P-120 | B48: Implementation Module 1 | C48: Implementation | D48: Development of test automation scripts | E48: Implementation and maintenance of test cases based on test concept and acceptance criteria | I48: 3.075 | K48: [test1] | L48: 45738 | M48: 45798 | N48: 2m | O48: bot(P-110) | P48: yes | W48: f20 | X48: f80
A49: P-130 | B49: Implementation Module 1 | C49: Implementation | D49: Performance test | E49: Performance test | I49: 2 | L49: 45769 | M49: 45798 | N49: 1m | O49: bot(P-110)+1m | P49: yes | S49: f20 | W49: f20 | Y49: f60
A50: P-140 | B50: Implementation Module 1 | C50: Implementation | D50: Security check | E50: Static code analysis, threat model (threat analysis); further information at security-check@adesso.de | I50: 2 | L50: 45769 | M50: 45798 | N50: 1m | O50: bot(P-130) | P50: yes | S50: f20 | Y50: f80
A51: P-150 | B51: Implementation Module 1 | C51: Implementation | D51: Bug fixing after final acceptance | E51: Feature task 'Bug fixing after final acceptance' | F51: FT(A)#4 | I51: 2.05 | L51: 45830 | M51: 45859 | N51: 1m | O51: aft(P-110) | P51: yes | W51: f20 | X51: f80
A52: P-160 | B52: Implementation Module 1 | C52: Implementation | D52: Customer training | E52: Prepare and conduct customer training courses | I52: 2 | L52: 45799 | M52: 45829 | N52: 1m | O52: bot(P-150)-1m | P52: yes | T52: f100
A53: P-170 | B53: Implementation Module 2 | C53: Planning | D53: Project initialization and planning | I53: 2 | L53: 45762 | M53: 45775 | N53: 2w | O53: bot(P-40)+2m | P53: yes | R53: f100
A54: P-180 | B54: Implementation Module 2 | C54: Planning | D54: Project kick-off meeting | I54: 1 | L54: 45776 | M54: 45782 | N54: 1w | O54: aft(P-170) | P54: yes | Q54: f50 | R54: f50
A55: P-190 | B55: Implementation Module 2 | C55: Planning | D55: Creation of software architecture concept | I55: 4 | L55: 45762 | M55: 45775 | N55: 2w | O55: bot(P-170) | P55: yes | S55: f100
A56: P-200 | B56: Implementation Module 2 | C56: Planning | D56: Creation of test concept | I56: 4 | L56: 45762 | M56: 45775 | N56: 2w | O56: bot(P-170) | P56: yes | V56: f100
A57: P-210 | B57: Implementation Module 2 | C57: Implementation | D57: Analysis & software design | E57: Feature task 'Analysis & software design' | F57: FT(B)#1 | I57: 5.075 | L57: 45783 | M57: 45813 | N57: 1m | O57: aft(P-180) | P57: yes | T57: f100
A58: P-220 | B58: Implementation Module 2 | C58: Implementation | D58: Software development | E58: Feature task 'Software development' | F58: FT(B)#2 | I58: 10.15 | J58: [dev2] | L58: 45821 | M58: 45850 | N58: 1m | O58: aft(P-210)+1w | P58: yes | X58: f100
A59: P-230 | B59: Implementation Module 2 | C59: Implementation | D59: Writing user manual | I59: 1.015 | K59: 10%*[dev2] | L59: 45851 | M59: 45864 | N59: 2w | O59: aft(P-220) | P59: yes | T59: f100
A60: P-240 | B60: Implementation Module 2 | C60: Implementation | D60: Software test | E60: Feature task 'Software test' | F60: FT(B)#3 | I60: 3.045 | J60: [test2] | L60: 45821 | M60: 45881 | N60: 2m | O60: bot(P-220) | P60: yes | W60: f100
A61: P-250 | B61: Implementation Module 2 | C61: Implementation | D61: Development of test automation scripts | I61: 3.045 | K61: [test2] | L61: 45821 | M61: 45850 | N61: 1m | O61: bot(P-240) | P61: yes | W61: f20 | X61: f80
A62: P-260 | B62: Implementation Module 2 | C62: Implementation | D62: Performance test | I62: 2 | L62: 45835 | M62: 45848 | N62: 2w | O62: bot(P-240)+2w | P62: yes | S62: f20 | Y62: f80
A63: P-270 | B63: Implementation Module 2 | C63: Implementation | D63: Security check | I63: 2 | L63: 45835 | M63: 45848 | N63: 2w | O63: bot(P-260) | P63: yes | S63: f20 | Y63: f80
A64: P-280 | B64: Implementation Module 2 | C64: Implementation | D64: Bug fixing after final acceptance | E64: Feature task 'Bug fixing after final acceptance' | F64: FT(B)#4 | I64: 2.03 | L64: 45882 | M64: 45912 | N64: 1m | O64: aft(P-240) | P64: yes | W64: f20 | X64: f80
A65: P-290 | B65: Implementation Module 2 | C65: Implementation | D65: Customer training | I65: 2 | L65: 45851 | M65: 45881 | N65: 1m | O65: bot(P-280)-1m | P65: yes | T65: f100
A66: P-300 | B66: Implementation Module 3+4 | C66: Planning | D66: Project initialization and planning | I66: 2 | L66: 45792 | M66: 45805 | N66: 2w | O66: bot(P-170)+1m | P66: yes | R66: f100
A67: P-310 | B67: Implementation Module 3+4 | C67: Planning | D67: Project kick-off meeting | I67: 1 | L67: 45806 | M67: 45812 | N67: 1w | O67: aft(P-300) | P67: yes | Q67: f50 | R67: f50
A68: P-320 | B68: Implementation Module 3+4 | C68: Planning | D68: Creation of software architecture concept | I68: 4 | L68: 45792 | M68: 45822 | N68: 1m | O68: bot(P-300) | P68: yes | S68: f100
A69: P-330 | B69: Implementation Module 3+4 | C69: Planning | D69: Creation of test concept | I69: 2 | L69: 45792 | M69: 45822 | N69: 1m | O69: bot(P-300) | P69: yes | V69: f100
A70: P-340 | B70: Implementation Module 3+4 | C70: Implementation | D70: Analysis & software design | E70: Feature task 'Analysis & software design' | F70: FT(C)#1 | I70: 13.625 | L70: 45813 | M70: 45873 | N70: 2m | O70: aft(P-310) | P70: yes | T70: f100
A71: P-350 | B71: Implementation Module 3+4 | C71: Implementation | D71: Software development | E71: Feature task 'Software development' | F71: FT(C)#2 | I71: 27.25 | J71: [dev3] | L71: 45843 | M71: 45904 | N71: 2m | O71: aft(P-340)-1m | P71: yes | X71: f100
A72: P-360 | B72: Implementation Module 3+4 | C72: Implementation | D72: Writing user manual | I72: 2.725 | K72: 10%*[dev3] | L72: 45905 | M72: 45934 | N72: 1m | O72: aft(P-350) | P72: yes | T72: f100
A73: P-370 | B73: Implementation Module 3+4 | C73: Implementation | D73: Software test | E73: Feature task 'Software test' | F73: FT(C)#3 | I73: 8.1750001 | J73: [test3] | L73: 45843 | M73: 45934 | N73: 3m | O73: bot(P-350) | P73: yes | W73: f100
A74: P-380 | B74: Implementation Module 3+4 | C74: Implementation | D74: Development of test automation scripts | I74: 8.1750001 | K74: [test3] | L74: 45843 | M74: 45904 | N74: 2m | O74: bot(P-370) | P74: yes | W74: f20 | X74: f80
A75: P-390 | B75: Implementation Module 3+4 | C75: Implementation | D75: Performance test | I75: 2 | L75: 45874 | M75: 45904 | N75: 1m | O75: bot(P-370)+1m | P75: yes | S75: f20 | Y75: f80
A76: P-400 | B76: Implementation Module 3+4 | C76: Implementation | D76: Security check | I76: 2 | L76: 45874 | M76: 45904 | N76: 1m | O76: bot(P-390) | P76: yes | S76: f20 | Y76: f80
A77: P-410 | B77: Implementation Module 3+4 | C77: Implementation | D77: Bug fixing after final acceptance | E77: Feature task 'Bug fixing after final acceptance' | F77: FT(C)#4 | I77: 5.45 | L77: 45935 | M77: 45965 | N77: 1m | O77: aft(P-370) | P77: yes | W77: f20 | X77: f80
A78: P-420 | B78: Implementation Module 3+4 | C78: Implementation | D78: Customer training | I78: 2 | L78: 45905 | M78: 45934 | N78: 1m | O78: bot(P-410)-1m | P78: yes | T78: f100
A79: P-430 | B79: Overall tasks | C79: Overall tasks | D79: Project management | E79: Project management and control, resource, stakeholder, risk and escalation management, planning updates, etc. Test management Comprehensive test management etc. | I79: 44 | K79: max([#projectlength]*ifs([#total1]<200,0.5,[#total1]<500,1,[#total1]<1000,1.5,[#total1]<2000,2,true,3),10%*[#total1]) | L79: 45658 | M79: 45965 | N79: 44w | O79: bot(P-10) | P79: yes | R79: f100
A80: P-440 | B80: Overall tasks | C80: Overall tasks | D80: Test management | E80: Comprehensive test and quality management | I80: 2.859 | K80: 20%*([test1]+[test2]+[test3]) | L80: 45658 | M80: 45965 | N80: 44w | O80: bot(P-10) | P80: yes | V80: f100
A81: P-450 | B81: Overall tasks | C81: Overall tasks | D81: Software architecture management | E81: Comprehensive software architecture management | I81: 10 | L81: 45658 | M81: 45965 | N81: 44w | O81: bot(P-10) | P81: yes | S81: f100
A82: P-460 | B82: Overall tasks | C82: Overall tasks | D82: DevOps support | E82: Comprehensive DevOps support | I82: 9.5300001 | K82: 20%*([dev1]+[dev2]+[dev3]) | L82: 45658 | M82: 45965 | N82: 44w | O82: bot(P-10) | P82: yes | Y82: f100
A83: P-470 | B83: Overall tasks | C83: Overall tasks | D83: Project meetings | E83: Meetings > 1 hour, e.g. for Scrum events or similar | I83: 10 | L83: 45658 | M83: 45965 | N83: 44w | O83: bot(P-10) | P83: yes | Q83: f100
A84: P-480 | B84: Overall tasks | C84: Overall tasks | D84: Travel times | F84: TT | I84: 10 | J84: [traveltime] | L84: 45658 | M84: 45965 | N84: 44w | O84: bot(P-10) | P84: yes | Q84: f100
A85: P-490 | B85: Overall tasks | C85: Overall tasks | D85: Risks | F85: RIS | I85: 34.999558 | J85: [risks] | L85: 45658 | M85: 45965 | N85: 44w | O85: bot(P-10) | P85: yes | Q85: f100
A86: P-500 | B86: Warranty | C86: Warranty | D86: Warranty | F86: WA | I86: 24.770306 | J86: [warranty] | K86: 10%*[#total1] | L86: 45966 | M86: 46146 | N86: 6m | O86: aft(P-410) | P86: no | Q86: f100
A88: Seniority Level
A89: any
A90: very low
A91: low
A92: middle
A93: high
A94: very high
A96: Location
A97: any
A98: Onsite
A99: Offsite
A100: On-/Offsite
... A102: Offshore
A104: Company | B104: Accounting-related company
A105: any | B105: no
A106: adesso SE | B106: yes
A107: adesso as a service | B107: no
A108: adesso Austria | B108: no
...

Sheet <test_simple_en>
A1: Key | B1: Value
A2: Proposal title | B2: Test project
A3: Contract type | B3: Work contract (fixed price)
A4: Customer | B4: Test customer
A5: Contractor | B5: adesso SE
A6: Calculation process | B6: Calculation with two teams
A7: Currency | B7: €
A8: Time period type | B8: 0
A9: Include inflation | B9: no
A10: No prior sorted tasks for GANTT chart | B10: yes
A11: Allocate first role efforts to other roles | B11: no
A12: FTE days | B12: 220
A13: Project length | B13: 58
A14: Team size | B14: 4
A15: Number of sprints | B15: 0
A17: Team member | B17: Team member role in proposal process
A18: Lieschen Müller | B18: Project and calculation manager
A19: Fritz Paulsen | B19: Software architect
A20: Hannes Hinrichs | B20: Test manager
A21: Sarah Schmidt | B21: Requirement engineer
A22: Pauline Harms | B22: Developer
A24: Description | B24: Assumptions | C24: Costs | D24: Costs to be charged
A25: Travel Costs | C25: 2000 | D25: 2000
A26: Licences for Tools | C26: 1000 | D26: 1000
A28: ID | B28: Risk title | C28: Risk description | D28: Linked items | E28: Risk likelihood | F28: Risk impact
A29: R-10 | B29: Risk A | C29: Risk A | D29: F-10,F-60,P-40 | E29: 0.29577285 | F29: 5.1999998
A30: R-20 | B30: Risk B | C30: Risk B | D30: F-60 | E30: 0.30097049 | F30: 11.4
A31: R-30 | B31: Risk C | C31: Risk C | D31: P-30 | E31: 0.97982937 | F31: 5.4000001
A32: R-40 | B32: Risk D | C32: Risk D | D32: P-40 | E32: 0.27827996 | F32: 2.8
A33: R-50 | B33: Risk E | C33: Risk E | E33: 0.16282159 | F33: 8.1000004
A34: R-60 | B34: Risk F | C34: Risk F | E34: 0.41007322 | F34: 5.5
A36: ID | B36: Task group | C36: Summary task | D36: Task | E36: Description | F36: Special task or feature query | G36: Assumptions | H36: Reference ID | I36: Effort | J36: Variable | K36: Formula | L36: Start | M36: Finish | N36: Duration | O36: Dependency | P36: GANTT | Q36: Role 1 | R36: Role 2 | S36: Role 3 | T36: Role 4 | U36: Role 5 | V36: Role 6 | W36: Role 7 | X36: Role 8 | Y36: Role 9 | Z36: Role 10 | AA36: Role 11 | AB36: Role 12 | AC36: Role 13 | AD36: Role 14 | AE36: Role 15 | AF36: Role 16 | AG36: Role 17 | AH36: Role 18 | AI36: Role 19 | AJ36: Role 20 | AK36: Role 21 | AL36: Role 22 | AM36: Role 23 | AN36: Role 24 | AO36: Role 25 | AP36: Role 26 | AQ36: Role 27 | AR36: Role 28 | AS36: Role 29 | AT36: Role 30
A37: P-10 | C37: Planning | D37: Project initialization and planning | E37: Initialization and planning of project; creation of a project manual, procurement of resources, setting up project controlling, etc. | I37: 3 | K37: 10%*[pm] | L37: 45658 | M37: 45688 | N37: 1m | P37: yes | R37: f100
A38: P-20 | C38: Planning | D38: Project kick-off meeting | E38: Internal and if necessary external meeting, participation, preparation and follow-up | I38: 2 | L38: 45689 | M38: 45702 | N38: 2w | O38: aft(P-10) | P38: yes | R38: f100
A39: P-30 | C39: Planning | D39: Creation of software architecture concept | E39: Setting up a sustainable and stable architecture for the targeted application and documentation | I39: 2 | L39: 45703 | M39: 45716 | N39: 2w | O39: aft(P-20) | P39: yes | S39: f100
A40: P-40 | C40: Planning | D40: Creation of test concept | E40: Creation of test concept, definition of test execution strategy and processes, preparation of test toolchain | I40: 2 | L40: 45703 | M40: 45716 | N40: 2w | O40: aft(P-20) | P40: yes | V40: f100
A41: P-50 | C41: Implementation | D41: Setup development environment | E41: Setup development, test and acceptance environment | I41: 2 | L41: 45703 | M41: 45716 | N41: 2w | O41: aft(P-20) | P41: yes | Y41: f100
A42: P-60 | C42: Implementation | D42: Analysis & software design | E42: Feature task 'Analysis & software design' | F42: FT#1 | I42: 57.625 | L42: 45703 | M42: 45761 | N42: 2m | O42: aft(P-20) | P42: yes | S42: f20 | T42: f80
A43: P-70 | C43: Implementation | D43: Software development | E43: Feature task 'Software development' | F43: FT#2 | I43: 115.25 | J43: [dev] | L43: 45717 | M43: 45838 | N43: 4m | O43: bot(P-60)+2w | P43: yes | X43: f100
A44: P-80 | C44: Implementation | D44: Software test | E44: Feature task 'Software test' | F44: FT#3 | I44: 34.575 | J44: [test] | L44: 45731 | M44: 45852 | N44: 4m | O44: bot(P-70)+2w | P44: yes | W44: f100
A45: P-90 | C45: Implementation | D45: Performance test | E45: Performance test | I45: 2 | L45: 45823 | M45: 45852 | N45: 1m | O45: aft(P-80)-1m | P45: yes | S45: f20 | Y45: f80
A46: P-100 | C46: Implementation | D46: Security check | E46: Static code analysis, threat model (threat analysis); further information at security-check@adesso.de | I46: 2 | L46: 45823 | M46: 45852 | N46: 1m | O46: aft(P-80)-1m | P46: yes | S46: f20 | Y46: f80
A47: P-110 | C47: Implementation | D47: Writing user manual | E47: Writing, correction and handover of a user manual | I47: 11.525 | K47: 10%*[dev] | L47: 45823 | M47: 45852 | N47: 1m | O47: aft(P-80)-1m | P47: yes | T47: f100
A48: P-120 | C48: Implementation | D48: Customer training | E48: Prepare and conduct customer training courses | I48: 4 | L48: 45823 | M48: 45852 | N48: 1m | O48: bot(P-130)-1m | P48: yes | T48: f100
A49: P-130 | C49: Closing | D49: Bug fixing after delivery for acceptance | E49: Feature task 'Bug fixing after delivery for acceptance' | F49: FT#4 | I49: 23.05 | J49: [bugfix] | L49: 45853 | M49: 45883 | N49: 1m | O49: aft(P-80) | P49: yes | W49: f20 | X49: f80
A50: P-140 | C50: Overall tasks | D50: Project management | E50: Project management and control, resource, stakeholder, risk and escalation management, planning updates, etc. Test management Comprehensive test management etc. | I50: 58 | J50: [pm] | K50: max([#projectlength]*ifs([#total1]<200,0.5,[#total1]<500,1,[#total1]<1000,1.5,[#total1]<2000,2,true,3),10%*[#total1]) | L50: 45658 | M50: 45883 | N50: 226d | O50: bot(P-10) | P50: yes | R50: f100
A51: P-150 | C51: Overall tasks | D51: Test management | E51: Comprehensive test and quality management | I51: 5 | L51: 45658 | M51: 45883 | N51: 226d | O51: bot(P-10) | P51: yes | V51: f100
A52: P-160 | C52: Overall tasks | D52: Software architecture management | E52: Comprehensive software architecture management | I52: 5 | L52: 45658 | M52: 45883 | N52: 226d | O52: bot(P-10) | P52: yes | S52: f100
A53: P-170 | C53: Overall tasks | D53: Project meetings | E53: Meetings > 1 hour, e.g. for Scrum events or similar | I53: 5 | L53: 45658 | M53: 45883 | N53: 226d | O53: bot(P-10) | P53: yes | Q53: f100
A54: P-180 | C54: Overall tasks | D54: Travel times | F54: TT | I54: 5 | J54: [traveltime] | L54: 45658 | M54: 45883 | N54: 226d | O54: bot(P-10) | P54: yes | Q54: f100
A55: P-190 | C55: Overall tasks | D55: Risks | F55: RIS | I55: 14.613603 | J55: [risks] | L55: 45658 | M55: 45883 | N55: 226d | O55: bot(P-10) | P55: yes | Q55: f100
A56: P-200 | C56: Warranty | D56: Warranty | F56: WA | I56: 33.4025 | J56: [warranty] | K56: 10%*[#total1] | L56: 45884 | M56: 46067 | N56: 6m | O56: aft(P-130) | P56: yes | Q56: f100
A58: Seniority Level
A59: any
A60: very low
A61: low
A62: middle
A63: high
A64: very high
A66: Location
A67: any
A68: Onsite
A69: Offsite
A70: On-/Offsite
... A72: Offshore
A74: Company | B74: Accounting-related company
A75: any | B75: no
A76: adesso SE | B76: yes
A77: adesso as a service | B77: no
A78: adesso Austria | B78: no
A79: adesso benefit solutions | B79: no
A80: adesso Bulgaria | B80: no
A81: adesso Finland | B81: no
A82: adesso health solutions | B82: no
A83: adesso Hungary | B83: no
A84: adesso India | B84: no
A85: adesso insurance solutions | B85: yes
... A108: Country | B108: Inflation rate
A109: any | B109: 0.02
A110: Germany | B110: 0.02
A111: Austria | B111: 0.035
A112: Bulgaria | B112: 0.03
A113: Finland | B113: 0.015
A114: Hungary | B114: 0.035
A115: India | B115: 0.055
A116: Italy | B116: 0.015
A117: Netherlands | B117: 0.025
A118: Romania | B118: 0.06
A119: Spain | B119: 0.025
A120: Sweden | B120: 0.025
... A122: Turkey | B122: 0.5
A124: Project role | B124: Sub role | C124: Percentage | D124: Company | E124: Country | F124: Location | G124: Seniority Level | H124: Daily costs | I124: Daily rate | J124: Daily costs (travel time) | K124: Daily rate (travel time)
A125: Any role | B125: Any role | C125: 1 | D125: adesso SE | E125: any | F125: any | G125: any | H125: 500 | I125: 900 | J125: 500 | K125: 450
A126: Project manager | B126: Project manager | C126: 1 | D126: adesso SE | E126: any | F126: any | G126: high | H126: 500 | I126: 900 | J126: 500 | K126: 450
A127: Project manager | B127: Project Office | C127: 0 | D127: adesso SE | E127: any | F127: any | G127: middle | H127: 500 | I127: 900 | J127: 500 | K127: 450
A128: Software architect | B128: Software Architect | C128: 1 | D128: adesso SE | E128: any | F128: any | G128: high | H128: 500 | I128: 900 | J128: 500 | K128: 450
A129: Requirement Engineer | B129: Requirement Engineer (Junior) | C129: 0 | D129: adesso SE | E129: any | F129: any | G129: low | H129: 500 | I129: 900 | J129: 500 | K129: 450
A130: Requirement Engineer | B130: Requirement Engineer (Middle) | C130: 1 | D130: adesso SE | E130: any | F130: any | G130: middle | H130: 500 | I130: 900 | J130: 500 | K130: 450
A131: Requirement Engineer | B131: Requirement Engineer (Senior) | C131: 0 | D131: adesso SE | E131: any | F131: any | G131: high | H131: 500 | I131: 900 | J131: 500 | K131: 450
A132: UI/UX Designer | B132: UI/UX Designer (Junior) | C132: 0 | D132: adesso SE | E132: any | F132: any | G132: low | H132: 500 | I132: 900 | J132: 500 | K132: 450
...

Sheet (Calc teams efforts)
A1: Calc teams efforts
A3: Team | B3: Item ID | C3: Value type | D3: Column | E3: Value

Sheet (Lists)
A1: Non-editable lists
A3: Worksheet "Start" | C3: Worksheet "Features" | E3: Worksheet "Project Tasks"
A5: Contract type | C5: Estimation method | E5: None-dynamic table:
A6: Work contract (fixed price) | C6: No specific method | E6: Special tasks
A7: Work contract (T&M) | C7: T-shirt sizing | E7: OPT
A8: Service contract (fixed price) | C8: Three-point estimation | E8: CUS
A9: Service contract (T&M) | C9: Planning poker | E9: WA
E10: TT
A11: Calculation process | C11: Input assistance | E11: RIS
A12: Calculation with one team | C12: No assistance | E12: FT#1
A13: Calculation with two teams | C13: Auto-fill blank cells | E13: FT#2
C14: Auto fill all cells (with override) | E14: FT#3
E15: FT#4
C16: T-shirt size
C17: XS
C18: S
C19: M
C20: L
C21: XL
C23: Story points
C24: 1
C25: 2
C26: 3
C27: 5
C28: 8
C29: 13
C30: 20
C31: 40
C32: 100 | E32: Start-Messages

Sheet (Options)
A1: Options
B2: Use menu above "Edit options":
A3: Currency: | B3: €
A4: Period type: | B4: 0
A5: Include inflation: | B5: no
A6: No prior sorted tasks for GANTT chart: | B6: yes
A7: Allocate first role efforts to other roles: | B7: no
A8: Capacity of one person (1 FTE): | B8: 220
A11: Admin mode: | B11: no
A12: Admin password: | B12: adcalc
A13: Link manual: | B13: https://o365adessogroup.sharepoint.com/sites/adesso_FU-ProjectManagement/SitePages/adesso-calculator.aspx
A14: Link manual (German): | B14: https://o365adessogroup.sharepoint.com/sites/adesso_FU-ProjectManagement/SitePages/de/adesso-calculator.aspx
A15: Chapter "Table of contens": | B15: #table-of-contents
A16: Link Teams channel: | B16: https://teams.microsoft.com/l/channel/19%3AtrMFhwN4ldM7sKA4KzSg3KGofZOCDNi6TzOMqlo-DLs1%40thread.tacv2/Start?groupId=0ed5a4b1-b300-4f1b-a886-fe17662e44f9&tenantId=3d355765-67d9-47cd-9c7a-bf31179f56eb

Sheet (Start Error Message)
A1: Start error message (if macros are deactivated)

Sheet (Quick guide)
A1: Quick guide
A3: Topic | B3: Show again | C3: Sheet
A4: Introduction | B4: any | C4: any
A5: Rules | B5: any | C5: any
A6: Advanced options | B6: any | C6: any
A7: Basic settings | B7: yes | C7: Start
A8: Features | B8: yes | C8: Features
A9: Project tasks | B9: yes | C9: Project tasks
A10: Creating formulas | B10: yes | C10: any
A11: Project risks | B11: yes | C11: Project risks
A12: Project roles | B12: yes | C12: Project roles
A13: Other costs | B13: yes | C13: Other costs
A14: Change history | B14: yes | C14: Change history
... A23: Risks Chart | B23: yes | C23: Chart | Risks
A25: Topic | B25: Sys | C25: Title | D25: Message | E25: Further Topic | F25: Manual Chapter
A26: Introduction | B26: any | C26: Welcome to adesso calculator! | D26: Welcome to adesso calculator Tool! _x000D_ _x000D_ This quick guide will help you get started, but it does not replace the detailed manual, which you should read first (click button "Manual")._x000D_ _x000D_ Use the button "< Prev" to navigate to the previous page and the button "Next >" to navigate to the next page. For each worksheet there is a context-related quick guide that is automatically displayed when you select this worksheet. You can call up these instructions again at any time in the menu above ‘Show quick guide’ in the help section._x000D_ _x000D_ Green buttons indicate further information. If the "Manual" button is green, the relevant chapter of the manual is displayed directly when you click on this button. Otherwise, the table of contents of the manual will be displayed. | F26: #quick-guides
A27: Introduction | B27: any | C27: We need to have some rules! | D27: Without appropriate rules for this Excel application, there is a risk that the adesso calculator will stop working at some point._x000D_ _x000D_ You cannot enter data in all places or insert additional columns at will - so please observe the rules and read the manual carefully!_x000D_ _x000D_ Click on the ‘Topic: Rules’ button below. | E27: Rules | F27: #input-rules-and-working-with-tables
A28: Introduction | B28: win | C28: Menu bar 'adesso calculator' | D28: Please have a look at the menu bar ‘adesso calculator’. This contains important functions that will make your work easier._x000D_ _x000D_ A few overall functions: _x000D_ _x000D_ "Go to sheet": Select a worksheet that you specifically want to switch to._x000D_ "Reset sheet": Reset a worksheet to its original state._x000D_ "Show manual": Display this user documentation._x000D_ "Show quick guide": Show a quick guide to the selected worksheet._x000D_ "Show version information": Displays the current version. | F28: #menu-bar
A29: Introduction | B29: mac | C29: Menu bar 'adesso calculator' | D29: Please have a look at the menu bar ‘adesso calculator’. This contains important functions that will make your work easier. MAC OS Excel doesn't support all features of Windows Excel (see next page). Unfortunately some icons in the menu bar are displayed as a round circle.
A30: Introduction | B30: mac | C30: Restrictions for MAC OS | D30: There are some restrictions for you as a MAC user. Microsoft Excel unfortunately behaves differently under MAC OS than under Windows: a) Some icons in the menu bar are displayed as a round circle. b) You are asked to enter a file name (incl. folder) for import and export functions. A selection dialogue is only available for Windows users. Please use the button "Paste" to get text from the clipboard. c) The key combination for inserting table rows is ‘Control Shift +’ and for removing rows ‘Control Shift + ’. d) Microsoft Project is not available for MAC OS. Therefore you can't export data to this application.
A31: Introduction | B31: any | C31: Additional notes in worksheets! | D31: Note the many additional help informations in the worksheets. These notes give you further tips for the application.
A32: Introduction | B32: any | C32: Calculation process | D32: If the total effort is expected to exceed 100 days, adesso always involves two estimation teams. For offers of less than 100 days, only one estimation team is involved. In this case, the "Inquistion" sub-process is also omitted._x000D_ _x000D_ In the sub-process "Preparation", the entire team sets up the project structure, the feature list and the risk list. The aim of this first sub-process is to gain a common understanding of the scope of services as a basis for the calculation._x000D_ _x000D_ In the sub-processes "Calculation first team" and "Calculation second team", the entire team is divided into two estimation teams. Each team calculates (estimates) the cost of the previously defined tasks, features and risks independently of each other._x000D_ _x000D_ In the "Inquisition" sub-process, the entire team is brought back together at one table. The estimates of the two teams are compared and discussed. The result of this inquisition is recorded._x000D_ _x000D_ In the "Finalization" sub-process, the calculation manager adds all other information, such as roles, scheduling, costs and prices, and thus creates an initial draft of the entire cost estimate for the quotation manager._x000D_ _x000D_ _x000D_ | F32: #calculation-process
A33: Rules | B33: any | C33: We need to have some rules! | D33: 1. You may only enter data in cells with a yellow background!_x000D_ _x000D_ 2. Insert rows or delete rows only in tables with a yellow background! (see next pages)_x000D_ _x000D_ 3. Do not insert, delete or rearrange any columns!_x000D_ _x000D_ 4. Do not sort or change any tables!_x000D_ _x000D_ 5. Do not change any formulas, if they are not contained as default values in the yellow fields mentioned above! In this case you can replace the formulas by concrete values._x000D_ _x000D_ 6. Do not rename any worksheets!_x000D_ _x000D_ 7. Please read the manual if you are unsure how to use this tool. | F33: #input-rules-and-working-with-tables
A34: Rules | B34: any | C34: Working in tables | D34: There are two types of tables in this tool, which are handled differently._x000D_ _x000D_ Dynamic tables (e.g. in “Start”, “History of changes” or “Companies” worksheets)_x000D_ _x000D_ Smart tables (e.g. in worksheets "Features", "Project tasks", "Project roles", "Project risks")_x000D_ _x000D_ Both types of table are explained on the following pages. | F34: #input-rules-and-working-with-tables
A35: Rules | B35: any | C35: Dynamic tables | D35: The tool uses dynamic tables for example in the worksheets “Start”, “History of changes” or “Companies” ._x000D_ _x000D_ You can add new rows by using the tab key in the last column of the last row._x000D_ _x000D_ You can also insert rows. To do this, use the context menu (right mouse button). | F35: #input-rules-and-working-with-tables
A36: Rules | B36: win | C36: Smart tables | D36: The tool uses smart tables for example in the worksheets "Features", "Project tasks", "Project roles" and "Project risks"._x000D_ _x000D_ A smart table contains very complex tables with many, sometimes time-consuming calculation logics and formulas._x000D_ _x000D_ You only insert a row via the menu item "Insert row" or use the key combination CTRL + (Windows)._x000D_ You only delete a row via the menu item "Delete row" or use the key combination CTRL - (Windows)._x000D_ You only move a row via the menu item "Move row"._x000D_ _x000D_ Please consider the restrictions in the worksheets "Project roles" and "Other costs"._x000D_ _x000D_ You may only enter or change data in the cells with a yellow background color! | F36: #input-rules-and-working-with-tables
A37: Rules | B37: mac | C37: Smart tables | D37: The tool uses smart tables for example in the worksheets "Features", "Project tasks", "Project roles" and "Project risks". A smart table contains very complex tables with many, sometimes time-consuming calculation logics and formulas. You only insert a row via the menu item "Insert row" or use the key combination Control + (MAC: Control Shift = ). You only delete a row via the menu item "Delete row" or use the key combination Control -. You only move a row via the menu item "Move row". Please consider the restrictions in the worksheets "Project roles" and "Other costs". You may only enter or change data in the cells with a yellow background color!
A38: Rules | B38: any | C38: Smart table: Unique IDs | D38: In the smart tables, unique IDs are required as these are referenced._x000D_ _x000D_ The IDs are permanently assigned in the "Other costs" table. They are processed internally in the "Project roles" table._x000D_ _x000D_ In the "Features", "Project tasks" and "Project risks" tables, you can either assign these IDs manually or leave the assignment of the IDs to the adesso calculator. Make sure that each row has a unique ID. You can also overwrite the suggested IDs with your own IDs. Remember that the IDs may reference each other (e.g. a risk refers to a task or the start date of a task depends on the finish date of a predecessor task)._x000D_ _x000D_ Also note that features must always start with "F-", project tasks with "P-" and risks with "R-". This is always followed by a whole number._x000D_ _x000D_ If the IDs are completely mixed up, you can use the menu item "Renumber IDs" to have them renumbered automatically. adesso calculator also adjusts the corresponding relationships. | F38: #input-rules-and-working-with-tables
A39: Advanced options | B39: any | C39: Basic options | D39: Enter the currency that is the basis for calculating the offer in the “Currency” field._x000D_ _x000D_ In the “FTE” field, the capacity of a resource working full-time (full-time equivalent) is entered (days per year).
A40: Advanced options | B40: any | C40: Calculation options | D40: “costs calculation includes inflation rates” ensures that inflation over the specified period is taken into account when calculating the costs of a task._x000D_ _x000D_ In the worksheet ‘Project Roles’, the respective countries must be assigned for all roles. In addition, you must update the current inflation rates in the worksheet ‘Country’._x000D_ _x000D_ Use the “time period type” field (see next page) to control whether inflation is calculated weekly, monthly or annually. | E40: Project roles
A41: Advanced options | B41: any | C41: Report & Chart options | D41: The "Time period type" option is used in reports and charts that use periods (including the GANTT chart). This option also controls the calculation of inflation._x000D_ _x000D_ The option "GANTT chart without prior sorted project tasks" is used for the worksheet "Chart | GANTT". If this option is not checked, then all tasks and parent elements are sorted for the GANTT chart._x000D_ _x000D_ If you want to distribute the "Any role" to the other roles, you must activate the option "Allocate first role efforts to other roles". In the "Project roles" worksheet and in reports and charts that evaluate roles, the effort for "Any Role" is finally 0 days._x000D_ _x000D_ _x000D_ _x000D_
A42: Basic settings | B42: any | C42: Enter basic data for project! | D42: Enter the basic data for this project in this worksheet._x000D_ _x000D_ Please remember the rules! (click on the ‘Rules’ button below)._x000D_ _x000D_ For the contract type and the associated billing type, however, you should check exactly which selection is best for your project. If you have to produce and deliver something for the customer, this is a wotk contract. If you only provide human resources who produce something under the customer's direction, it is usually a service contract. Still unsure? Then the "adesso Projektfibel" will help you!_x000D_ _x000D_ The correct selection of the contractor is important for the gross profit calculation (see worksheet 'Project roles' and 'Summary'). | E42: Rules | F42: #preparation-basic-settings
A43: Basic settings | B43: any | C43: Choose a template! | D43: A calculation template contains a predefined project structure that you can use for your calculation._x000D_ _x000D_ Select a template via the menu item "Import" --> "Import from internal template" and decide in the dialog which data you want to use. | F43: #preparation-basic-settings
A44: Basic settings | B44: any | C44: Choose the calculation process! | D44: If you need to estimate a small project (< 100 PT), then one estimation team is sufficient, so in this case you choose "Calculation with one team". For larger projects, choose "Calculation with two teams"._x000D_ _x000D_ Make sure that the process step in the menu bar is set to "Preparation" (this should be the default). | F44: #preparation-basic-settings
A45: Basic settings | B45: any | C45: adesso calculation team | D45: In the table "adesso calculation team" you enter all employees who are fully or partially involved in the calculation process._x000D_ _x000D_ This information is very helpful for the understanding of third parties who were involved in the process! | F45: #preparation-basic-settings
A46: Basic settings | B46: any | C46: Advanced options | D46: Click on the menu item "Edit options" for advanced settings. _x000D_ _x000D_ For example, enter a different currency._x000D_ _x000D_ Click on the button below to get more information about this topic. | E46: Advanced options
A47: Features | B47: any | C47: What are features? | D47: Features are delivery items that we produce for our customers (e.g. software features). They usually relate to requirements from a customer or supplier specification._x000D_ _x000D_ The production process goes through certain stages, which we call “feature tasks”. You can customize these feature tasks at any time using the menu item “Edit feature tasks” menu._x000D_ _x000D_ It is helpful for the later calculation if you establish a common estimate of the percentage distribution of the feature tasks. | F47: #preparation-feature-list
A48: Features | B48: any | C48: Preparation | D48: In the “Preparation” process step, the feature tasks (use the "Edit feature task" menu item) are defined and all features are entered in the table. You can also document assumptions and capture risks (use the “Add risk” menu item)._x000D_ _x000D_ When entering data, please note the input rules (click on the button below to get more information about this topic)._x000D_ _x000D_ Please refer to the manual for information on the individual columns._x000D_ _x000D_ Efforts are not yet calculated in this process step. | E48: Rules | F48: #preparation-feature-list
A49: Features | B49: any | C49: Calculation: Estimation methods | D49: There are a number of ways that adesso calculator offers you to estimate and record efforts. Please select the method in the selection field:_x000D_ _x000D_ a) Expert estimation without help_x000D_ b) Expert estimation with input support - an accelerated method_x000D_ c) T-shirt sizing - using comparisons to arrive at estimates_x000D_ d) Planning Poker - the method for agilists_x000D_ e) Three Point Estimation_x000D_ _x000D_ These methods are explained in detail in the manual! | F49: #calculation-features-calculation
A50: Features | B50: any | C50: Calculation: Input assistance | D50: adesso calculator can relieve you of a little paperwork and help your estimation team to concentrate on the essentials first. In the selection list "Input Assistance for task values", select the option "Auto-fill blank cells". At least one column header of the feature tasks should then have a red background color. This highlighted feature task is the "key task"._x000D_ _x000D_ You will initially only focus on this key task in your effort estimation. You only enter the estimated feature task values in the corresponding column. The other feature tasks are calculated according to the forecasted percentages and automatically entered by adesso calculator._x000D_ _x000D_ You can, of course, veto any pre-assignment of the other feature task values. You can then adjust these values accordingly._x000D_ _x000D_ If there are already values in the respective columns, these are not overwritten. If these values are to be overwritten, you must first select the "Auto fill all cells (with override)" assistance. | F50: #calculation-features-calculation
A51: Project tasks | B51: any | C51: Overview | D51: This table contains the following column groups:_x000D_ _x000D_ 1. Description of a task (columns "ID" to "Ref. ID") _x000D_ 2. Calculation of a task (columns "Effort" to "Result of formula")_x000D_ 3. Scheduling a task (column "Start" to "Show in GANTT?") _x000D_ 4. Distribution of expenses to the individual roles (from "Not allocated effort" column)_x000D_ _x000D_ You edit group 1 in the "Preparation" sub-process, group 2 in the "Calculation" sub-process and groups 3 and 4 in the "Finalization" sub-process. Show or hide the groups accordingly (see +/- above the title of the worksheet).
A52: Project tasks | B52: any | C52: Preparation: Work breakdown structure | D52: In the sub-process "Preparation" you create the work breakdown structure for the project._x000D_ _x000D_ If you are using a template, you will probably already find a pre-filled "smart table" here and only need to adapt it._x000D_ _x000D_ At least the column "Task title" must be filled in. Depending on the size of the project, you can use the higher-level columns "Task group" and "Summary task" to further structure your project tasks. You enter a task description in the "Task description" template, assumptions in the "Assumptions" column and references to the specifications in the "Ref.ID" column. You create risks via the "Add risk" menu item._x000D_ _x000D_ See next page: What is a "special task"? | E52: Rules | F52: #preparation-work-breakdown-structure
A53: Project tasks | B53: any | C53: Preparation: Special tasks | D53: Certain tasks have properties that are treated as special cases for the calculation. These "Special Tasks" are entered in the column of the same name:_x000D_ _x000D_ OPT: The project task should only be offered as an option (OPT = Optional task)._x000D_ _x000D_ CUS: The project task is a contributory service that is the responsibility of the customer (CUS = Customer task)._x000D_ _x000D_ TT: The project task represents a travel time (TT = Travel time). Make sure that you define at least one project task as a special task "TT". If there is no travel time (which is only conceivable for purely remote projects), then this project task can be omitted._x000D_ _x000D_ WA: The project task represents warranty work (WA = Warranty). Make sure that you define at least one project task as a special task "WA". This project task can only be omitted if the project is not offered as a work contract but as a service contract._x000D_ _x000D_ RIS: The project task represents the risks from the "Project Risks" worksheet with the sum of the expenses from the "weighted risk impacts". Only one risk task may be created._x000D_ _x000D_ FT#number, e.g. FT#1 or FT#3: The project task represents a feature task (FT). The number refers to the column number of the feature task in the "Features" worksheet. There are extended options for a feature query (menu item "Edit feature query"). Further information can be found in the manual. | F53: #preparation-work-breakdown-structure
A54: Project tasks | B54: any | C54: Calculation | D54: Sub-process calculation:_x000D_ _x000D_ The rows, in which some columns are displayed with a white background color, already contain values ("Effort" column). These efforts are linked to the feature tasks from our previously edited feature list, among other things, and can of course no longer be overwritten._x000D_ _x000D_ Formulas have been stored for some project tasks ("Formula" column), which are of course only to be understood as suggestions. If you want to accept the result, enter "f" in the "Effort" column. In this case, the value is accepted and a "yes" is entered in the "Use formula?" column._x000D_ _x000D_ The function "Calculate tasks automatically" (see menu) takes the results from the formula calculations for all tasks for which a "yes" is entered in the "Use Formula?" column._x000D_ _x000D_ Please use this function and the formulas very carefully. adesso calculator does not know your project context and therefore only gives you an idea of the effort involved. So check the results carefully and overwrite these values accordingly if the team has a different estimate. | E54: Creating formulas | F54: #calculation-project-tasks-calculation
A55: Project tasks | B55: any | C55: Finalization: Assignment of roles | D55: Sub-process "Finalization":_x000D_ _x000D_ The efforts of the tasks are assigned to the main roles defined in the "Preparation" sub-process in the "Project tasks" worksheet._x000D_ _x000D_ You can also add, remove or rename roles in this sub-process. To do this, use the menu item "Edit roles". There should always be a role "Any role" (or similar). You will assign this role to tasks where participation is difficult to predict, e.g. travel times, risks and warranty._x000D_ _x000D_ Please transfer the value or part of the value from the "Effort" column to the role columns. You can also use "short characters" for this, which can make input easier for you:_x000D_ _x000D_ f[<percentage>] = full value ("f") or part of it ("f50" = 50% of the full value)_x000D_ r[<percentage>] = rest of value ("r") or part of it("r30" = 30% of the rest value)_x000D_ c<value> = constant value_x000D_ _x000D_ In the "Not allocated effort" column, you can see which effort has not yet been allocated to a role. Make sure that each project task is fully allocated to all roles at the end. | F55: #finalization-assignment-of-roles
A56: Project tasks | B56: any | C56: Finalization: Project scheduling | D56: Sub-process "Finalization":_x000D_ _x000D_ In the "Project tasks" worksheet, you can schedule the tasks and define the dependencies. This creates the basis for a timeline (GANTT chart), for capacity planning and for an inflation calculation. _x000D_ _x000D_ Enter a date in the "Start" column or define a dependency in the "Dependency" column:_x000D_ _x000D_ bot(<id>)[+|-<duration>[d|w|m|y]] = starts together with predecessor task_x000D_ eot(<id>)[+|-<duration>[d|w|m|y]] = starts at the end of predecessor task_x000D_ aft(<id>)[+|-<duration>[d|w|m|y]] = starts one day after the predecessor task_x000D_ _x000D_ By entering the duration in the "Duration" column, the end date is calculated in the "Finish" column. Dependent tasks are recalculated on an ongoing basis._x000D_ _x000D_ In the "Show in GANTT?" column, you specify whether this task should be displayed in the GANTT chart in the "Chart | GANTT" worksheet. | F56: #finalization-project-scheduling
